Workbook

Sheet Total
C1: LTS
A2: Sector | D2: 2023 | E2: 2024 | F2: 2025 | G2: 2026 | H2: 2027 | I2: 2028 | J2: 2029 | K2: 2030 | L2: 2031 | M2: 2032 | N2: 2033 | O2: 2034 | P2: 2035 | Q2: 2036 | R2: 2037 | S2: 2038 | T2: 2039 | U2: 2040 | V2: 2041 | W2: 2042 | X2: 2043 | Y2: 2044 | Z2: 2045 | AA2: 2046 | AB2: 2047 | AC2: 2048 | AD2: 2049 | AE2: 2050
A3: EN - Power Industry | D3: 0 | E3: 0 | F3: 1.6405576 | G3: 0.34625024 | H3: 1.9174732 | I3: 2.5989561 | J3: 7.4215444 | K3: 12.361299 | L3: 10.532018 | M3: 2.5227963 | N3: 0 | O3: 0 | P3: 0 | Q3: 0.17038217 | R3: 1.7411691 | S3: 1.6253737 | T3: 1.3839284 | U3: 0.36629935 | V3: 1.2547853 | W3: 1.1758144 | X3: 1.1289111 | Y3: 0 | Z3: 1.9889886 | AA3: 1.1108272 | AB3: 1.9490205 | AC3: 1.7886575 | AD3: 3.3536365 | AE3: 7.1215774
A4: EN - Building | D4: 0 | E4: 0 | F4: 0 | G4: 0.012392549 | H4: 0.023961415 | I4: 0.034716882 | J4: 0.04467692 | K4: 0.064827291 | L4: 0.087174788 | M4: 0.11568716 | N4: 0.15926129 | O4: 0.23577258 | P4: 0.37229479 | Q4: 0.5841981 | R4: 0.83360216 | S4: 1.0449121 | T4: 1.1831236 | U4: 1.2640512 | V4: 1.3137549 | W4: 1.3490937 | X4: 1.3785 | Y4: 1.4057886 | Z4: 1.42454 | AA4: 1.4421371 | AB4: 1.4605851 | AC4: 1.4799217 | AD4: 1.5001853 | AE4: 1.5214156
A5: EN - Transportation | D5: 0 | E5: 0 | F5: 0.00071354781 | G5: 0.0034838861 | H5: 0.0064159389 | I5: 0.0095152481 | J5: 0.012795081 | K5: 0.016253265 | L5: 0.019892768 | M5: 0.023716181 | N5: 0.10602808 | O5: 0.17937431 | P5: 0.24473071 | Q5: 0.3029889 | R5: 0.35496134 | S5: 0.40138644 | T5: 0.44293309 | U5: 0.48020527 | V5: 0.51399811 | W5: 0.54484237 | X5: 0.57320804 | Y5: 0.59950962 | Z5: 0.6241114 | AA5: 0.64733216 | AB5: 0.66945045 | AC5: 0.69070656 | AD5: 0.71130656 | AE5: 0.73142549
A6: EN - Industrial combustion | D6: 0 | E6: 0 | F6: 0.014978408 | G6: 0.038599098 | H6: 0.061850965 | I6: 0.087728895 | J6: 0.11327748 | K6: 0.13857169 | L6: 0.16369791 | M6: 0.18873901 | N6: 0.21377563 | O6: 0.23887801 | P6: 0.26408324 | Q6: 0.28937229 | R6: 0.31468311 | S6: 0.33995973 | T6: 0.36518397 | U6: 0.39036782 | V6: 0.41560148 | W6: 0.4409168 | X6: 0.46633933 | Y6: 0.4918873 | Z6: 0.51757356 | AA6: 0.54340571 | AB6: 0.56938683 | AC6: 0.59551643 | AD6: 0.62157441 | AE6: 0.6477426
A7: IN - Industrial processes | D7: 0 | E7: 0 | F7: 0 | G7: 0.81392292 | H7: 0.9083042 | I7: 1.0048392 | J7: 1.1037592 | K7: 1.2048031 | L7: 1.3079567 | M7: 1.4132038 | N7: 1.5205262 | O7: 1.6299038 | P7: 1.7413146 | Q7: 1.8547346 | R7: 1.9701378 | S7: 2.0874964 | T7: 2.2067804 | U7: 2.3279581 | V7: 2.451401 | W7: 2.5771386 | X7: 2.7052009 | Y7: 2.8356177 | Z7: 2.9684192 | AA7: 3.103636 | AB7: 3.2412985 | AC7: 3.3814378 | AD7: 3.5240848 | AE7: 3.6692709
A8: Waste - Solid waste | D8: 0 | E8: 0 | F8: 0.087052446 | G8: 0.11358144 | H8: 0.1399269 | I8: 0.16354773 | J8: 0.1829564 | K8: 0.19795117 | L8: 0.20917977 | M8: 0.2175722 | N8: 0.2239904 | O8: 0.22909745 | P8: 0.2333409 | Q8: 0.23815074 | R8: 0.24258702 | S8: 0.24672606 | T8: 0.25063224 | U8: 0.25436408 | V8: 0.25796955 | W8: 0.26148254 | X8: 0.25997613 | Y8: 0.2584831 | Z8: 0.25701392 | AA8: 0.25557792 | AB8: 0.25418242 | AC8: 0.25283533 | AD8: 0.2513073 | AE8: 0.24983327
A9: Waste - Wastewater treatment (trww) | D9: 0 | E9: 0 | F9: 0 | G9: 0.11709818 | H9: 0.24928301 | I9: 0.39763456 | J9: 0.56345437 | K9: 0.74777457 | L9: 0.95177063 | M9: 1.1766567 | N9: 1.4236858 | O9: 1.6941498 | P9: 1.9893781 | Q9: 2.0439521 | R9: 2.0993942 | S9: 2.1556968 | T9: 2.2128525 | U9: 2.270853 | V9: 2.3303178 | W9: 2.3912911 | X9: 2.4538189 | Y9: 2.5179499 | Z9: 2.5837353 | AA9: 2.651228 | AB9: 2.7204793 | AC9: 2.7915445 | AD9: 2.8644803 | AE9: 2.9393447
A10: Waste - Wastewater (liquid waste) | D10: 0 | E10: 0 | F10: 0 | G10: 0 | H10: 0 | I10: 0 | J10: 0 | K10: 0 | L10: 0 | M10: 0 | N10: 0 | O10: 0 | P10: 0 | Q10: 0 | R10: 0 | S10: 0 | T10: 0 | U10: 0 | V10: 0 | W10: 0 | X10: 0 | Y10: 0 | Z10: 0 | AA10: 0 | AB10: 0 | AC10: 0 | AD10: 0 | AE10: 0
A11: AG - Livestock (manure) | D11: 0 | E11: 0 | F11: 0 | G11: 0 | H11: 0 | I11: 0 | J11: 0 | K11: 0 | L11: 0 | M11: 0 | N11: 0 | O11: 0 | P11: 0 | Q11: 0 | R11: 0 | S11: 0 | T11: 0 | U11: 0 | V11: 0 | W11: 0 | X11: 0 | Y11: 0 | Z11: 0 | AA11: 0 | AB11: 0 | AC11: 0 | AD11: 0 | AE11: 0
A12: LULUCF - Forest land | D12: 0 | E12: 0 | F12: 0.98551391 | G12: 1.217631 | H12: 1.4249767 | I12: 1.6039905 | J12: 1.7589536 | K12: 1.8900428 | L12: 2.0088138 | M12: 2.1188086 | N12: 2.2220535 | O12: 2.3206628 | P12: 2.416521 | Q12: 2.5108192 | R12: 2.6038114 | S12: 2.6944069 | T12: 2.7814845 | U12: 2.8635156 | V12: 2.9386065 | W12: 3.0067889 | X12: 3.0641981 | Y12: 3.1042697 | Z12: 3.1347957 | AA12: 3.1556165 | AB12: 3.1657721 | AC12: 3.1641768 | AD12: 3.131214 | AE12: 3.2774395
A14: units: billion 2019 USD
B15: GDP (constant 2019 PPP Billion US$) | D15: 316.71546 | E15: 326.67617 | F15: 337.46301 | G15: 348.87601 | H15: 360.72035 | I15: 372.90909 | J15: 385.62156 | K15: 398.62402 | L15: 411.91668 | M15: 425.49945 | N15: 439.37189 | O15: 453.53325 | P15: 467.9824 | Q15: 482.71789 | R15: 497.73788 | S15: 513.04015 | T15: 528.62212 | U15: 544.48078 | V15: 560.8152 | W15: 577.63966 | X15: 594.96885 | Y15: 612.81791 | Z15: 631.20245 | AA15: 650.13852 | AB15: 669.64268 | AC15: 689.73196 | AD15: 710.42392 | AE15: 731.73664
B16: Gross capital formation (% of GDP) | D16: 28.99836 | E16: 30.074355 | F16: 31.871247 | G16: 31.871247 | H16: 31.871247 | I16: 31.871247 | J16: 31.871247 | K16: 31.871247 | L16: 31.871247 | M16: 31.871247 | N16: 31.871247 | O16: 31.871247 | P16: 31.871247 | Q16: 31.871247 | R16: 31.871247 | S16: 31.871247 | T16: 31.871247 | U16: 31.871247 | V16: 31.871247 | W16: 31.871247 | X16: 31.871247 | Y16: 31.871247 | Z16: 31.871247 | AA16: 31.871247 | AB16: 31.871247 | AC16: 31.871247 | AD16: 31.871247 | AE16: 31.871247
B17: Gross capital formation (constant 2019 PPP Billion US$) | D17: =+D15*(D16)/100 -> 91.84229 | E17: =+E15*(E16)/100 -> 98.24575 | F17: =+F15*(F16)/100 -> 107.55367 | G17: =+G15*(G16)/100 -> 111.19114 | H17: =+H15*(H16)/100 -> 114.96608 | I17: =+I15*(I16)/100 -> 118.85078 | J17: =+J15*(J16)/100 -> 122.9024 | K17: =+K15*(K16)/100 -> 127.04645 | ... AE17: =+AE15*(AE16)/100 -> 233.21359
D19: LTS -Percent Change as Shock
A20: EN - Power Industry | D20: =+D3/D$17 -> 0 | E20: =+E3/E$17 -> 0 | F20: =+F3/F$17 -> 0.015253385 | G20: =+G3/G$17 -> 0.0031140094 | H20: =+H3/H$17 -> 0.0166786 | I20: =+I3/I$17 -> 0.021867388 | J20: =+J3/J$17 -> 0.060385674 | K20: =+K3/K$17 -> 0.097297482 | ... AE20: =+AE3/AE$17 -> 0.030536717
A21: EN - Building | D21: =+D4/D$17 -> 0 | E21: =+E4/E$17 -> 0 | F21: =+F4/F$17 -> 0 | G21: =+G4/G$17 -> 0.00011145267 | H21: =+H4/H$17 -> 0.00020842161 | I21: =+I4/I$17 -> 0.00029210479 | J21: =+J4/J$17 -> 0.00036351544 | K21: =+K4/K$17 -> 0.00051026449 | ... AE21: =+AE4/AE$17 -> 0.0065237005
A22: EN - Transportation | D22: =+D5/D$17 -> 0 | E22: =+E5/E$17 -> 0 | F22: =+F5/F$17 -> 6.6343418e-06 | G22: =+G5/G$17 -> 3.1332409e-05 | H22: =+H5/H$17 -> 5.5807236e-05 | I22: =+I5/I$17 -> 8.0060461e-05 | J22: =+J5/J$17 -> 0.00010410765 | K22: =+K5/K$17 -> 0.00012793168 | ... AE22: =+AE5/AE$17 -> 0.0031362901
A23: EN - Industrial combustion | D23: =+D6/D$17 -> 0 | E23: =+E6/E$17 -> 0 | F23: =+F6/F$17 -> 0.0001392645 | G23: =+G6/G$17 -> 0.00034714186 | H23: =+H6/H$17 -> 0.00053799318 | I23: =+I6/I$17 -> 0.0007381432 | J23: =+J6/J$17 -> 0.00092168645 | K23: =+K6/K$17 -> 0.0010907168 | ... AE23: =+AE6/AE$17 -> 0.0027774651
A24: IN - Industrial processes | D24: =+D7/D$17 -> 0 | E24: =+E7/E$17 -> 0 | F24: =+F7/F$17 -> 0 | G24: =+G7/G$17 -> 0.0073200342 | H24: =+H7/H$17 -> 0.0079006281 | I24: =+I7/I$17 -> 0.0084546283 | J24: =+J7/J$17 -> 0.0089807783 | K24: =+K7/K$17 -> 0.0094831707 | ... AE24: =+AE7/AE$17 -> 0.015733521
A25: Waste - Solid waste | D25: =+D8/D$17 -> 0 | E25: =+E8/E$17 -> 0 | F25: =+F8/F$17 -> 0.0008093861 | G25: =+G8/G$17 -> 0.0010214972 | H25: =+H8/H$17 -> 0.0012171147 | I25: =+I8/I$17 -> 0.0013760762 | J25: =+J8/J$17 -> 0.0014886316 | K25: =+K8/K$17 -> 0.0015581008 | ... AE25: =+AE8/AE$17 -> 0.0010712637
A26: Waste - Wastewater treatment (trww) | D26: =+D9/D$17 -> 0 | E26: =+E9/E$17 -> 0 | F26: =+F9/F$17 -> 0 | G26: =+G9/G$17 -> 0.0010531251 | H26: =+H9/H$17 -> 0.002168318 | I26: =+I9/I$17 -> 0.0033456622 | J26: =+J9/J$17 -> 0.0045845676 | K26: =+K9/K$17 -> 0.0058858361 | ... AE26: =+AE9/AE$17 -> 0.012603659
A27: Waste - Wastewater (liquid waste) | D27: =+D10/D$17 -> 0 | E27: =+E10/E$17 -> 0 | F27: =+F10/F$17 -> 0 | G27: =+G10/G$17 -> 0 | H27: =+H10/H$17 -> 0 | I27: =+I10/I$17 -> 0 | J27: =+J10/J$17 -> 0 | K27: =+K10/K$17 -> 0 | ... AE27: =+AE10/AE$17 -> 0
A28: AG - Livestock (manure) | D28: =+D11/D$17 -> 0 | E28: =+E11/E$17 -> 0 | F28: =+F11/F$17 -> 0 | G28: =+G11/G$17 -> 0 | H28: =+H11/H$17 -> 0 | I28: =+I11/I$17 -> 0 | J28: =+J11/J$17 -> 0 | K28: =+K11/K$17 -> 0 | ... AE28: =+AE11/AE$17 -> 0
A29: LULUCF - Forest land | D29: =+D12/D$17 -> 0 | E29: =+E12/E$17 -> 0 | F29: =+F12/F$17 -> 0.0091629965 | G29: =+G12/G$17 -> 0.010950792 | H29: =+H12/H$17 -> 0.012394758 | I29: =+I12/I$17 -> 0.013495835 | J29: =+J12/J$17 -> 0.014311792 | K29: =+K12/K$17 -> 0.014876786 | ... AE29: =+AE12/AE$17 -> 0.014053381
D31: =+SUM(D20:D29) -> 0 | E31: =+SUM(E20:E29) -> 0 | F31: =+SUM(F20:F29) -> 0.025371667 | G31: =+SUM(G20:G29) -> 0.023949385 | H31: =+SUM(H20:H29) -> 0.041161641 | I31: =+SUM(I20:I29) -> 0.049649899 | J31: =+SUM(J20:J29) -> 0.091140753 | K31: =+SUM(K20:K29) -> 0.13083029 | ... AE31: =+SUM(AE20:AE29) -> 0.086435997
A33: Sector | B33: Agent | C33: % | D33: 2023 | E33: 2024 | F33: 2025 | G33: 2026 | H33: 2027 | I33: 2028 | J33: 2029 | K33: 2030 | L33: 2031 | M33: 2032 | N33: 2033 | O33: 2034 | P33: 2035 | Q33: 2036 | R33: 2037 | S33: 2038 | T33: 2039 | U33: 2040 | V33: 2041 | W33: 2042 | X33: 2043 | Y33: 2044 | Z33: 2045 | AA33: 2046 | AB33: 2047 | AC33: 2048 | AD33: 2049 | AE33: 2050
A34: EN - Power Industry | B34: Government | C34: =+C102 -> 0.05 | D34: =+D$3*$C34 -> 0 | E34: =+E$3*$C34 -> 0 | F34: =+F$3*$C34 -> 0.082027879 | G34: =+G$3*$C34 -> 0.017312512 | H34: =+H$3*$C34 -> 0.095873659 | I34: =+I$3*$C34 -> 0.12994781 | J34: =+J$3*$C34 -> 0.37107722 | K34: =+K$3*$C34 -> 0.61806497 | ... AE34: =+AE$3*$C34 -> 0.35607887
B35: Firms | C35: =+D102 -> 0.9 | D35: =+D$3*$C35 -> 0 | E35: =+E$3*$C35 -> 0 | F35: =+F$3*$C35 -> 1.4765018 | G35: =+G$3*$C35 -> 0.31162522 | H35: =+H$3*$C35 -> 1.7257259 | I35: =+I$3*$C35 -> 2.3390605 | J35: =+J$3*$C35 -> 6.6793899 | K35: =+K$3*$C35 -> 11.125169 | ... AE35: =+AE$3*$C35 -> 6.4094196
B36: Households | C36: =+E102 -> 0.05 | D36: =+D$3*$C36 -> 0 | E36: =+E$3*$C36 -> 0 | F36: =+F$3*$C36 -> 0.082027879 | G36: =+G$3*$C36 -> 0.017312512 | H36: =+H$3*$C36 -> 0.095873659 | I36: =+I$3*$C36 -> 0.12994781 | J36: =+J$3*$C36 -> 0.37107722 | K36: =+K$3*$C36 -> 0.61806497 | ... AE36: =+AE$3*$C36 -> 0.35607887
A37: EN - Building | B37: Government | C37: =+C103 -> 0.25 | D37: =+D$4*$C37 -> 0 | E37: =+E$4*$C37 -> 0 | F37: =+F$4*$C37 -> 0 | G37: =+G$4*$C37 -> 0.0030981372 | H37: =+H$4*$C37 -> 0.0059903538 | I37: =+I$4*$C37 -> 0.0086792205 | J37: =+J$4*$C37 -> 0.01116923 | K37: =+K$4*$C37 -> 0.016206823 | ... AE37: =+AE$4*$C37 -> 0.38035391
B38: Firms | C38: =+D103 -> 0.25 | D38: =+D$4*$C38 -> 0 | E38: =+E$4*$C38 -> 0 | F38: =+F$4*$C38 -> 0 | G38: =+G$4*$C38 -> 0.0030981372 | H38: =+H$4*$C38 -> 0.0059903538 | I38: =+I$4*$C38 -> 0.0086792205 | J38: =+J$4*$C38 -> 0.01116923 | K38: =+K$4*$C38 -> 0.016206823 | ... AE38: =+AE$4*$C38 -> 0.38035391
B39: Households | C39: =+E103 -> 0.5 | D39: =+D$4*$C39 -> 0 | E39: =+E$4*$C39 -> 0 | F39: =+F$4*$C39 -> 0 | G39: =+G$4*$C39 -> 0.0061962745 | H39: =+H$4*$C39 -> 0.011980708 | I39: =+I$4*$C39 -> 0.017358441 | J39: =+J$4*$C39 -> 0.02233846 | K39: =+K$4*$C39 -> 0.032413645 | ... AE39: =+AE$4*$C39 -> 0.76070782
A40: EN - Transportation | B40: Government | C40: =+C104 -> 0.15 | D40: =+D$5*$C40 -> 0 | E40: =+E$5*$C40 -> 0 | F40: =+F$5*$C40 -> 0.00010703217 | G40: =+G$5*$C40 -> 0.00052258292 | H40: =+H$5*$C40 -> 0.00096239084 | I40: =+I$5*$C40 -> 0.0014272872 | J40: =+J$5*$C40 -> 0.0019192621 | K40: =+K$5*$C40 -> 0.0024379898 | ... AE40: =+AE$5*$C40 -> 0.10971382
B41: Firms | C41: =+D104 -> 0.35 | D41: =+D$5*$C41 -> 0 | E41: =+E$5*$C41 -> 0 | F41: =+F$5*$C41 -> 0.00024974173 | G41: =+G$5*$C41 -> 0.0012193601 | H41: =+H$5*$C41 -> 0.0022455786 | I41: =+I$5*$C41 -> 0.0033303368 | J41: =+J$5*$C41 -> 0.0044782783 | K41: =+K$5*$C41 -> 0.0056886429 | ... AE41: =+AE$5*$C41 -> 0.25599892
B42: Households | C42: =+E104 -> 0.5 | D42: =+D$5*$C42 -> 0 | E42: =+E$5*$C42 -> 0 | F42: =+F$5*$C42 -> 0.00035677391 | G42: =+G$5*$C42 -> 0.0017419431 | H42: =+H$5*$C42 -> 0.0032079695 | I42: =+I$5*$C42 -> 0.0047576241 | J42: =+J$5*$C42 -> 0.0063975404 | K42: =+K$5*$C42 -> 0.0081266327 | ... AE42: =+AE$5*$C42 -> 0.36571274
A43: EN - Industrial combustion | B43: Government | C43: =+C105 -> 0.1 | D43: =+D$6*$C43 -> 0 | E43: =+E$6*$C43 -> 0 | F43: =+F$6*$C43 -> 0.0014978408 | G43: =+G$6*$C43 -> 0.0038599098 | H43: =+H$6*$C43 -> 0.0061850965 | I43: =+I$6*$C43 -> 0.0087728895 | J43: =+J$6*$C43 -> 0.011327748 | K43: =+K$6*$C43 -> 0.013857169 | ... AE43: =+AE$6*$C43 -> 0.06477426
B44: Firms | C44: =+D105 -> 0.9 | D44: =+D$6*$C44 -> 0 | E44: =+E$6*$C44 -> 0 | F44: =+F$6*$C44 -> 0.013480567 | G44: =+G$6*$C44 -> 0.034739188 | H44: =+H$6*$C44 -> 0.055665868 | I44: =+I$6*$C44 -> 0.078956005 | J44: =+J$6*$C44 -> 0.10194973 | K44: =+K$6*$C44 -> 0.12471452 | ... AE44: =+AE$6*$C44 -> 0.58296834
B45: Households | C45: =+E105 -> 0 | D45: =+D$6*$C45 -> 0 | E45: =+E$6*$C45 -> 0 | F45: =+F$6*$C45 -> 0 | G45: =+G$6*$C45 -> 0 | H45: =+H$6*$C45 -> 0 | I45: =+I$6*$C45 -> 0 | J45: =+J$6*$C45 -> 0 | K45: =+K$6*$C45 -> 0 | ... AE45: =+AE$6*$C45 -> 0
A46: IN - Industrial processes | B46: Government | C46: =+C106 -> 0.02 | D46: =+D$7*$C46 -> 0 | E46: =+E$7*$C46 -> 0 | F46: =+F$7*$C46 -> 0 | G46: =+G$7*$C46 -> 0.016278458 | H46: =+H$7*$C46 -> 0.018166084 | I46: =+I$7*$C46 -> 0.020096783 | J46: =+J$7*$C46 -> 0.022075184 | K46: =+K$7*$C46 -> 0.024096063 | ... AE46: =+AE$7*$C46 -> 0.073385418
B47: Firms | C47: =+D106 -> 0.98 | D47: =+D$7*$C47 -> 0 | E47: =+E$7*$C47 -> 0 | F47: =+F$7*$C47 -> 0 | G47: =+G$7*$C47 -> 0.79764446 | H47: =+H$7*$C47 -> 0.89013811 | I47: =+I$7*$C47 -> 0.98474237 | J47: =+J$7*$C47 -> 1.081684 | K47: =+K$7*$C47 -> 1.1807071 | ... AE47: =+AE$7*$C47 -> 3.5958855
B48: Households | C48: =+E106 -> 0 | D48: =+D$7*$C48 -> 0 | E48: =+E$7*$C48 -> 0 | F48: =+F$7*$C48 -> 0 | G48: =+G$7*$C48 -> 0 | H48: =+H$7*$C48 -> 0 | I48: =+I$7*$C48 -> 0 | J48: =+J$7*$C48 -> 0 | K48: =+K$7*$C48 -> 0 | ... AE48: =+AE$7*$C48 -> 0
A49: Waste - Solid waste | B49: Government | C49: =+C107 -> 0.5 | D49: =+D$8*$C49 -> 0 | E49: =+E$8*$C49 -> 0 | F49: =+F$8*$C49 -> 0.043526223 | G49: =+G$8*$C49 -> 0.056790719 | H49: =+H$8*$C49 -> 0.06996345 | I49: =+I$8*$C49 -> 0.081773866 | J49: =+J$8*$C49 -> 0.091478198 | K49: =+K$8*$C49 -> 0.098975584 | ... AE49: =+AE$8*$C49 -> 0.12491663
B50: Firms | C50: =+D107 -> 0.5 | D50: =+D$8*$C50 -> 0 | E50: =+E$8*$C50 -> 0 | F50: =+F$8*$C50 -> 0.043526223 | G50: =+G$8*$C50 -> 0.056790719 | H50: =+H$8*$C50 -> 0.06996345 | I50: =+I$8*$C50 -> 0.081773866 | J50: =+J$8*$C50 -> 0.091478198 | K50: =+K$8*$C50 -> 0.098975584 | ... AE50: =+AE$8*$C50 -> 0.12491663
B51: Households | C51: =+E107 -> 0 | D51: =+D$8*$C51 -> 0 | E51: =+E$8*$C51 -> 0 | F51: =+F$8*$C51 -> 0 | G51: =+G$8*$C51 -> 0 | H51: =+H$8*$C51 -> 0 | I51: =+I$8*$C51 -> 0 | J51: =+J$8*$C51 -> 0 | K51: =+K$8*$C51 -> 0 | ... AE51: =+AE$8*$C51 -> 0
A52: Waste - Wastewater treatment (trww) | B52: Government | C52: =+C108 -> 0.7 | D52: =+D$9*$C52 -> 0 | E52: =+E$9*$C52 -> 0 | F52: =+F$9*$C52 -> 0 | G52: =+G$9*$C52 -> 0.081968724 | H52: =+H$9*$C52 -> 0.17449811 | I52: =+I$9*$C52 -> 0.27834419 | J52: =+J$9*$C52 -> 0.39441806 | K52: =+K$9*$C52 -> 0.5234422 | ... AE52: =+AE$9*$C52 -> 2.0575413
B53: Firms | C53: =+D108 -> 0.3 | D53: =+D$9*$C53 -> 0 | E53: =+E$9*$C53 -> 0 | F53: =+F$9*$C53 -> 0 | G53: =+G$9*$C53 -> 0.035129453 | H53: =+H$9*$C53 -> 0.074784903 | I53: =+I$9*$C53 -> 0.11929037 | J53: =+J$9*$C53 -> 0.16903631 | K53: =+K$9*$C53 -> 0.22433237 | ... AE53: =+AE$9*$C53 -> 0.8818034
B54: Households | C54: =+E108 -> 0 | D54: =+D$9*$C54 -> 0 | E54: =+E$9*$C54 -> 0 | F54: =+F$9*$C54 -> 0 | G54: =+G$9*$C54 -> 0 | H54: =+H$9*$C54 -> 0 | I54: =+I$9*$C54 -> 0 | J54: =+J$9*$C54 -> 0 | K54: =+K$9*$C54 -> 0 | ... AE54: =+AE$9*$C54 -> 0
A55: Waste - Wastewater (liquid waste) | B55: Government | C55: =+C109 -> 0.7 | D55: =+D$10*$C55 -> 0 | E55: =+E$10*$C55 -> 0 | F55: =+F$10*$C55 -> 0 | G55: =+G$10*$C55 -> 0 | H55: =+H$10*$C55 -> 0 | I55: =+I$10*$C55 -> 0 | J55: =+J$10*$C55 -> 0 | K55: =+K$10*$C55 -> 0 | ... AE55: =+AE$10*$C55 -> 0
B56: Firms | C56: =+D109 -> 0.3 | D56: =+D$10*$C56 -> 0 | E56: =+E$10*$C56 -> 0 | F56: =+F$10*$C56 -> 0 | G56: =+G$10*$C56 -> 0 | H56: =+H$10*$C56 -> 0 | I56: =+I$10*$C56 -> 0 | J56: =+J$10*$C56 -> 0 | K56: =+K$10*$C56 -> 0 | ... AE56: =+AE$10*$C56 -> 0
B57: Households | C57: =+E109 -> 0 | D57: =+D$10*$C57 -> 0 | E57: =+E$10*$C57 -> 0 | F57: =+F$10*$C57 -> 0 | G57: =+G$10*$C57 -> 0 | H57: =+H$10*$C57 -> 0 | I57: =+I$10*$C57 -> 0 | J57: =+J$10*$C57 -> 0 | K57: =+K$10*$C57 -> 0 | ... AE57: =+AE$10*$C57 -> 0
A58: AG - Livestock (manure) | B58: Government | C58: =+C110 -> 0 | D58: =+D$11*$C58 -> 0 | E58: =+E$11*$C58 -> 0 | F58: =+F$11*$C58 -> 0 | G58: =+G$11*$C58 -> 0 | H58: =+H$11*$C58 -> 0 | I58: =+I$11*$C58 -> 0 | J58: =+J$11*$C58 -> 0 | K58: =+K$11*$C58 -> 0 | ... AE58: =+AE$11*$C58 -> 0
B59: Firms | C59: =+D110 -> 1 | D59: =+D$11*$C59 -> 0 | E59: =+E$11*$C59 -> 0 | F59: =+F$11*$C59 -> 0 | G59: =+G$11*$C59 -> 0 | H59: =+H$11*$C59 -> 0 | I59: =+I$11*$C59 -> 0 | J59: =+J$11*$C59 -> 0 | K59: =+K$11*$C59 -> 0 | ... AE59: =+AE$11*$C59 -> 0
B60: Households | C60: =+E110 -> 0 | D60: =+D$11*$C60 -> 0 | E60: =+E$11*$C60 -> 0 | F60: =+F$11*$C60 -> 0 | G60: =+G$11*$C60 -> 0 | H60: =+H$11*$C60 -> 0 | I60: =+I$11*$C60 -> 0 | J60: =+J$11*$C60 -> 0 | K60: =+K$11*$C60 -> 0 | ... AE60: =+AE$11*$C60 -> 0
A61: LULUCF - Forest land | B61: Government | C61: =+C111 -> 0.8 | D61: =+D$12*$C61 -> 0 | E61: =+E$12*$C61 -> 0 | F61: =+F$12*$C61 -> 0.78841112 | G61: =+G$12*$C61 -> 0.97410478 | H61: =+H$12*$C61 -> 1.1399814 | I61: =+I$12*$C61 -> 1.2831924 | J61: =+J$12*$C61 -> 1.4071629 | K61: =+K$12*$C61 -> 1.5120342 | ... AE61: =+AE$12*$C61 -> 2.6219516
B62: Firms | C62: =+D111 -> 0.15 | D62: =+D$12*$C62 -> 0 | E62: =+E$12*$C62 -> 0 | F62: =+F$12*$C62 -> 0.14782709 | G62: =+G$12*$C62 -> 0.18264465 | H62: =+H$12*$C62 -> 0.21374651 | I62: =+I$12*$C62 -> 0.24059858 | J62: =+J$12*$C62 -> 0.26384304 | K62: =+K$12*$C62 -> 0.28350642 | ... AE62: =+AE$12*$C62 -> 0.49161592
B63: Households | C63: =+E111 -> 0.05 | D63: =+D$12*$C63 -> 0 | E63: =+E$12*$C63 -> 0 | F63: =+F$12*$C63 -> 0.049275695 | G63: =+G$12*$C63 -> 0.060881549 | H63: =+H$12*$C63 -> 0.071248835 | I63: =+I$12*$C63 -> 0.080199527 | J63: =+J$12*$C63 -> 0.087947679 | K63: =+K$12*$C63 -> 0.09450214 | ... AE63: =+AE$12*$C63 -> 0.16387197
C66: LTS -Percent Change as Shock
A67: Sector | B67: Agent | D67: 2023 | E67: 2024 | F67: 2025 | G67: 2026 | H67: 2027 | I67: 2028 | J67: 2029 | K67: 2030 | L67: 2031 | M67: 2032 | N67: 2033 | O67: 2034 | P67: 2035 | Q67: 2036 | R67: 2037 | S67: 2038 | T67: 2039 | U67: 2040 | V67: 2041 | W67: 2042 | X67: 2043 | Y67: 2044 | Z67: 2045 | AA67: 2046 | AB67: 2047 | AC67: 2048 | AD67: 2049 | AE67: 2050
A68: EN - Power Industry | B68: Government | D68: =+D34/D$17 -> 0 | E68: =+E34/E$17 -> 0 | F68: =+F34/F$17 -> 0.00076266927 | G68: =+G34/G$17 -> 0.00015570047 | H68: =+H34/H$17 -> 0.00083393 | I68: =+I34/I$17 -> 0.0010933694 | J68: =+J34/J$17 -> 0.0030192837 | K68: =+K34/K$17 -> 0.0048648741 | ... AE68: =+AE34/AE$17 -> 0.0015268358
B69: Firms | D69: =+D35/D$17 -> 0 | E69: =+E35/E$17 -> 0 | F69: =+F35/F$17 -> 0.013728047 | G69: =+G35/G$17 -> 0.0028026085 | H69: =+H35/H$17 -> 0.01501074 | I69: =+I35/I$17 -> 0.019680649 | J69: =+J35/J$17 -> 0.054347107 | K69: =+K35/K$17 -> 0.087567733 | ... AE69: =+AE35/AE$17 -> 0.027483045
B70: Households | D70: =+D36/D$17 -> 0 | E70: =+E36/E$17 -> 0 | F70: =+F36/F$17 -> 0.00076266927 | G70: =+G36/G$17 -> 0.00015570047 | H70: =+H36/H$17 -> 0.00083393 | I70: =+I36/I$17 -> 0.0010933694 | J70: =+J36/J$17 -> 0.0030192837 | K70: =+K36/K$17 -> 0.0048648741 | ... AE70: =+AE36/AE$17 -> 0.0015268358
A71: EN - Building | B71: Government | D71: =+D37/D$17 -> 0 | E71: =+E37/E$17 -> 0 | F71: =+F37/F$17 -> 0 | G71: =+G37/G$17 -> 2.7863167e-05 | H71: =+H37/H$17 -> 5.2105404e-05 | I71: =+I37/I$17 -> 7.3026198e-05 | J71: =+J37/J$17 -> 9.0878859e-05 | K71: =+K37/K$17 -> 0.00012756612 | ... AE71: =+AE37/AE$17 -> 0.0016309251
B72: Firms | D72: =+D38/D$17 -> 0 | E72: =+E38/E$17 -> 0 | F72: =+F38/F$17 -> 0 | G72: =+G38/G$17 -> 2.7863167e-05 | H72: =+H38/H$17 -> 5.2105404e-05 | I72: =+I38/I$17 -> 7.3026198e-05 | J72: =+J38/J$17 -> 9.0878859e-05 | K72: =+K38/K$17 -> 0.00012756612 | ... AE72: =+AE38/AE$17 -> 0.0016309251
B73: Households | D73: =+D39/D$17 -> 0 | E73: =+E39/E$17 -> 0 | F73: =+F39/F$17 -> 0 | G73: =+G39/G$17 -> 5.5726335e-05 | H73: =+H39/H$17 -> 0.00010421081 | I73: =+I39/I$17 -> 0.0001460524 | J73: =+J39/J$17 -> 0.00018175772 | K73: =+K39/K$17 -> 0.00025513224 | ... AE73: =+AE39/AE$17 -> 0.0032618503
A74: EN - Transportation | B74: Government | D74: =+D40/D$17 -> 0 | E74: =+E40/E$17 -> 0 | F74: =+F40/F$17 -> 9.9515126e-07 | G74: =+G40/G$17 -> 4.6998613e-06 | H74: =+H40/H$17 -> 8.3710855e-06 | I74: =+I40/I$17 -> 1.2009069e-05 | J74: =+J40/J$17 -> 1.5616148e-05 | K74: =+K40/K$17 -> 1.9189752e-05 | ... AE74: =+AE40/AE$17 -> 0.00047044352
B75: Firms | D75: =+D41/D$17 -> 0 | E75: =+E41/E$17 -> 0 | F75: =+F41/F$17 -> 2.3220196e-06 | G75: =+G41/G$17 -> 1.0966343e-05 | H75: =+H41/H$17 -> 1.9532533e-05 | I75: =+I41/I$17 -> 2.8021161e-05 | J75: =+J41/J$17 -> 3.6437679e-05 | K75: =+K41/K$17 -> 4.4776088e-05 | ... AE75: =+AE41/AE$17 -> 0.0010977015
B76: Households | D76: =+D42/D$17 -> 0 | E76: =+E42/E$17 -> 0 | F76: =+F42/F$17 -> 3.3171709e-06 | G76: =+G42/G$17 -> 1.5666204e-05 | H76: =+H42/H$17 -> 2.7903618e-05 | I76: =+I42/I$17 -> 4.003023e-05 | J76: =+J42/J$17 -> 5.2053827e-05 | K76: =+K42/K$17 -> 6.396584e-05 | ... AE76: =+AE42/AE$17 -> 0.0015681451
A77: EN - Industrial combustion | B77: Government | D77: =+D43/D$17 -> 0 | E77: =+E43/E$17 -> 0 | F77: =+F43/F$17 -> 1.392645e-05 | G77: =+G43/G$17 -> 3.4714186e-05 | H77: =+H43/H$17 -> 5.3799318e-05 | I77: =+I43/I$17 -> 7.381432e-05 | J77: =+J43/J$17 -> 9.2168645e-05 | K77: =+K43/K$17 -> 0.00010907168 | ... AE77: =+AE43/AE$17 -> 0.00027774651
B78: Firms | D78: =+D44/D$17 -> 0 | E78: =+E44/E$17 -> 0 | F78: =+F44/F$17 -> 0.00012533805 | G78: =+G44/G$17 -> 0.00031242767 | H78: =+H44/H$17 -> 0.00048419386 | I78: =+I44/I$17 -> 0.00066432888 | J78: =+J44/J$17 -> 0.0008295178 | K78: =+K44/K$17 -> 0.00098164508 | ... AE78: =+AE44/AE$17 -> 0.0024997185
B79: Households | D79: =+D45/D$17 -> 0 | E79: =+E45/E$17 -> 0 | F79: =+F45/F$17 -> 0 | G79: =+G45/G$17 -> 0 | H79: =+H45/H$17 -> 0 | I79: =+I45/I$17 -> 0 | J79: =+J45/J$17 -> 0 | K79: =+K45/K$17 -> 0 | ... AE79: =+AE45/AE$17 -> 0
A80: IN - Industrial processes | B80: Government | D80: =+D46/D$17 -> 0 | E80: =+E46/E$17 -> 0 | F80: =+F46/F$17 -> 0 | G80: =+G46/G$17 -> 0.00014640068 | H80: =+H46/H$17 -> 0.00015801256 | I80: =+I46/I$17 -> 0.00016909257 | J80: =+J46/J$17 -> 0.00017961557 | K80: =+K46/K$17 -> 0.00018966341 | ... AE80: =+AE46/AE$17 -> 0.00031467042
B81: Firms | D81: =+D47/D$17 -> 0 | E81: =+E47/E$17 -> 0 | F81: =+F47/F$17 -> 0 | G81: =+G47/G$17 -> 0.0071736335 | H81: =+H47/H$17 -> 0.0077426155 | I81: =+I47/I$17 -> 0.0082855357 | J81: =+J47/J$17 -> 0.0088011627 | K81: =+K47/K$17 -> 0.0092935072 | ... AE81: =+AE47/AE$17 -> 0.01541885
B82: Households | D82: =+D48/D$17 -> 0 | E82: =+E48/E$17 -> 0 | F82: =+F48/F$17 -> 0 | G82: =+G48/G$17 -> 0 | H82: =+H48/H$17 -> 0 | I82: =+I48/I$17 -> 0 | J82: =+J48/J$17 -> 0 | K82: =+K48/K$17 -> 0 | ... AE82: =+AE48/AE$17 -> 0
A83: Waste - Solid waste | B83: Government | D83: =+D49/D$17 -> 0 | E83: =+E49/E$17 -> 0 | F83: =+F49/F$17 -> 0.00040469305 | G83: =+G49/G$17 -> 0.00051074861 | H83: =+H49/H$17 -> 0.00060855735 | I83: =+I49/I$17 -> 0.00068803811 | J83: =+J49/J$17 -> 0.00074431579 | K83: =+K49/K$17 -> 0.00077905039 | ... AE83: =+AE49/AE$17 -> 0.00053563187
B84: Firms | D84: =+D50/D$17 -> 0 | E84: =+E50/E$17 -> 0 | F84: =+F50/F$17 -> 0.00040469305 | G84: =+G50/G$17 -> 0.00051074861 | H84: =+H50/H$17 -> 0.00060855735 | I84: =+I50/I$17 -> 0.00068803811 | J84: =+J50/J$17 -> 0.00074431579 | K84: =+K50/K$17 -> 0.00077905039 | ... AE84: =+AE50/AE$17 -> 0.00053563187
B85: Households | D85: =+D51/D$17 -> 0 | E85: =+E51/E$17 -> 0 | F85: =+F51/F$17 -> 0 | G85: =+G51/G$17 -> 0 | H85: =+H51/H$17 -> 0 | I85: =+I51/I$17 -> 0 | J85: =+J51/J$17 -> 0 | K85: =+K51/K$17 -> 0 | ... AE85: =+AE51/AE$17 -> 0
A86: Waste - Wastewater treatment (trww) | B86: Government | D86: =+D52/D$17 -> 0 | E86: =+E52/E$17 -> 0 | F86: =+F52/F$17 -> 0 | G86: =+G52/G$17 -> 0.00073718757 | H86: =+H52/H$17 -> 0.0015178226 | I86: =+I52/I$17 -> 0.0023419636 | J86: =+J52/J$17 -> 0.0032091973 | K86: =+K52/K$17 -> 0.0041200853 | ... AE86: =+AE52/AE$17 -> 0.0088225615
B87: Firms | D87: =+D53/D$17 -> 0 | E87: =+E53/E$17 -> 0 | F87: =+F53/F$17 -> 0 | G87: =+G53/G$17 -> 0.00031593753 | H87: =+H53/H$17 -> 0.0006504954 | I87: =+I53/I$17 -> 0.0010036987 | J87: =+J53/J$17 -> 0.0013753703 | K87: =+K53/K$17 -> 0.0017657508 | ... AE87: =+AE53/AE$17 -> 0.0037810978
B88: Households | D88: =+D54/D$17 -> 0 | E88: =+E54/E$17 -> 0 | F88: =+F54/F$17 -> 0 | G88: =+G54/G$17 -> 0 | H88: =+H54/H$17 -> 0 | I88: =+I54/I$17 -> 0 | J88: =+J54/J$17 -> 0 | K88: =+K54/K$17 -> 0 | ... AE88: =+AE54/AE$17 -> 0
A89: Waste - Wastewater (liquid waste) | B89: Government | D89: =+D55/D$17 -> 0 | E89: =+E55/E$17 -> 0 | F89: =+F55/F$17 -> 0 | G89: =+G55/G$17 -> 0 | H89: =+H55/H$17 -> 0 | I89: =+I55/I$17 -> 0 | J89: =+J55/J$17 -> 0 | K89: =+K55/K$17 -> 0 | ... AE89: =+AE55/AE$17 -> 0
B90: Firms | D90: =+D56/D$17 -> 0 | E90: =+E56/E$17 -> 0 | F90: =+F56/F$17 -> 0 | G90: =+G56/G$17 -> 0 | H90: =+H56/H$17 -> 0 | I90: =+I56/I$17 -> 0 | J90: =+J56/J$17 -> 0 | K90: =+K56/K$17 -> 0 | ... AE90: =+AE56/AE$17 -> 0
B91: Households | D91: =+D57/D$17 -> 0 | E91: =+E57/E$17 -> 0 | F91: =+F57/F$17 -> 0 | G91: =+G57/G$17 -> 0 | H91: =+H57/H$17 -> 0 | I91: =+I57/I$17 -> 0 | J91: =+J57/J$17 -> 0 | K91: =+K57/K$17 -> 0 | ... AE91: =+AE57/AE$17 -> 0
A92: AG - Livestock (manure) | B92: Government | D92: =+D58/D$17 -> 0 | E92: =+E58/E$17 -> 0 | F92: =+F58/F$17 -> 0 | G92: =+G58/G$17 -> 0 | H92: =+H58/H$17 -> 0 | I92: =+I58/I$17 -> 0 | J92: =+J58/J$17 -> 0 | K92: =+K58/K$17 -> 0 | ... AE92: =+AE58/AE$17 -> 0
B93: Firms | D93: =+D59/D$17 -> 0 | E93: =+E59/E$17 -> 0 | F93: =+F59/F$17 -> 0 | G93: =+G59/G$17 -> 0 | H93: =+H59/H$17 -> 0 | I93: =+I59/I$17 -> 0 | J93: =+J59/J$17 -> 0 | K93: =+K59/K$17 -> 0 | ... AE93: =+AE59/AE$17 -> 0
B94: Households | D94: =+D60/D$17 -> 0 | E94: =+E60/E$17 -> 0 | F94: =+F60/F$17 -> 0 | G94: =+G60/G$17 -> 0 | H94: =+H60/H$17 -> 0 | I94: =+I60/I$17 -> 0 | J94: =+J60/J$17 -> 0 | K94: =+K60/K$17 -> 0 | ... AE94: =+AE60/AE$17 -> 0
A95: LULUCF - Forest land | B95: Government | D95: =+D61/D$17 -> 0 | E95: =+E61/E$17 -> 0 | F95: =+F61/F$17 -> 0.0073303972 | G95: =+G61/G$17 -> 0.0087606334 | H95: =+H61/H$17 -> 0.0099158066 | I95: =+I61/I$17 -> 0.010796668 | J95: =+J61/J$17 -> 0.011449433 | K95: =+K61/K$17 -> 0.011901429 | ... AE95: =+AE61/AE$17 -> 0.011242705
B96: Firms | D96: =+D62/D$17 -> 0 | E96: =+E62/E$17 -> 0 | F96: =+F62/F$17 -> 0.0013744495 | G96: =+G62/G$17 -> 0.0016426188 | H96: =+H62/H$17 -> 0.0018592137 | I96: =+I62/I$17 -> 0.0020243753 | J96: =+J62/J$17 -> 0.0021467688 | K96: =+K62/K$17 -> 0.0022315179 | ... AE96: =+AE62/AE$17 -> 0.0021080071
B97: Households | D97: =+D63/D$17 -> 0 | E97: =+E63/E$17 -> 0 | F97: =+F63/F$17 -> 0.00045814982 | G97: =+G63/G$17 -> 0.00054753959 | H97: =+H63/H$17 -> 0.00061973791 | I97: =+I63/I$17 -> 0.00067479177 | J97: =+J63/J$17 -> 0.00071558959 | K97: =+K63/K$17 -> 0.0007438393 | ... AE97: =+AE63/AE$17 -> 0.00070266905
D99: =+SUM(D68:D97) -> 0 | E99: =+SUM(E68:E97) -> 0 | F99: =+SUM(F68:F97) -> 0.025371667 | G99: =+SUM(G68:G97) -> 0.023949385 | H99: =+SUM(H68:H97) -> 0.041161641 | I99: =+SUM(I68:I97) -> 0.049649899 | J99: =+SUM(J68:J97) -> 0.091140753 | K99: =+SUM(K68:K97) -> 0.13083029 | ... AE99: =+SUM(AE68:AE97) -> 0.086435997
B101: Investment sector | C101: Gov % | D101: Firms % | E101: HH % | F101: Justification
B102: EN - Power Industry | C102: 0.05 | D102: 0.9 | E102: 0.05 | F102: BDD CDN: power generation projects (M01-M08) are 100% privately financed (IPPs). 5% Gov for residual ONEE capacity; 5% HH for rooftop PV (assumption).
B103: EN - Building | C103: 0.25 | D103: 0.25 | E103: 0.5 | F103: BDD CDN: building projects are 27% public. SNBC matrix: State funds support programmes and public lighting; households buy appliances and residential equipment; firms fund tertiary PV.
B104: EN - Transportation | C104: 0.15 | D104: 0.35 | E104: 0.5 | F104: BDD CDN: vehicle programmes (M43-M44, M49-M52) are 25% public; SNBC matrix: State purchase support is ~6% of fleet cost. Gov 15% = midpoint; remainder mostly households (private cars).
B105: EN - Industrial combustion | C105: 0.1 | D105: 0.9 | E105: 0 | F105: BDD CDN: industrial energy projects (efficiency, biomass, PV, incl. phosphates) are 8-13% public; SNBC matrix classifies them as private investment. Gov 10% = midpoint.
B106: IN - Industrial processes | C106: 0.02 | D106: 0.98 | E106: 0 | F106: BDD CDN: cement, phosphate CO2 capture and HFC projects are 2% public; the rest is financed by producers.
B107: Waste - Solid waste | C107: 0.5 | D107: 0.5 | E107: 0 | F107: BDD CDN: landfill methane capture and waste treatment projects (M56-M58) are 47% public, reflecting 50/50 public-private partnerships.
B108: Waste - Wastewater treatment (trww) | C108: 0.7 | D108: 0.3 | E108: 0 | F108: BDD CDN: wastewater methane recovery and reuse projects (M55, A01) are 66% public; rounded to 70% as treatment plants are run by ONEE and municipalities.
...

Sheet SAM
A1: Morocco SAM sector | B1: EN - Power Industry | C1: EN - Power Industry - Government | D1: EN - Power Industry - Firms | E1: EN - Power Industry - Households | F1: EN - Building | G1: EN - Building - Government | H1: EN - Building - Firms | I1: EN - Building - Households | J1: EN - Transportation | K1: EN - Transportation - Government | L1: EN - Transportation - Firms | M1: EN - Transportation - Households | N1: EN - Industrial combustion | O1: EN - Industrial combustion - Government | P1: EN - Industrial combustion - Firms | Q1: EN - Industrial combustion - Households | R1: IN - Industrial processes | S1: IN - Industrial processes - Government | T1: IN - Industrial processes - Firms | U1: IN - Industrial processes - Households | V1: Waste - Solid waste | W1: Waste - Solid waste - Government | X1: Waste - Solid waste - Firms | Y1: Waste - Solid waste - Households | Z1: Waste - Wastewater treatment (trww) | AA1: Waste - Wastewater treatment (trww) - Government | AB1: Waste - Wastewater treatment (trww) - Firms | AC1: Waste - Wastewater treatment (trww) - Households | AD1: Waste - Wastewater (liquid waste) | AE1: Waste - Wastewater (liquid waste) - Government | AF1: Waste - Wastewater (liquid waste) - Firms | AG1: Waste - Wastewater (liquid waste) - Households | AH1: AG - Livestock (manure) | AI1: AG - Livestock (manure) - Government | AJ1: AG - Livestock (manure) - Firms | AK1: AG - Livestock (manure) - Households | AL1: LULUCF - Forest land | AM1: LULUCF - Forest land - Government | AN1: LULUCF - Forest land - Firms | AO1: LULUCF - Forest land - Households
A2: crops | C2: =+$B2*Total!C$102 -> 0 | D2: =+$B2*Total!D$102 -> 0 | E2: =+$B2*Total!E$102 -> 0 | G2: =$F2*Total!C$103 -> 0 | H2: =$F2*Total!D$103 -> 0 | I2: =$F2*Total!E$103 -> 0 | K2: =$J2*Total!C$104 -> 0 | L2: =$J2*Total!D$104 -> 0 | M2: =$J2*Total!E$104 -> 0 | O2: =$N2*Total!C$105 -> 0 | P2: =$N2*Total!D$105 -> 0 | Q2: =$N2*Total!E$105 -> 0 | S2: =$R2*Total!C$106 -> 0 | T2: =$R2*Total!D$106 -> 0 | U2: =$R2*Total!E$106 -> 0 | W2: =$V2*Total!C$107 -> 0 | X2: =$V2*Total!D$107 -> 0 | Y2: =$V2*Total!E$107 -> 0 | AA2: =$Z2*Total!C$108 -> 0 | AB2: =$Z2*Total!D$108 -> 0 | AC2: =$Z2*Total!E$108 -> 0 | AE2: 0 | AF2: 0 | AG2: 0 | AI2: =$AH2*Total!C$110 -> 0 | AJ2: =$AH2*Total!D$110 -> 0 | AK2: =$AH2*Total!E$110 -> 0 | AL2: 0.15 | AM2: =$AL2*Total!C$111 -> 0.12 | AN2: =$AL2*Total!D$111 -> 0.0225 | AO2: =$AL2*Total!E$111 -> 0.0075
A3: forestry | C3: =+$B3*Total!C$102 -> 0 | D3: =+$B3*Total!D$102 -> 0 | E3: =+$B3*Total!E$102 -> 0 | G3: =$F3*Total!C$103 -> 0 | H3: =$F3*Total!D$103 -> 0 | I3: =$F3*Total!E$103 -> 0 | K3: =$J3*Total!C$104 -> 0 | L3: =$J3*Total!D$104 -> 0 | M3: =$J3*Total!E$104 -> 0 | O3: =$N3*Total!C$105 -> 0 | P3: =$N3*Total!D$105 -> 0 | Q3: =$N3*Total!E$105 -> 0 | S3: =$R3*Total!C$106 -> 0 | T3: =$R3*Total!D$106 -> 0 | U3: =$R3*Total!E$106 -> 0 | W3: =$V3*Total!C$107 -> 0 | X3: =$V3*Total!D$107 -> 0 | Y3: =$V3*Total!E$107 -> 0 | AA3: =$Z3*Total!C$108 -> 0 | AB3: =$Z3*Total!D$108 -> 0 | AC3: =$Z3*Total!E$108 -> 0 | AE3: 0 | AF3: 0 | AG3: 0 | AI3: =$AH3*Total!C$110 -> 0 | AJ3: =$AH3*Total!D$110 -> 0 | AK3: =$AH3*Total!E$110 -> 0 | AL3: 0.35 | AM3: =$AL3*Total!C$111 -> 0.28 | AN3: =$AL3*Total!D$111 -> 0.0525 | AO3: =$AL3*Total!E$111 -> 0.0175
A4: livestock | C4: =+$B4*Total!C$102 -> 0 | D4: =+$B4*Total!D$102 -> 0 | E4: =+$B4*Total!E$102 -> 0 | G4: =$F4*Total!C$103 -> 0 | H4: =$F4*Total!D$103 -> 0 | I4: =$F4*Total!E$103 -> 0 | K4: =$J4*Total!C$104 -> 0 | L4: =$J4*Total!D$104 -> 0 | M4: =$J4*Total!E$104 -> 0 | O4: =$N4*Total!C$105 -> 0 | P4: =$N4*Total!D$105 -> 0 | Q4: =$N4*Total!E$105 -> 0 | S4: =$R4*Total!C$106 -> 0 | T4: =$R4*Total!D$106 -> 0 | U4: =$R4*Total!E$106 -> 0 | W4: =$V4*Total!C$107 -> 0 | X4: =$V4*Total!D$107 -> 0 | Y4: =$V4*Total!E$107 -> 0 | AA4: =$Z4*Total!C$108 -> 0 | AB4: =$Z4*Total!D$108 -> 0 | AC4: =$Z4*Total!E$108 -> 0 | AE4: 0 | AF4: 0 | AG4: 0 | AI4: =$AH4*Total!C$110 -> 0 | AJ4: =$AH4*Total!D$110 -> 0 | AK4: =$AH4*Total!E$110 -> 0 | AM4: =$AL4*Total!C$111 -> 0 | AN4: =$AL4*Total!D$111 -> 0 | AO4: =$AL4*Total!E$111 -> 0
A5: fishery and aquaculture | C5: =+$B5*Total!C$102 -> 0 | D5: =+$B5*Total!D$102 -> 0 | E5: =+$B5*Total!E$102 -> 0 | G5: =$F5*Total!C$103 -> 0 | H5: =$F5*Total!D$103 -> 0 | I5: =$F5*Total!E$103 -> 0 | K5: =$J5*Total!C$104 -> 0 | L5: =$J5*Total!D$104 -> 0 | M5: =$J5*Total!E$104 -> 0 | O5: =$N5*Total!C$105 -> 0 | P5: =$N5*Total!D$105 -> 0 | Q5: =$N5*Total!E$105 -> 0 | S5: =$R5*Total!C$106 -> 0 | T5: =$R5*Total!D$106 -> 0 | U5: =$R5*Total!E$106 -> 0 | W5: =$V5*Total!C$107 -> 0 | X5: =$V5*Total!D$107 -> 0 | Y5: =$V5*Total!E$107 -> 0 | AA5: =$Z5*Total!C$108 -> 0 | AB5: =$Z5*Total!D$108 -> 0 | AC5: =$Z5*Total!E$108 -> 0 | AE5: 0 | AF5: 0 | AG5: 0 | AI5: =$AH5*Total!C$110 -> 0 | AJ5: =$AH5*Total!D$110 -> 0 | AK5: =$AH5*Total!E$110 -> 0 | AM5: =$AL5*Total!C$111 -> 0 | AN5: =$AL5*Total!D$111 -> 0 | AO5: =$AL5*Total!E$111 -> 0
A6: Extractive activities | C6: =+$B6*Total!C$102 -> 0 | D6: =+$B6*Total!D$102 -> 0 | E6: =+$B6*Total!E$102 -> 0 | G6: =$F6*Total!C$103 -> 0 | H6: =$F6*Total!D$103 -> 0 | I6: =$F6*Total!E$103 -> 0 | K6: =$J6*Total!C$104 -> 0 | L6: =$J6*Total!D$104 -> 0 | M6: =$J6*Total!E$104 -> 0 | O6: =$N6*Total!C$105 -> 0 | P6: =$N6*Total!D$105 -> 0 | Q6: =$N6*Total!E$105 -> 0 | S6: =$R6*Total!C$106 -> 0 | T6: =$R6*Total!D$106 -> 0 | U6: =$R6*Total!E$106 -> 0 | W6: =$V6*Total!C$107 -> 0 | X6: =$V6*Total!D$107 -> 0 | Y6: =$V6*Total!E$107 -> 0 | AA6: =$Z6*Total!C$108 -> 0 | AB6: =$Z6*Total!D$108 -> 0 | AC6: =$Z6*Total!E$108 -> 0 | AE6: 0 | AF6: 0 | AG6: 0 | AI6: =$AH6*Total!C$110 -> 0 | AJ6: =$AH6*Total!D$110 -> 0 | AK6: =$AH6*Total!E$110 -> 0 | AM6: =$AL6*Total!C$111 -> 0 | AN6: =$AL6*Total!D$111 -> 0 | AO6: =$AL6*Total!E$111 -> 0
A7: food manufacturing and beverage | C7: =+$B7*Total!C$102 -> 0 | D7: =+$B7*Total!D$102 -> 0 | E7: =+$B7*Total!E$102 -> 0 | G7: =$F7*Total!C$103 -> 0 | H7: =$F7*Total!D$103 -> 0 | I7: =$F7*Total!E$103 -> 0 | K7: =$J7*Total!C$104 -> 0 | L7: =$J7*Total!D$104 -> 0 | M7: =$J7*Total!E$104 -> 0 | O7: =$N7*Total!C$105 -> 0 | P7: =$N7*Total!D$105 -> 0 | Q7: =$N7*Total!E$105 -> 0 | S7: =$R7*Total!C$106 -> 0 | T7: =$R7*Total!D$106 -> 0 | U7: =$R7*Total!E$106 -> 0 | W7: =$V7*Total!C$107 -> 0 | X7: =$V7*Total!D$107 -> 0 | Y7: =$V7*Total!E$107 -> 0 | AA7: =$Z7*Total!C$108 -> 0 | AB7: =$Z7*Total!D$108 -> 0 | AC7: =$Z7*Total!E$108 -> 0 | AE7: 0 | AF7: 0 | AG7: 0 | AI7: =$AH7*Total!C$110 -> 0 | AJ7: =$AH7*Total!D$110 -> 0 | AK7: =$AH7*Total!E$110 -> 0 | AM7: =$AL7*Total!C$111 -> 0 | AN7: =$AL7*Total!D$111 -> 0 | AO7: =$AL7*Total!E$111 -> 0
A8: textile manufacturing and clothes | C8: =+$B8*Total!C$102 -> 0 | D8: =+$B8*Total!D$102 -> 0 | E8: =+$B8*Total!E$102 -> 0 | G8: =$F8*Total!C$103 -> 0 | H8: =$F8*Total!D$103 -> 0 | I8: =$F8*Total!E$103 -> 0 | K8: =$J8*Total!C$104 -> 0 | L8: =$J8*Total!D$104 -> 0 | M8: =$J8*Total!E$104 -> 0 | O8: =$N8*Total!C$105 -> 0 | P8: =$N8*Total!D$105 -> 0 | Q8: =$N8*Total!E$105 -> 0 | S8: =$R8*Total!C$106 -> 0 | T8: =$R8*Total!D$106 -> 0 | U8: =$R8*Total!E$106 -> 0 | W8: =$V8*Total!C$107 -> 0 | X8: =$V8*Total!D$107 -> 0 | Y8: =$V8*Total!E$107 -> 0 | AA8: =$Z8*Total!C$108 -> 0 | AB8: =$Z8*Total!D$108 -> 0 | AC8: =$Z8*Total!E$108 -> 0 | AE8: 0 | AF8: 0 | AG8: 0 | AI8: =$AH8*Total!C$110 -> 0 | AJ8: =$AH8*Total!D$110 -> 0 | AK8: =$AH8*Total!E$110 -> 0 | AM8: =$AL8*Total!C$111 -> 0 | AN8: =$AL8*Total!D$111 -> 0 | AO8: =$AL8*Total!E$111 -> 0
A9: Wood product manufacturing | C9: =+$B9*Total!C$102 -> 0 | D9: =+$B9*Total!D$102 -> 0 | E9: =+$B9*Total!E$102 -> 0 | F9: 0.03 | G9: =$F9*Total!C$103 -> 0.0075 | H9: =$F9*Total!D$103 -> 0.0075 | I9: =$F9*Total!E$103 -> 0.015 | K9: =$J9*Total!C$104 -> 0 | L9: =$J9*Total!D$104 -> 0 | M9: =$J9*Total!E$104 -> 0 | O9: =$N9*Total!C$105 -> 0 | P9: =$N9*Total!D$105 -> 0 | Q9: =$N9*Total!E$105 -> 0 | S9: =$R9*Total!C$106 -> 0 | T9: =$R9*Total!D$106 -> 0 | U9: =$R9*Total!E$106 -> 0 | W9: =$V9*Total!C$107 -> 0 | X9: =$V9*Total!D$107 -> 0 | Y9: =$V9*Total!E$107 -> 0 | AA9: =$Z9*Total!C$108 -> 0 | AB9: =$Z9*Total!D$108 -> 0 | AC9: =$Z9*Total!E$108 -> 0 | AE9: 0 | AF9: 0 | AG9: 0 | AI9: =$AH9*Total!C$110 -> 0 | AJ9: =$AH9*Total!D$110 -> 0 | AK9: =$AH9*Total!E$110 -> 0 | AM9: =$AL9*Total!C$111 -> 0 | AN9: =$AL9*Total!D$111 -> 0 | AO9: =$AL9*Total!E$111 -> 0
A10: coking and refining production | C10: =+$B10*Total!C$102 -> 0 | D10: =+$B10*Total!D$102 -> 0 | E10: =+$B10*Total!E$102 -> 0 | G10: =$F10*Total!C$103 -> 0 | H10: =$F10*Total!D$103 -> 0 | I10: =$F10*Total!E$103 -> 0 | K10: =$J10*Total!C$104 -> 0 | L10: =$J10*Total!D$104 -> 0 | M10: =$J10*Total!E$104 -> 0 | O10: =$N10*Total!C$105 -> 0 | P10: =$N10*Total!D$105 -> 0 | Q10: =$N10*Total!E$105 -> 0 | S10: =$R10*Total!C$106 -> 0 | T10: =$R10*Total!D$106 -> 0 | U10: =$R10*Total!E$106 -> 0 | W10: =$V10*Total!C$107 -> 0 | X10: =$V10*Total!D$107 -> 0 | Y10: =$V10*Total!E$107 -> 0 | AA10: =$Z10*Total!C$108 -> 0 | AB10: =$Z10*Total!D$108 -> 0 | AC10: =$Z10*Total!E$108 -> 0 | AE10: 0 | AF10: 0 | AG10: 0 | AI10: =$AH10*Total!C$110 -> 0 | AJ10: =$AH10*Total!D$110 -> 0 | AK10: =$AH10*Total!E$110 -> 0 | AM10: =$AL10*Total!C$111 -> 0 | AN10: =$AL10*Total!D$111 -> 0 | AO10: =$AL10*Total!E$111 -> 0
A11: chemical products | C11: =+$B11*Total!C$102 -> 0 | D11: =+$B11*Total!D$102 -> 0 | E11: =+$B11*Total!E$102 -> 0 | G11: =$F11*Total!C$103 -> 0 | H11: =$F11*Total!D$103 -> 0 | I11: =$F11*Total!E$103 -> 0 | K11: =$J11*Total!C$104 -> 0 | L11: =$J11*Total!D$104 -> 0 | M11: =$J11*Total!E$104 -> 0 | O11: =$N11*Total!C$105 -> 0 | P11: =$N11*Total!D$105 -> 0 | Q11: =$N11*Total!E$105 -> 0 | R11: 0.1 | S11: =$R11*Total!C$106 -> 0.002 | T11: =$R11*Total!D$106 -> 0.098 | U11: =$R11*Total!E$106 -> 0 | W11: =$V11*Total!C$107 -> 0 | X11: =$V11*Total!D$107 -> 0 | Y11: =$V11*Total!E$107 -> 0 | Z11: 0.04 | AA11: =$Z11*Total!C$108 -> 0.028 | AB11: =$Z11*Total!D$108 -> 0.012 | AC11: =$Z11*Total!E$108 -> 0 | AD11: 0.04 | AE11: =+$AD11*Total!C$109 -> 0.028 | AF11: =+$AD11*Total!D$109 -> 0.012 | AG11: =+$AD11*Total!E$109 -> 0 | AI11: =$AH11*Total!C$110 -> 0 | AJ11: =$AH11*Total!D$110 -> 0 | AK11: =$AH11*Total!E$110 -> 0 | AM11: =$AL11*Total!C$111 -> 0 | AN11: =$AL11*Total!D$111 -> 0 | AO11: =$AL11*Total!E$111 -> 0
A12: pharmaceutical products | C12: =+$B12*Total!C$102 -> 0 | D12: =+$B12*Total!D$102 -> 0 | E12: =+$B12*Total!E$102 -> 0 | G12: =$F12*Total!C$103 -> 0 | H12: =$F12*Total!D$103 -> 0 | I12: =$F12*Total!E$103 -> 0 | K12: =$J12*Total!C$104 -> 0 | L12: =$J12*Total!D$104 -> 0 | M12: =$J12*Total!E$104 -> 0 | O12: =$N12*Total!C$105 -> 0 | P12: =$N12*Total!D$105 -> 0 | Q12: =$N12*Total!E$105 -> 0 | S12: =$R12*Total!C$106 -> 0 | T12: =$R12*Total!D$106 -> 0 | U12: =$R12*Total!E$106 -> 0 | W12: =$V12*Total!C$107 -> 0 | X12: =$V12*Total!D$107 -> 0 | Y12: =$V12*Total!E$107 -> 0 | AA12: =$Z12*Total!C$108 -> 0 | AB12: =$Z12*Total!D$108 -> 0 | AC12: =$Z12*Total!E$108 -> 0 | AE12: 0 | AF12: 0 | AG12: 0 | AI12: =$AH12*Total!C$110 -> 0 | AJ12: =$AH12*Total!D$110 -> 0 | AK12: =$AH12*Total!E$110 -> 0 | AM12: =$AL12*Total!C$111 -> 0 | AN12: =$AL12*Total!D$111 -> 0 | AO12: =$AL12*Total!E$111 -> 0
A13: rubber manufacturing | C13: =+$B13*Total!C$102 -> 0 | D13: =+$B13*Total!D$102 -> 0 | E13: =+$B13*Total!E$102 -> 0 | G13: =$F13*Total!C$103 -> 0 | H13: =$F13*Total!D$103 -> 0 | I13: =$F13*Total!E$103 -> 0 | K13: =$J13*Total!C$104 -> 0 | L13: =$J13*Total!D$104 -> 0 | M13: =$J13*Total!E$104 -> 0 | O13: =$N13*Total!C$105 -> 0 | P13: =$N13*Total!D$105 -> 0 | Q13: =$N13*Total!E$105 -> 0 | S13: =$R13*Total!C$106 -> 0 | T13: =$R13*Total!D$106 -> 0 | U13: =$R13*Total!E$106 -> 0 | W13: =$V13*Total!C$107 -> 0 | X13: =$V13*Total!D$107 -> 0 | Y13: =$V13*Total!E$107 -> 0 | AA13: =$Z13*Total!C$108 -> 0 | AB13: =$Z13*Total!D$108 -> 0 | AC13: =$Z13*Total!E$108 -> 0 | AE13: 0 | AF13: 0 | AG13: 0 | AI13: =$AH13*Total!C$110 -> 0 | AJ13: =$AH13*Total!D$110 -> 0 | AK13: =$AH13*Total!E$110 -> 0 | AM13: =$AL13*Total!C$111 -> 0 | AN13: =$AL13*Total!D$111 -> 0 | AO13: =$AL13*Total!E$111 -> 0
A14: metalwork manufacturing | B14: 0.059 | C14: =+$B14*Total!C$102 -> 0.00295 | D14: =+$B14*Total!D$102 -> 0.0531 | E14: =+$B14*Total!E$102 -> 0.00295 | G14: =$F14*Total!C$103 -> 0 | H14: =$F14*Total!D$103 -> 0 | I14: =$F14*Total!E$103 -> 0 | K14: =$J14*Total!C$104 -> 0 | L14: =$J14*Total!D$104 -> 0 | M14: =$J14*Total!E$104 -> 0 | N14: 0.12 | O14: =$N14*Total!C$105 -> 0.012 | P14: =$N14*Total!D$105 -> 0.108 | Q14: =$N14*Total!E$105 -> 0 | R14: 0.15 | S14: =$R14*Total!C$106 -> 0.003 | T14: =$R14*Total!D$106 -> 0.147 | U14: =$R14*Total!E$106 -> 0 | W14: =$V14*Total!C$107 -> 0 | X14: =$V14*Total!D$107 -> 0 | Y14: =$V14*Total!E$107 -> 0 | AA14: =$Z14*Total!C$108 -> 0 | AB14: =$Z14*Total!D$108 -> 0 | AC14: =$Z14*Total!E$108 -> 0 | AE14: 0 | AF14: 0 | AG14: 0 | AI14: =$AH14*Total!C$110 -> 0 | AJ14: =$AH14*Total!D$110 -> 0 | AK14: =$AH14*Total!E$110 -> 0 | AM14: =$AL14*Total!C$111 -> 0 | AN14: =$AL14*Total!D$111 -> 0 | AO14: =$AL14*Total!E$111 -> 0
A15: Manufacture of computer, electronic and optical products | B15: 0.0111 | C15: =+$B15*Total!C$102 -> 0.000555 | D15: =+$B15*Total!D$102 -> 0.00999 | E15: =+$B15*Total!E$102 -> 0.000555 | G15: =$F15*Total!C$103 -> 0 | H15: =$F15*Total!D$103 -> 0 | I15: =$F15*Total!E$103 -> 0 | K15: =$J15*Total!C$104 -> 0 | L15: =$J15*Total!D$104 -> 0 | M15: =$J15*Total!E$104 -> 0 | O15: =$N15*Total!C$105 -> 0 | P15: =$N15*Total!D$105 -> 0 | Q15: =$N15*Total!E$105 -> 0 | S15: =$R15*Total!C$106 -> 0 | T15: =$R15*Total!D$106 -> 0 | U15: =$R15*Total!E$106 -> 0 | W15: =$V15*Total!C$107 -> 0 | X15: =$V15*Total!D$107 -> 0 | Y15: =$V15*Total!E$107 -> 0 | AA15: =$Z15*Total!C$108 -> 0 | AB15: =$Z15*Total!D$108 -> 0 | AC15: =$Z15*Total!E$108 -> 0 | AE15: 0 | AF15: 0 | AG15: 0 | AI15: =$AH15*Total!C$110 -> 0 | AJ15: =$AH15*Total!D$110 -> 0 | AK15: =$AH15*Total!E$110 -> 0 | AM15: =$AL15*Total!C$111 -> 0 | AN15: =$AL15*Total!D$111 -> 0 | AO15: =$AL15*Total!E$111 -> 0
A16: electrical equipment manufacturing | B16: 0.0872 | C16: =+$B16*Total!C$102 -> 0.00436 | D16: =+$B16*Total!D$102 -> 0.07848 | E16: =+$B16*Total!E$102 -> 0.00436 | F16: 0.15 | G16: =$F16*Total!C$103 -> 0.0375 | H16: =$F16*Total!D$103 -> 0.0375 | I16: =$F16*Total!E$103 -> 0.075 | J16: 0.08 | K16: =$J16*Total!C$104 -> 0.012 | L16: =$J16*Total!D$104 -> 0.028 | M16: =$J16*Total!E$104 -> 0.04 | N16: 0.08 | O16: =$N16*Total!C$105 -> 0.008 | P16: =$N16*Total!D$105 -> 0.072 | Q16: =$N16*Total!E$105 -> 0 | S16: =$R16*Total!C$106 -> 0 | T16: =$R16*Total!D$106 -> 0 | U16: =$R16*Total!E$106 -> 0 | W16: =$V16*Total!C$107 -> 0 | X16: =$V16*Total!D$107 -> 0 | Y16: =$V16*Total!E$107 -> 0 | AA16: =$Z16*Total!C$108 -> 0 | AB16: =$Z16*Total!D$108 -> 0 | AC16: =$Z16*Total!E$108 -> 0 | AE16: 0 | AF16: 0 | AG16: 0 | AI16: =$AH16*Total!C$110 -> 0 | AJ16: =$AH16*Total!D$110 -> 0 | AK16: =$AH16*Total!E$110 -> 0 | AM16: =$AL16*Total!C$111 -> 0 | AN16: =$AL16*Total!D$111 -> 0 | AO16: =$AL16*Total!E$111 -> 0
A17: machinery and equipment manufacturing | B17: 0.0772 | C17: =+$B17*Total!C$102 -> 0.00386 | D17: =+$B17*Total!D$102 -> 0.06948 | E17: =+$B17*Total!E$102 -> 0.00386 | F17: 0.05 | G17: =$F17*Total!C$103 -> 0.0125 | H17: =$F17*Total!D$103 -> 0.0125 | I17: =$F17*Total!E$103 -> 0.025 | K17: =$J17*Total!C$104 -> 0 | L17: =$J17*Total!D$104 -> 0 | M17: =$J17*Total!E$104 -> 0 | N17: 0.25 | O17: =$N17*Total!C$105 -> 0.025 | P17: =$N17*Total!D$105 -> 0.225 | Q17: =$N17*Total!E$105 -> 0 | R17: 0.3 | S17: =$R17*Total!C$106 -> 0.006 | T17: =$R17*Total!D$106 -> 0.294 | U17: =$R17*Total!E$106 -> 0 | V17: 0.2 | W17: =$V17*Total!C$107 -> 0.1 | X17: =$V17*Total!D$107 -> 0.1 | Y17: =$V17*Total!E$107 -> 0 | Z17: 0.15 | AA17: =$Z17*Total!C$108 -> 0.105 | AB17: =$Z17*Total!D$108 -> 0.045 | AC17: =$Z17*Total!E$108 -> 0 | AD17: 0.15 | AE17: =+$AD17*Total!C$109 -> 0.105 | AF17: =+$AD17*Total!D$109 -> 0.045 | AG17: =+$AD17*Total!E$109 -> 0 | AI17: =$AH17*Total!C$110 -> 0 | AJ17: =$AH17*Total!D$110 -> 0 | AK17: =$AH17*Total!E$110 -> 0 | AM17: =$AL17*Total!C$111 -> 0 | AN17: =$AL17*Total!D$111 -> 0 | AO17: =$AL17*Total!E$111 -> 0
A18: transport equipment manufacturing | B18: 0.0282 | C18: =+$B18*Total!C$102 -> 0.00141 | D18: =+$B18*Total!D$102 -> 0.02538 | E18: =+$B18*Total!E$102 -> 0.00141 | G18: =$F18*Total!C$103 -> 0 | H18: =$F18*Total!D$103 -> 0 | I18: =$F18*Total!E$103 -> 0 | J18: 0.15 | K18: =$J18*Total!C$104 -> 0.0225 | L18: =$J18*Total!D$104 -> 0.0525 | M18: =$J18*Total!E$104 -> 0.075 | O18: =$N18*Total!C$105 -> 0 | P18: =$N18*Total!D$105 -> 0 | Q18: =$N18*Total!E$105 -> 0 | S18: =$R18*Total!C$106 -> 0 | T18: =$R18*Total!D$106 -> 0 | U18: =$R18*Total!E$106 -> 0 | V18: 0.1 | W18: =$V18*Total!C$107 -> 0.05 | X18: =$V18*Total!D$107 -> 0.05 | Y18: =$V18*Total!E$107 -> 0 | AA18: =$Z18*Total!C$108 -> 0 | AB18: =$Z18*Total!D$108 -> 0 | AC18: =$Z18*Total!E$108 -> 0 | AE18: 0 | AF18: 0 | AG18: 0 | AI18: =$AH18*Total!C$110 -> 0 | AJ18: =$AH18*Total!D$110 -> 0 | AK18: =$AH18*Total!E$110 -> 0 | AM18: =$AL18*Total!C$111 -> 0 | AN18: =$AL18*Total!D$111 -> 0 | AO18: =$AL18*Total!E$111 -> 0
A19: other manufacturing | C19: =+$B19*Total!C$102 -> 0 | D19: =+$B19*Total!D$102 -> 0 | E19: =+$B19*Total!E$102 -> 0 | G19: =$F19*Total!C$103 -> 0 | H19: =$F19*Total!D$103 -> 0 | I19: =$F19*Total!E$103 -> 0 | K19: =$J19*Total!C$104 -> 0 | L19: =$J19*Total!D$104 -> 0 | M19: =$J19*Total!E$104 -> 0 | O19: =$N19*Total!C$105 -> 0 | P19: =$N19*Total!D$105 -> 0 | Q19: =$N19*Total!E$105 -> 0 | S19: =$R19*Total!C$106 -> 0 | T19: =$R19*Total!D$106 -> 0 | U19: =$R19*Total!E$106 -> 0 | W19: =$V19*Total!C$107 -> 0 | X19: =$V19*Total!D$107 -> 0 | Y19: =$V19*Total!E$107 -> 0 | AA19: =$Z19*Total!C$108 -> 0 | AB19: =$Z19*Total!D$108 -> 0 | AC19: =$Z19*Total!E$108 -> 0 | AE19: 0 | AF19: 0 | AG19: 0 | AI19: =$AH19*Total!C$110 -> 0 | AJ19: =$AH19*Total!D$110 -> 0 | AK19: =$AH19*Total!E$110 -> 0 | AM19: =$AL19*Total!C$111 -> 0 | AN19: =$AL19*Total!D$111 -> 0 | AO19: =$AL19*Total!E$111 -> 0
A20: electricity generation - coal | C20: =+$B20*Total!C$102 -> 0 | D20: =+$B20*Total!D$102 -> 0 | E20: =+$B20*Total!E$102 -> 0 | G20: =$F20*Total!C$103 -> 0 | H20: =$F20*Total!D$103 -> 0 | I20: =$F20*Total!E$103 -> 0 | K20: =$J20*Total!C$104 -> 0 | L20: =$J20*Total!D$104 -> 0 | M20: =$J20*Total!E$104 -> 0 | O20: =$N20*Total!C$105 -> 0 | P20: =$N20*Total!D$105 -> 0 | Q20: =$N20*Total!E$105 -> 0 | S20: =$R20*Total!C$106 -> 0 | T20: =$R20*Total!D$106 -> 0 | U20: =$R20*Total!E$106 -> 0 | W20: =$V20*Total!C$107 -> 0 | X20: =$V20*Total!D$107 -> 0 | Y20: =$V20*Total!E$107 -> 0 | AA20: =$Z20*Total!C$108 -> 0 | AB20: =$Z20*Total!D$108 -> 0 | AC20: =$Z20*Total!E$108 -> 0 | AE20: 0 | AF20: 0 | AG20: 0 | AI20: =$AH20*Total!C$110 -> 0 | AJ20: =$AH20*Total!D$110 -> 0 | AK20: =$AH20*Total!E$110 -> 0 | AM20: =$AL20*Total!C$111 -> 0 | AN20: =$AL20*Total!D$111 -> 0 | AO20: =$AL20*Total!E$111 -> 0
A21: electricity generation - oil | C21: =+$B21*Total!C$102 -> 0 | D21: =+$B21*Total!D$102 -> 0 | E21: =+$B21*Total!E$102 -> 0 | G21: =$F21*Total!C$103 -> 0 | H21: =$F21*Total!D$103 -> 0 | I21: =$F21*Total!E$103 -> 0 | K21: =$J21*Total!C$104 -> 0 | L21: =$J21*Total!D$104 -> 0 | M21: =$J21*Total!E$104 -> 0 | O21: =$N21*Total!C$105 -> 0 | P21: =$N21*Total!D$105 -> 0 | Q21: =$N21*Total!E$105 -> 0 | S21: =$R21*Total!C$106 -> 0 | T21: =$R21*Total!D$106 -> 0 | U21: =$R21*Total!E$106 -> 0 | W21: =$V21*Total!C$107 -> 0 | X21: =$V21*Total!D$107 -> 0 | Y21: =$V21*Total!E$107 -> 0 | AA21: =$Z21*Total!C$108 -> 0 | AB21: =$Z21*Total!D$108 -> 0 | AC21: =$Z21*Total!E$108 -> 0 | AE21: 0 | AF21: 0 | AG21: 0 | AI21: =$AH21*Total!C$110 -> 0 | AJ21: =$AH21*Total!D$110 -> 0 | AK21: =$AH21*Total!E$110 -> 0 | AM21: =$AL21*Total!C$111 -> 0 | AN21: =$AL21*Total!D$111 -> 0 | AO21: =$AL21*Total!E$111 -> 0
A22: electricity generation - natural gas | C22: =+$B22*Total!C$102 -> 0 | D22: =+$B22*Total!D$102 -> 0 | E22: =+$B22*Total!E$102 -> 0 | G22: =$F22*Total!C$103 -> 0 | H22: =$F22*Total!D$103 -> 0 | I22: =$F22*Total!E$103 -> 0 | K22: =$J22*Total!C$104 -> 0 | L22: =$J22*Total!D$104 -> 0 | M22: =$J22*Total!E$104 -> 0 | O22: =$N22*Total!C$105 -> 0 | P22: =$N22*Total!D$105 -> 0 | Q22: =$N22*Total!E$105 -> 0 | S22: =$R22*Total!C$106 -> 0 | T22: =$R22*Total!D$106 -> 0 | U22: =$R22*Total!E$106 -> 0 | W22: =$V22*Total!C$107 -> 0 | X22: =$V22*Total!D$107 -> 0 | Y22: =$V22*Total!E$107 -> 0 | AA22: =$Z22*Total!C$108 -> 0 | AB22: =$Z22*Total!D$108 -> 0 | AC22: =$Z22*Total!E$108 -> 0 | AE22: 0 | AF22: 0 | AG22: 0 | AI22: =$AH22*Total!C$110 -> 0 | AJ22: =$AH22*Total!D$110 -> 0 | AK22: =$AH22*Total!E$110 -> 0 | AM22: =$AL22*Total!C$111 -> 0 | AN22: =$AL22*Total!D$111 -> 0 | AO22: =$AL22*Total!E$111 -> 0
A23: electricity generation - hydro | C23: =+$B23*Total!C$102 -> 0 | D23: =+$B23*Total!D$102 -> 0 | E23: =+$B23*Total!E$102 -> 0 | G23: =$F23*Total!C$103 -> 0 | H23: =$F23*Total!D$103 -> 0 | I23: =$F23*Total!E$103 -> 0 | K23: =$J23*Total!C$104 -> 0 | L23: =$J23*Total!D$104 -> 0 | M23: =$J23*Total!E$104 -> 0 | O23: =$N23*Total!C$105 -> 0 | P23: =$N23*Total!D$105 -> 0 | Q23: =$N23*Total!E$105 -> 0 | S23: =$R23*Total!C$106 -> 0 | T23: =$R23*Total!D$106 -> 0 | U23: =$R23*Total!E$106 -> 0 | W23: =$V23*Total!C$107 -> 0 | X23: =$V23*Total!D$107 -> 0 | Y23: =$V23*Total!E$107 -> 0 | AA23: =$Z23*Total!C$108 -> 0 | AB23: =$Z23*Total!D$108 -> 0 | AC23: =$Z23*Total!E$108 -> 0 | AE23: 0 | AF23: 0 | AG23: 0 | AI23: =$AH23*Total!C$110 -> 0 | AJ23: =$AH23*Total!D$110 -> 0 | AK23: =$AH23*Total!E$110 -> 0 | AM23: =$AL23*Total!C$111 -> 0 | AN23: =$AL23*Total!D$111 -> 0 | AO23: =$AL23*Total!E$111 -> 0
A24: electricity generation - wind | C24: =+$B24*Total!C$102 -> 0 | D24: =+$B24*Total!D$102 -> 0 | E24: =+$B24*Total!E$102 -> 0 | G24: =$F24*Total!C$103 -> 0 | H24: =$F24*Total!D$103 -> 0 | I24: =$F24*Total!E$103 -> 0 | K24: =$J24*Total!C$104 -> 0 | L24: =$J24*Total!D$104 -> 0 | M24: =$J24*Total!E$104 -> 0 | O24: =$N24*Total!C$105 -> 0 | P24: =$N24*Total!D$105 -> 0 | Q24: =$N24*Total!E$105 -> 0 | S24: =$R24*Total!C$106 -> 0 | T24: =$R24*Total!D$106 -> 0 | U24: =$R24*Total!E$106 -> 0 | W24: =$V24*Total!C$107 -> 0 | X24: =$V24*Total!D$107 -> 0 | Y24: =$V24*Total!E$107 -> 0 | AA24: =$Z24*Total!C$108 -> 0 | AB24: =$Z24*Total!D$108 -> 0 | AC24: =$Z24*Total!E$108 -> 0 | AE24: 0 | AF24: 0 | AG24: 0 | AI24: =$AH24*Total!C$110 -> 0 | AJ24: =$AH24*Total!D$110 -> 0 | AK24: =$AH24*Total!E$110 -> 0 | AM24: =$AL24*Total!C$111 -> 0 | AN24: =$AL24*Total!D$111 -> 0 | AO24: =$AL24*Total!E$111 -> 0
A25: electricity generation - solar | C25: =+$B25*Total!C$102 -> 0 | D25: =+$B25*Total!D$102 -> 0 | E25: =+$B25*Total!E$102 -> 0 | G25: =$F25*Total!C$103 -> 0 | H25: =$F25*Total!D$103 -> 0 | I25: =$F25*Total!E$103 -> 0 | K25: =$J25*Total!C$104 -> 0 | L25: =$J25*Total!D$104 -> 0 | M25: =$J25*Total!E$104 -> 0 | O25: =$N25*Total!C$105 -> 0 | P25: =$N25*Total!D$105 -> 0 | Q25: =$N25*Total!E$105 -> 0 | S25: =$R25*Total!C$106 -> 0 | T25: =$R25*Total!D$106 -> 0 | U25: =$R25*Total!E$106 -> 0 | W25: =$V25*Total!C$107 -> 0 | X25: =$V25*Total!D$107 -> 0 | Y25: =$V25*Total!E$107 -> 0 | AA25: =$Z25*Total!C$108 -> 0 | AB25: =$Z25*Total!D$108 -> 0 | AC25: =$Z25*Total!E$108 -> 0 | AE25: 0 | AF25: 0 | AG25: 0 | AI25: =$AH25*Total!C$110 -> 0 | AJ25: =$AH25*Total!D$110 -> 0 | AK25: =$AH25*Total!E$110 -> 0 | AM25: =$AL25*Total!C$111 -> 0 | AN25: =$AL25*Total!D$111 -> 0 | AO25: =$AL25*Total!E$111 -> 0
A26: electricity generation - other sources | C26: =+$B26*Total!C$102 -> 0 | D26: =+$B26*Total!D$102 -> 0 | E26: =+$B26*Total!E$102 -> 0 | G26: =$F26*Total!C$103 -> 0 | H26: =$F26*Total!D$103 -> 0 | I26: =$F26*Total!E$103 -> 0 | K26: =$J26*Total!C$104 -> 0 | L26: =$J26*Total!D$104 -> 0 | M26: =$J26*Total!E$104 -> 0 | O26: =$N26*Total!C$105 -> 0 | P26: =$N26*Total!D$105 -> 0 | Q26: =$N26*Total!E$105 -> 0 | S26: =$R26*Total!C$106 -> 0 | T26: =$R26*Total!D$106 -> 0 | U26: =$R26*Total!E$106 -> 0 | W26: =$V26*Total!C$107 -> 0 | X26: =$V26*Total!D$107 -> 0 | Y26: =$V26*Total!E$107 -> 0 | AA26: =$Z26*Total!C$108 -> 0 | AB26: =$Z26*Total!D$108 -> 0 | AC26: =$Z26*Total!E$108 -> 0 | AE26: 0 | AF26: 0 | AG26: 0 | AI26: =$AH26*Total!C$110 -> 0 | AJ26: =$AH26*Total!D$110 -> 0 | AK26: =$AH26*Total!E$110 -> 0 | AM26: =$AL26*Total!C$111 -> 0 | AN26: =$AL26*Total!D$111 -> 0 | AO26: =$AL26*Total!E$111 -> 0
A27: electricity transmission and distribution | C27: =+$B27*Total!C$102 -> 0 | D27: =+$B27*Total!D$102 -> 0 | E27: =+$B27*Total!E$102 -> 0 | G27: =$F27*Total!C$103 -> 0 | H27: =$F27*Total!D$103 -> 0 | I27: =$F27*Total!E$103 -> 0 | K27: =$J27*Total!C$104 -> 0 | L27: =$J27*Total!D$104 -> 0 | M27: =$J27*Total!E$104 -> 0 | O27: =$N27*Total!C$105 -> 0 | P27: =$N27*Total!D$105 -> 0 | Q27: =$N27*Total!E$105 -> 0 | S27: =$R27*Total!C$106 -> 0 | T27: =$R27*Total!D$106 -> 0 | U27: =$R27*Total!E$106 -> 0 | W27: =$V27*Total!C$107 -> 0 | X27: =$V27*Total!D$107 -> 0 | Y27: =$V27*Total!E$107 -> 0 | AA27: =$Z27*Total!C$108 -> 0 | AB27: =$Z27*Total!D$108 -> 0 | AC27: =$Z27*Total!E$108 -> 0 | AE27: 0 | AF27: 0 | AG27: 0 | AI27: =$AH27*Total!C$110 -> 0 | AJ27: =$AH27*Total!D$110 -> 0 | AK27: =$AH27*Total!E$110 -> 0 | AM27: =$AL27*Total!C$111 -> 0 | AN27: =$AL27*Total!D$111 -> 0 | AO27: =$AL27*Total!E$111 -> 0
A28: gas manufacture, distribution | C28: =+$B28*Total!C$102 -> 0 | D28: =+$B28*Total!D$102 -> 0 | E28: =+$B28*Total!E$102 -> 0 | G28: =$F28*Total!C$103 -> 0 | H28: =$F28*Total!D$103 -> 0 | I28: =$F28*Total!E$103 -> 0 | K28: =$J28*Total!C$104 -> 0 | L28: =$J28*Total!D$104 -> 0 | M28: =$J28*Total!E$104 -> 0 | O28: =$N28*Total!C$105 -> 0 | P28: =$N28*Total!D$105 -> 0 | Q28: =$N28*Total!E$105 -> 0 | S28: =$R28*Total!C$106 -> 0 | T28: =$R28*Total!D$106 -> 0 | U28: =$R28*Total!E$106 -> 0 | W28: =$V28*Total!C$107 -> 0 | X28: =$V28*Total!D$107 -> 0 | Y28: =$V28*Total!E$107 -> 0 | AA28: =$Z28*Total!C$108 -> 0 | AB28: =$Z28*Total!D$108 -> 0 | AC28: =$Z28*Total!E$108 -> 0 | AE28: 0 | AF28: 0 | AG28: 0 | AI28: =$AH28*Total!C$110 -> 0 | AJ28: =$AH28*Total!D$110 -> 0 | AK28: =$AH28*Total!E$110 -> 0 | AM28: =$AL28*Total!C$111 -> 0 | AN28: =$AL28*Total!D$111 -> 0 | AO28: =$AL28*Total!E$111 -> 0
A29: water supply and sewerage | C29: =+$B29*Total!C$102 -> 0 | D29: =+$B29*Total!D$102 -> 0 | E29: =+$B29*Total!E$102 -> 0 | G29: =$F29*Total!C$103 -> 0 | H29: =$F29*Total!D$103 -> 0 | I29: =$F29*Total!E$103 -> 0 | K29: =$J29*Total!C$104 -> 0 | L29: =$J29*Total!D$104 -> 0 | M29: =$J29*Total!E$104 -> 0 | O29: =$N29*Total!C$105 -> 0 | P29: =$N29*Total!D$105 -> 0 | Q29: =$N29*Total!E$105 -> 0 | S29: =$R29*Total!C$106 -> 0 | T29: =$R29*Total!D$106 -> 0 | U29: =$R29*Total!E$106 -> 0 | W29: =$V29*Total!C$107 -> 0 | X29: =$V29*Total!D$107 -> 0 | Y29: =$V29*Total!E$107 -> 0 | Z29: 0.12 | AA29: =$Z29*Total!C$108 -> 0.084 | AB29: =$Z29*Total!D$108 -> 0.036 | AC29: =$Z29*Total!E$108 -> 0 | AD29: 0.12 | AE29: =+$AD29*Total!C$109 -> 0.084 | AF29: =+$AD29*Total!D$109 -> 0.036 | AG29: =+$AD29*Total!E$109 -> 0 | AI29: =$AH29*Total!C$110 -> 0 | AJ29: =$AH29*Total!D$110 -> 0 | AK29: =$AH29*Total!E$110 -> 0 | AM29: =$AL29*Total!C$111 -> 0 | AN29: =$AL29*Total!D$111 -> 0 | AO29: =$AL29*Total!E$111 -> 0
A30: construction | B30: 0.2252 | C30: =+$B30*Total!C$102 -> 0.01126 | D30: =+$B30*Total!D$102 -> 0.20268 | E30: =+$B30*Total!E$102 -> 0.01126 | F30: 0.25 | G30: =$F30*Total!C$103 -> 0.0625 | H30: =$F30*Total!D$103 -> 0.0625 | I30: =$F30*Total!E$103 -> 0.125 | J30: 0.07 | K30: =$J30*Total!C$104 -> 0.0105 | L30: =$J30*Total!D$104 -> 0.0245 | M30: =$J30*Total!E$104 -> 0.035 | N30: 0.1 | O30: =$N30*Total!C$105 -> 0.01 | P30: =$N30*Total!D$105 -> 0.09 | Q30: =$N30*Total!E$105 -> 0 | R30: 0.2 | S30: =$R30*Total!C$106 -> 0.004 | T30: =$R30*Total!D$106 -> 0.196 | U30: =$R30*Total!E$106 -> 0 | V30: 0.4 | W30: =$V30*Total!C$107 -> 0.2 | X30: =$V30*Total!D$107 -> 0.2 | Y30: =$V30*Total!E$107 -> 0 | Z30: 0.55 | AA30: =$Z30*Total!C$108 -> 0.385 | AB30: =$Z30*Total!D$108 -> 0.165 | AC30: =$Z30*Total!E$108 -> 0 | AD30: 0.55 | AE30: =+$AD30*Total!C$109 -> 0.385 | AF30: =+$AD30*Total!D$109 -> 0.165 | AG30: =+$AD30*Total!E$109 -> 0 | AH30: 1 | AI30: =$AH30*Total!C$110 -> 0 | AJ30: =$AH30*Total!D$110 -> 1 | AK30: =$AH30*Total!E$110 -> 0 | AL30: 0.08 | AM30: =$AL30*Total!C$111 -> 0.064 | AN30: =$AL30*Total!D$111 -> 0.012 | AO30: =$AL30*Total!E$111 -> 0.004
A31: repair of motor vehicles and motorcycles | C31: =+$B31*Total!C$102 -> 0 | D31: =+$B31*Total!D$102 -> 0 | E31: =+$B31*Total!E$102 -> 0 | G31: =$F31*Total!C$103 -> 0 | H31: =$F31*Total!D$103 -> 0 | I31: =$F31*Total!E$103 -> 0 | J31: 0.1 | K31: =$J31*Total!C$104 -> 0.015 | L31: =$J31*Total!D$104 -> 0.035 | M31: =$J31*Total!E$104 -> 0.05 | O31: =$N31*Total!C$105 -> 0 | P31: =$N31*Total!D$105 -> 0 | Q31: =$N31*Total!E$105 -> 0 | S31: =$R31*Total!C$106 -> 0 | T31: =$R31*Total!D$106 -> 0 | U31: =$R31*Total!E$106 -> 0 | W31: =$V31*Total!C$107 -> 0 | X31: =$V31*Total!D$107 -> 0 | Y31: =$V31*Total!E$107 -> 0 | AA31: =$Z31*Total!C$108 -> 0 | AB31: =$Z31*Total!D$108 -> 0 | AC31: =$Z31*Total!E$108 -> 0 | AE31: 0 | AF31: 0 | AG31: 0 | AI31: =$AH31*Total!C$110 -> 0 | AJ31: =$AH31*Total!D$110 -> 0 | AK31: =$AH31*Total!E$110 -> 0 | AM31: =$AL31*Total!C$111 -> 0 | AN31: =$AL31*Total!D$111 -> 0 | AO31: =$AL31*Total!E$111 -> 0
A32: transport and warehouse | C32: =+$B32*Total!C$102 -> 0 | D32: =+$B32*Total!D$102 -> 0 | E32: =+$B32*Total!E$102 -> 0 | G32: =$F32*Total!C$103 -> 0 | H32: =$F32*Total!D$103 -> 0 | I32: =$F32*Total!E$103 -> 0 | K32: =$J32*Total!C$104 -> 0 | L32: =$J32*Total!D$104 -> 0 | M32: =$J32*Total!E$104 -> 0 | O32: =$N32*Total!C$105 -> 0 | P32: =$N32*Total!D$105 -> 0 | Q32: =$N32*Total!E$105 -> 0 | S32: =$R32*Total!C$106 -> 0 | T32: =$R32*Total!D$106 -> 0 | U32: =$R32*Total!E$106 -> 0 | W32: =$V32*Total!C$107 -> 0 | X32: =$V32*Total!D$107 -> 0 | Y32: =$V32*Total!E$107 -> 0 | AA32: =$Z32*Total!C$108 -> 0 | AB32: =$Z32*Total!D$108 -> 0 | AC32: =$Z32*Total!E$108 -> 0 | AE32: 0 | AF32: 0 | AG32: 0 | AI32: =$AH32*Total!C$110 -> 0 | AJ32: =$AH32*Total!D$110 -> 0 | AK32: =$AH32*Total!E$110 -> 0 | AL32: 0.07 | AM32: =$AL32*Total!C$111 -> 0.056 | AN32: =$AL32*Total!D$111 -> 0.0105 | AO32: =$AL32*Total!E$111 -> 0.0035
A33: Accommodation, Food and service activities | C33: =+$B33*Total!C$102 -> 0 | D33: =+$B33*Total!D$102 -> 0 | E33: =+$B33*Total!E$102 -> 0 | G33: =$F33*Total!C$103 -> 0 | H33: =$F33*Total!D$103 -> 0 | I33: =$F33*Total!E$103 -> 0 | K33: =$J33*Total!C$104 -> 0 | L33: =$J33*Total!D$104 -> 0 | M33: =$J33*Total!E$104 -> 0 | O33: =$N33*Total!C$105 -> 0 | P33: =$N33*Total!D$105 -> 0 | Q33: =$N33*Total!E$105 -> 0 | S33: =$R33*Total!C$106 -> 0 | T33: =$R33*Total!D$106 -> 0 | U33: =$R33*Total!E$106 -> 0 | W33: =$V33*Total!C$107 -> 0 | X33: =$V33*Total!D$107 -> 0 | Y33: =$V33*Total!E$107 -> 0 | AA33: =$Z33*Total!C$108 -> 0 | AB33: =$Z33*Total!D$108 -> 0 | AC33: =$Z33*Total!E$108 -> 0 | AE33: 0 | AF33: 0 | AG33: 0 | AI33: =$AH33*Total!C$110 -> 0 | AJ33: =$AH33*Total!D$110 -> 0 | AK33: =$AH33*Total!E$110 -> 0 | AM33: =$AL33*Total!C$111 -> 0 | AN33: =$AL33*Total!D$111 -> 0 | AO33: =$AL33*Total!E$111 -> 0
A34: Information and communication | C34: =+$B34*Total!C$102 -> 0 | D34: =+$B34*Total!D$102 -> 0 | E34: =+$B34*Total!E$102 -> 0 | G34: =$F34*Total!C$103 -> 0 | H34: =$F34*Total!D$103 -> 0 | I34: =$F34*Total!E$103 -> 0 | K34: =$J34*Total!C$104 -> 0 | L34: =$J34*Total!D$104 -> 0 | M34: =$J34*Total!E$104 -> 0 | O34: =$N34*Total!C$105 -> 0 | P34: =$N34*Total!D$105 -> 0 | Q34: =$N34*Total!E$105 -> 0 | S34: =$R34*Total!C$106 -> 0 | T34: =$R34*Total!D$106 -> 0 | U34: =$R34*Total!E$106 -> 0 | W34: =$V34*Total!C$107 -> 0 | X34: =$V34*Total!D$107 -> 0 | Y34: =$V34*Total!E$107 -> 0 | AA34: =$Z34*Total!C$108 -> 0 | AB34: =$Z34*Total!D$108 -> 0 | AC34: =$Z34*Total!E$108 -> 0 | AE34: 0 | AF34: 0 | AG34: 0 | AI34: =$AH34*Total!C$110 -> 0 | AJ34: =$AH34*Total!D$110 -> 0 | AK34: =$AH34*Total!E$110 -> 0 | AM34: =$AL34*Total!C$111 -> 0 | AN34: =$AL34*Total!D$111 -> 0 | AO34: =$AL34*Total!E$111 -> 0
A35: financial and insurance activities | C35: =+$B35*Total!C$102 -> 0 | D35: =+$B35*Total!D$102 -> 0 | E35: =+$B35*Total!E$102 -> 0 | G35: =$F35*Total!C$103 -> 0 | H35: =$F35*Total!D$103 -> 0 | I35: =$F35*Total!E$103 -> 0 | K35: =$J35*Total!C$104 -> 0 | L35: =$J35*Total!D$104 -> 0 | M35: =$J35*Total!E$104 -> 0 | O35: =$N35*Total!C$105 -> 0 | P35: =$N35*Total!D$105 -> 0 | Q35: =$N35*Total!E$105 -> 0 | S35: =$R35*Total!C$106 -> 0 | T35: =$R35*Total!D$106 -> 0 | U35: =$R35*Total!E$106 -> 0 | W35: =$V35*Total!C$107 -> 0 | X35: =$V35*Total!D$107 -> 0 | Y35: =$V35*Total!E$107 -> 0 | AA35: =$Z35*Total!C$108 -> 0 | AB35: =$Z35*Total!D$108 -> 0 | AC35: =$Z35*Total!E$108 -> 0 | AE35: 0 | AF35: 0 | AG35: 0 | AI35: =$AH35*Total!C$110 -> 0 | AJ35: =$AH35*Total!D$110 -> 0 | AK35: =$AH35*Total!E$110 -> 0 | AM35: =$AL35*Total!C$111 -> 0 | AN35: =$AL35*Total!D$111 -> 0 | AO35: =$AL35*Total!E$111 -> 0
A36: real estate | C36: =+$B36*Total!C$102 -> 0 | D36: =+$B36*Total!D$102 -> 0 | E36: =+$B36*Total!E$102 -> 0 | G36: =$F36*Total!C$103 -> 0 | H36: =$F36*Total!D$103 -> 0 | I36: =$F36*Total!E$103 -> 0 | K36: =$J36*Total!C$104 -> 0 | L36: =$J36*Total!D$104 -> 0 | M36: =$J36*Total!E$104 -> 0 | O36: =$N36*Total!C$105 -> 0 | P36: =$N36*Total!D$105 -> 0 | Q36: =$N36*Total!E$105 -> 0 | S36: =$R36*Total!C$106 -> 0 | T36: =$R36*Total!D$106 -> 0 | U36: =$R36*Total!E$106 -> 0 | W36: =$V36*Total!C$107 -> 0 | X36: =$V36*Total!D$107 -> 0 | Y36: =$V36*Total!E$107 -> 0 | AA36: =$Z36*Total!C$108 -> 0 | AB36: =$Z36*Total!D$108 -> 0 | AC36: =$Z36*Total!E$108 -> 0 | AE36: 0 | AF36: 0 | AG36: 0 | AI36: =$AH36*Total!C$110 -> 0 | AJ36: =$AH36*Total!D$110 -> 0 | AK36: =$AH36*Total!E$110 -> 0 | AM36: =$AL36*Total!C$111 -> 0 | AN36: =$AL36*Total!D$111 -> 0 | AO36: =$AL36*Total!E$111 -> 0
A37: research and development; travel agencies; support activities | B37: 0.0532 | C37: =+$B37*Total!C$102 -> 0.00266 | D37: =+$B37*Total!D$102 -> 0.04788 | E37: =+$B37*Total!E$102 -> 0.00266 | F37: 0.07 | G37: =$F37*Total!C$103 -> 0.0175 | H37: =$F37*Total!D$103 -> 0.0175 | I37: =$F37*Total!E$103 -> 0.035 | J37: 0.05 | K37: =$J37*Total!C$104 -> 0.0075 | L37: =$J37*Total!D$104 -> 0.0175 | M37: =$J37*Total!E$104 -> 0.025 | N37: 0.05 | O37: =$N37*Total!C$105 -> 0.005 | P37: =$N37*Total!D$105 -> 0.045 | Q37: =$N37*Total!E$105 -> 0 | R37: 0.1 | S37: =$R37*Total!C$106 -> 0.002 | T37: =$R37*Total!D$106 -> 0.098 | U37: =$R37*Total!E$106 -> 0 | V37: 0.08 | W37: =$V37*Total!C$107 -> 0.04 | X37: =$V37*Total!D$107 -> 0.04 | Y37: =$V37*Total!E$107 -> 0 | Z37: 0.06 | AA37: =$Z37*Total!C$108 -> 0.042 | AB37: =$Z37*Total!D$108 -> 0.018 | AC37: =$Z37*Total!E$108 -> 0 | AD37: 0.06 | AE37: =+$AD37*Total!C$109 -> 0.042 | AF37: =+$AD37*Total!D$109 -> 0.018 | AG37: =+$AD37*Total!E$109 -> 0 | AI37: =$AH37*Total!C$110 -> 0 | AJ37: =$AH37*Total!D$110 -> 0 | AK37: =$AH37*Total!E$110 -> 0 | AL37: 0.15 | AM37: =$AL37*Total!C$111 -> 0.12 | AN37: =$AL37*Total!D$111 -> 0.0225 | AO37: =$AL37*Total!E$111 -> 0.0075
A38: public administration | C38: =+$B38*Total!C$102 -> 0 | D38: =+$B38*Total!D$102 -> 0 | E38: =+$B38*Total!E$102 -> 0 | G38: =$F38*Total!C$103 -> 0 | H38: =$F38*Total!D$103 -> 0 | I38: =$F38*Total!E$103 -> 0 | K38: =$J38*Total!C$104 -> 0 | L38: =$J38*Total!D$104 -> 0 | M38: =$J38*Total!E$104 -> 0 | O38: =$N38*Total!C$105 -> 0 | P38: =$N38*Total!D$105 -> 0 | Q38: =$N38*Total!E$105 -> 0 | S38: =$R38*Total!C$106 -> 0 | T38: =$R38*Total!D$106 -> 0 | U38: =$R38*Total!E$106 -> 0 | W38: =$V38*Total!C$107 -> 0 | X38: =$V38*Total!D$107 -> 0 | Y38: =$V38*Total!E$107 -> 0 | AA38: =$Z38*Total!C$108 -> 0 | AB38: =$Z38*Total!D$108 -> 0 | AC38: =$Z38*Total!E$108 -> 0 | AE38: 0 | AF38: 0 | AG38: 0 | AI38: =$AH38*Total!C$110 -> 0 | AJ38: =$AH38*Total!D$110 -> 0 | AK38: =$AH38*Total!E$110 -> 0 | AL38: 0.1 | AM38: =$AL38*Total!C$111 -> 0.08 | AN38: =$AL38*Total!D$111 -> 0.015 | AO38: =$AL38*Total!E$111 -> 0.005
A39: education; health and social work | C39: =+$B39*Total!C$102 -> 0 | D39: =+$B39*Total!D$102 -> 0 | E39: =+$B39*Total!E$102 -> 0 | G39: =$F39*Total!C$103 -> 0 | H39: =$F39*Total!D$103 -> 0 | I39: =$F39*Total!E$103 -> 0 | K39: =$J39*Total!C$104 -> 0 | L39: =$J39*Total!D$104 -> 0 | M39: =$J39*Total!E$104 -> 0 | O39: =$N39*Total!C$105 -> 0 | P39: =$N39*Total!D$105 -> 0 | Q39: =$N39*Total!E$105 -> 0 | S39: =$R39*Total!C$106 -> 0 | T39: =$R39*Total!D$106 -> 0 | U39: =$R39*Total!E$106 -> 0 | W39: =$V39*Total!C$107 -> 0 | X39: =$V39*Total!D$107 -> 0 | Y39: =$V39*Total!E$107 -> 0 | AA39: =$Z39*Total!C$108 -> 0 | AB39: =$Z39*Total!D$108 -> 0 | AC39: =$Z39*Total!E$108 -> 0 | AE39: 0 | AF39: 0 | AG39: 0 | AI39: =$AH39*Total!C$110 -> 0 | AJ39: =$AH39*Total!D$110 -> 0 | AK39: =$AH39*Total!E$110 -> 0 | AM39: =$AL39*Total!C$111 -> 0 | AN39: =$AL39*Total!D$111 -> 0 | AO39: =$AL39*Total!E$111 -> 0
A40: other services | C40: =+$B40*Total!C$102 -> 0 | D40: =+$B40*Total!D$102 -> 0 | E40: =+$B40*Total!E$102 -> 0 | G40: =$F40*Total!C$103 -> 0 | H40: =$F40*Total!D$103 -> 0 | I40: =$F40*Total!E$103 -> 0 | K40: =$J40*Total!C$104 -> 0 | L40: =$J40*Total!D$104 -> 0 | M40: =$J40*Total!E$104 -> 0 | O40: =$N40*Total!C$105 -> 0 | P40: =$N40*Total!D$105 -> 0 | Q40: =$N40*Total!E$105 -> 0 | S40: =$R40*Total!C$106 -> 0 | T40: =$R40*Total!D$106 -> 0 | U40: =$R40*Total!E$106 -> 0 | V40: 0.1 | W40: =$V40*Total!C$107 -> 0.05 | X40: =$V40*Total!D$107 -> 0.05 | Y40: =$V40*Total!E$107 -> 0 | AA40: =$Z40*Total!C$108 -> 0 | AB40: =$Z40*Total!D$108 -> 0 | AC40: =$Z40*Total!E$108 -> 0 | AE40: 0 | AF40: 0 | AG40: 0 | AI40: =$AH40*Total!C$110 -> 0 | AJ40: =$AH40*Total!D$110 -> 0 | AK40: =$AH40*Total!E$110 -> 0 | AL40: 0.1 | AM40: =$AL40*Total!C$111 -> 0.08 | AN40: =$AL40*Total!D$111 -> 0.015 | AO40: =$AL40*Total!E$111 -> 0.005
A41: imports | B41: 0.4589 | C41: =+$B41*Total!C$102 -> 0.022945 | D41: =+$B41*Total!D$102 -> 0.41301 | E41: =+$B41*Total!E$102 -> 0.022945 | F41: 0.45 | G41: =$F41*Total!C$103 -> 0.1125 | H41: =$F41*Total!D$103 -> 0.1125 | I41: =$F41*Total!E$103 -> 0.225 | J41: 0.55 | K41: =$J41*Total!C$104 -> 0.0825 | L41: =$J41*Total!D$104 -> 0.1925 | M41: =$J41*Total!E$104 -> 0.275 | N41: 0.4 | O41: =$N41*Total!C$105 -> 0.04 | P41: =$N41*Total!D$105 -> 0.36 | Q41: =$N41*Total!E$105 -> 0 | R41: 0.15 | S41: =$R41*Total!C$106 -> 0.003 | T41: =$R41*Total!D$106 -> 0.147 | U41: =$R41*Total!E$106 -> 0 | V41: 0.12 | W41: =$V41*Total!C$107 -> 0.06 | X41: =$V41*Total!D$107 -> 0.06 | Y41: =$V41*Total!E$107 -> 0 | Z41: 0.08 | AA41: =$Z41*Total!C$108 -> 0.056 | AB41: =$Z41*Total!D$108 -> 0.024 | AC41: =$Z41*Total!E$108 -> 0 | AD41: 0.08 | AE41: =+$AD41*Total!C$109 -> 0.056 | AF41: =+$AD41*Total!D$109 -> 0.024 | AG41: =+$AD41*Total!E$109 -> 0 | AI41: =$AH41*Total!C$110 -> 0 | AJ41: =$AH41*Total!D$110 -> 0 | AK41: =$AH41*Total!E$110 -> 0 | AM41: =$AL41*Total!C$111 -> 0 | AN41: =$AL41*Total!D$111 -> 0 | AO41: =$AL41*Total!E$111 -> 0
B42: =+SUM(B2:B41) -> 1 | F42: =+SUM(F2:F41) -> 1 | J42: =+SUM(J2:J41) -> 1 | N42: =+SUM(N2:N41) -> 1 | R42: =+SUM(R2:R41) -> 1 | V42: =+SUM(V2:V41) -> 1 | Z42: =+SUM(Z2:Z41) -> 1 | AD42: =+SUM(AD2:AD41) -> 1 | AH42: =+SUM(AH2:AH41) -> 1 | AL42: =+SUM(AL2:AL41) -> 1
E43: =+SUM(C2:E41) -> 1 | I43: =+SUM(G2:I41) -> 1 | M43: =+SUM(K2:M41) -> 1 | Q43: =+SUM(O2:Q41) -> 1 | U43: =+SUM(S2:U41) -> 1 | Y43: =+SUM(W2:Y41) -> 1 | AC43: =+SUM(AA2:AC41) -> 1 | AG43: =+SUM(AE2:AG41) -> 1 | AK43: =+SUM(AI2:AK41) -> 1 | AO43: =+SUM(AM2:AO41) -> 1

Sheet Government
C1: LTS
A2: Sector | D2: 2023 | E2: 2024 | F2: 2025 | G2: 2026 | H2: 2027 | I2: 2028 | J2: 2029 | K2: 2030 | L2: 2031 | M2: 2032 | N2: 2033 | O2: 2034 | P2: 2035 | Q2: 2036 | R2: 2037 | S2: 2038 | T2: 2039 | U2: 2040 | V2: 2041 | W2: 2042 | X2: 2043 | Y2: 2044 | Z2: 2045 | AA2: 2046 | AB2: 2047 | AC2: 2048 | AD2: 2049 | AE2: 2050
A3: EN - Power Industry | D3: =+Total!D3 -> 0 | E3: =+Total!E3 -> 0 | F3: =+Total!F3 -> 1.6405576 | G3: =+Total!G3 -> 0.34625024 | H3: =+Total!H3 -> 1.9174732 | I3: =+Total!I3 -> 2.5989561 | J3: =+Total!J3 -> 7.4215444 | K3: =+Total!K3 -> 12.361299 | ... AE3: =+Total!AE3 -> 7.1215774
A4: EN - Building | D4: =+Total!D4 -> 0 | E4: =+Total!E4 -> 0 | F4: =+Total!F4 -> 0 | G4: =+Total!G4 -> 0.012392549 | H4: =+Total!H4 -> 0.023961415 | I4: =+Total!I4 -> 0.034716882 | J4: =+Total!J4 -> 0.04467692 | K4: =+Total!K4 -> 0.064827291 | ... AE4: =+Total!AE4 -> 1.5214156
A5: EN - Transportation | D5: =+Total!D5 -> 0 | E5: =+Total!E5 -> 0 | F5: =+Total!F5 -> 0.00071354781 | G5: =+Total!G5 -> 0.0034838861 | H5: =+Total!H5 -> 0.0064159389 | I5: =+Total!I5 -> 0.0095152481 | J5: =+Total!J5 -> 0.012795081 | K5: =+Total!K5 -> 0.016253265 | ... AE5: =+Total!AE5 -> 0.73142549
A6: EN - Industrial combustion | D6: =+Total!D6 -> 0 | E6: =+Total!E6 -> 0 | F6: =+Total!F6 -> 0.014978408 | G6: =+Total!G6 -> 0.038599098 | H6: =+Total!H6 -> 0.061850965 | I6: =+Total!I6 -> 0.087728895 | J6: =+Total!J6 -> 0.11327748 | K6: =+Total!K6 -> 0.13857169 | ... AE6: =+Total!AE6 -> 0.6477426
A7: IN - Industrial processes | D7: =+Total!D7 -> 0 | E7: =+Total!E7 -> 0 | F7: =+Total!F7 -> 0 | G7: =+Total!G7 -> 0.81392292 | H7: =+Total!H7 -> 0.9083042 | I7: =+Total!I7 -> 1.0048392 | J7: =+Total!J7 -> 1.1037592 | K7: =+Total!K7 -> 1.2048031 | ... AE7: =+Total!AE7 -> 3.6692709
A8: Waste - Solid waste | D8: =+Total!D8 -> 0 | E8: =+Total!E8 -> 0 | F8: =+Total!F8 -> 0.087052446 | G8: =+Total!G8 -> 0.11358144 | H8: =+Total!H8 -> 0.1399269 | I8: =+Total!I8 -> 0.16354773 | J8: =+Total!J8 -> 0.1829564 | K8: =+Total!K8 -> 0.19795117 | ... AE8: =+Total!AE8 -> 0.24983327
A9: Waste - Wastewater treatment (trww) | D9: =+Total!D9 -> 0 | E9: =+Total!E9 -> 0 | F9: =+Total!F9 -> 0 | G9: =+Total!G9 -> 0.11709818 | H9: =+Total!H9 -> 0.24928301 | I9: =+Total!I9 -> 0.39763456 | J9: =+Total!J9 -> 0.56345437 | K9: =+Total!K9 -> 0.74777457 | ... AE9: =+Total!AE9 -> 2.9393447
A10: Waste - Wastewater (liquid waste) | D10: =+Total!D10 -> 0 | E10: =+Total!E10 -> 0 | F10: =+Total!F10 -> 0 | G10: =+Total!G10 -> 0 | H10: =+Total!H10 -> 0 | I10: =+Total!I10 -> 0 | J10: =+Total!J10 -> 0 | K10: =+Total!K10 -> 0 | ... AE10: =+Total!AE10 -> 0
A11: AG - Livestock (manure) | D11: =+Total!D11 -> 0 | E11: =+Total!E11 -> 0 | F11: =+Total!F11 -> 0 | G11: =+Total!G11 -> 0 | H11: =+Total!H11 -> 0 | I11: =+Total!I11 -> 0 | J11: =+Total!J11 -> 0 | K11: =+Total!K11 -> 0 | ... AE11: =+Total!AE11 -> 0
A12: LULUCF - Forest land | D12: =+Total!D12 -> 0 | E12: =+Total!E12 -> 0 | F12: =+Total!F12 -> 0.98551391 | G12: =+Total!G12 -> 1.217631 | H12: =+Total!H12 -> 1.4249767 | I12: =+Total!I12 -> 1.6039905 | J12: =+Total!J12 -> 1.7589536 | K12: =+Total!K12 -> 1.8900428 | ... AE12: =+Total!AE12 -> 3.2774395
A14: units: billion 2019 USD
A16: Sector | B16: SAM destination | C16: Government rate | D16: 2023 | E16: 2024 | F16: 2025 | G16: 2026 | H16: 2027 | I16: 2028 | J16: 2029 | K16: 2030 | L16: 2031 | M16: 2032 | N16: 2033 | O16: 2034 | P16: 2035 | Q16: 2036 | R16: 2037 | S16: 2038 | T16: 2039 | U16: 2040 | V16: 2041 | W16: 2042 | X16: 2043 | Y16: 2044 | Z16: 2045 | AA16: 2046 | AB16: 2047 | AC16: 2048 | AD16: 2049 | AE16: 2050
A17: EN - Power Industry | B17: crops | C17: =+SAM!C2 -> 0 | D17: =+$C17*D$3 -> 0 | E17: =+$C17*E$3 -> 0 | F17: =+$C17*F$3 -> 0 | G17: =+$C17*G$3 -> 0 | H17: =+$C17*H$3 -> 0 | I17: =+$C17*I$3 -> 0 | J17: =+$C17*J$3 -> 0 | K17: =+$C17*K$3 -> 0 | ... AE17: =+$C17*AE$3 -> 0
B18: forestry | C18: =+SAM!C3 -> 0 | D18: =+$C18*D$3 -> 0 | E18: =+$C18*E$3 -> 0 | F18: =+$C18*F$3 -> 0 | G18: =+$C18*G$3 -> 0 | H18: =+$C18*H$3 -> 0 | I18: =+$C18*I$3 -> 0 | J18: =+$C18*J$3 -> 0 | K18: =+$C18*K$3 -> 0 | ... AE18: =+$C18*AE$3 -> 0
B19: livestock | C19: =+SAM!C4 -> 0 | D19: =+$C19*D$3 -> 0 | E19: =+$C19*E$3 -> 0 | F19: =+$C19*F$3 -> 0 | G19: =+$C19*G$3 -> 0 | H19: =+$C19*H$3 -> 0 | I19: =+$C19*I$3 -> 0 | J19: =+$C19*J$3 -> 0 | K19: =+$C19*K$3 -> 0 | ... AE19: =+$C19*AE$3 -> 0
B20: fishery and aquaculture | C20: =+SAM!C5 -> 0 | D20: =+$C20*D$3 -> 0 | E20: =+$C20*E$3 -> 0 | F20: =+$C20*F$3 -> 0 | G20: =+$C20*G$3 -> 0 | H20: =+$C20*H$3 -> 0 | I20: =+$C20*I$3 -> 0 | J20: =+$C20*J$3 -> 0 | K20: =+$C20*K$3 -> 0 | ... AE20: =+$C20*AE$3 -> 0
B21: Extractive activities | C21: =+SAM!C6 -> 0 | D21: =+$C21*D$3 -> 0 | E21: =+$C21*E$3 -> 0 | F21: =+$C21*F$3 -> 0 | G21: =+$C21*G$3 -> 0 | H21: =+$C21*H$3 -> 0 | I21: =+$C21*I$3 -> 0 | J21: =+$C21*J$3 -> 0 | K21: =+$C21*K$3 -> 0 | ... AE21: =+$C21*AE$3 -> 0
B22: food manufacturing and beverage | C22: =+SAM!C7 -> 0 | D22: =+$C22*D$3 -> 0 | E22: =+$C22*E$3 -> 0 | F22: =+$C22*F$3 -> 0 | G22: =+$C22*G$3 -> 0 | H22: =+$C22*H$3 -> 0 | I22: =+$C22*I$3 -> 0 | J22: =+$C22*J$3 -> 0 | K22: =+$C22*K$3 -> 0 | ... AE22: =+$C22*AE$3 -> 0
B23: textile manufacturing and clothes | C23: =+SAM!C8 -> 0 | D23: =+$C23*D$3 -> 0 | E23: =+$C23*E$3 -> 0 | F23: =+$C23*F$3 -> 0 | G23: =+$C23*G$3 -> 0 | H23: =+$C23*H$3 -> 0 | I23: =+$C23*I$3 -> 0 | J23: =+$C23*J$3 -> 0 | K23: =+$C23*K$3 -> 0 | ... AE23: =+$C23*AE$3 -> 0
B24: Wood product manufacturing | C24: =+SAM!C9 -> 0 | D24: =+$C24*D$3 -> 0 | E24: =+$C24*E$3 -> 0 | F24: =+$C24*F$3 -> 0 | G24: =+$C24*G$3 -> 0 | H24: =+$C24*H$3 -> 0 | I24: =+$C24*I$3 -> 0 | J24: =+$C24*J$3 -> 0 | K24: =+$C24*K$3 -> 0 | ... AE24: =+$C24*AE$3 -> 0
B25: coking and refining production | C25: =+SAM!C10 -> 0 | D25: =+$C25*D$3 -> 0 | E25: =+$C25*E$3 -> 0 | F25: =+$C25*F$3 -> 0 | G25: =+$C25*G$3 -> 0 | H25: =+$C25*H$3 -> 0 | I25: =+$C25*I$3 -> 0 | J25: =+$C25*J$3 -> 0 | K25: =+$C25*K$3 -> 0 | ... AE25: =+$C25*AE$3 -> 0
B26: chemical products | C26: =+SAM!C11 -> 0 | D26: =+$C26*D$3 -> 0 | E26: =+$C26*E$3 -> 0 | F26: =+$C26*F$3 -> 0 | G26: =+$C26*G$3 -> 0 | H26: =+$C26*H$3 -> 0 | I26: =+$C26*I$3 -> 0 | J26: =+$C26*J$3 -> 0 | K26: =+$C26*K$3 -> 0 | ... AE26: =+$C26*AE$3 -> 0
B27: pharmaceutical products | C27: =+SAM!C12 -> 0 | D27: =+$C27*D$3 -> 0 | E27: =+$C27*E$3 -> 0 | F27: =+$C27*F$3 -> 0 | G27: =+$C27*G$3 -> 0 | H27: =+$C27*H$3 -> 0 | I27: =+$C27*I$3 -> 0 | J27: =+$C27*J$3 -> 0 | K27: =+$C27*K$3 -> 0 | ... AE27: =+$C27*AE$3 -> 0
B28: rubber manufacturing | C28: =+SAM!C13 -> 0 | D28: =+$C28*D$3 -> 0 | E28: =+$C28*E$3 -> 0 | F28: =+$C28*F$3 -> 0 | G28: =+$C28*G$3 -> 0 | H28: =+$C28*H$3 -> 0 | I28: =+$C28*I$3 -> 0 | J28: =+$C28*J$3 -> 0 | K28: =+$C28*K$3 -> 0 | ... AE28: =+$C28*AE$3 -> 0
B29: metalwork manufacturing | C29: =+SAM!C14 -> 0.00295 | D29: =+$C29*D$3 -> 0 | E29: =+$C29*E$3 -> 0 | F29: =+$C29*F$3 -> 0.0048396449 | G29: =+$C29*G$3 -> 0.0010214382 | H29: =+$C29*H$3 -> 0.0056565459 | I29: =+$C29*I$3 -> 0.0076669205 | J29: =+$C29*J$3 -> 0.021893556 | K29: =+$C29*K$3 -> 0.036465833 | ... AE29: =+$C29*AE$3 -> 0.021008653
... B56: imports | C56: =+SAM!C41 -> 0.022945 | D56: =+$C56*D$3 -> 0 | E56: =+$C56*E$3 -> 0 | F56: =+$C56*F$3 -> 0.037642594 | G56: =+$C56*G$3 -> 0.0079447118 | H56: =+$C56*H$3 -> 0.043996422 | I56: =+$C56*I$3 -> 0.059633048 | J56: =+$C56*J$3 -> 0.17028734 | K56: =+$C56*K$3 -> 0.28363001 | ... AE56: =+$C56*AE$3 -> 0.16340459
A57: EN - Building | B57: crops | C57: =+SAM!G2 -> 0 | D57: =+$C57*D$4 -> 0 | E57: =+$C57*E$4 -> 0 | F57: =+$C57*F$4 -> 0 | G57: =+$C57*G$4 -> 0 | H57: =+$C57*H$4 -> 0 | I57: =+$C57*I$4 -> 0 | J57: =+$C57*J$4 -> 0 | K57: =+$C57*K$4 -> 0 | ... AE57: =+$C57*AE$4 -> 0
B58: forestry | C58: =+SAM!G3 -> 0 | D58: =+$C58*D$4 -> 0 | E58: =+$C58*E$4 -> 0 | F58: =+$C58*F$4 -> 0 | G58: =+$C58*G$4 -> 0 | H58: =+$C58*H$4 -> 0 | I58: =+$C58*I$4 -> 0 | J58: =+$C58*J$4 -> 0 | K58: =+$C58*K$4 -> 0 | ... AE58: =+$C58*AE$4 -> 0
B59: livestock | C59: =+SAM!G4 -> 0 | D59: =+$C59*D$4 -> 0 | E59: =+$C59*E$4 -> 0 | F59: =+$C59*F$4 -> 0 | G59: =+$C59*G$4 -> 0 | H59: =+$C59*H$4 -> 0 | I59: =+$C59*I$4 -> 0 | J59: =+$C59*J$4 -> 0 | K59: =+$C59*K$4 -> 0 | ... AE59: =+$C59*AE$4 -> 0
B60: fishery and aquaculture | C60: =+SAM!G5 -> 0 | D60: =+$C60*D$4 -> 0 | E60: =+$C60*E$4 -> 0 | F60: =+$C60*F$4 -> 0 | G60: =+$C60*G$4 -> 0 | H60: =+$C60*H$4 -> 0 | I60: =+$C60*I$4 -> 0 | J60: =+$C60*J$4 -> 0 | K60: =+$C60*K$4 -> 0 | ... AE60: =+$C60*AE$4 -> 0
B61: Extractive activities | C61: =+SAM!G6 -> 0 | D61: =+$C61*D$4 -> 0 | E61: =+$C61*E$4 -> 0 | F61: =+$C61*F$4 -> 0 | G61: =+$C61*G$4 -> 0 | H61: =+$C61*H$4 -> 0 | I61: =+$C61*I$4 -> 0 | J61: =+$C61*J$4 -> 0 | K61: =+$C61*K$4 -> 0 | ... AE61: =+$C61*AE$4 -> 0
B62: food manufacturing and beverage | C62: =+SAM!G7 -> 0 | D62: =+$C62*D$4 -> 0 | E62: =+$C62*E$4 -> 0 | F62: =+$C62*F$4 -> 0 | G62: =+$C62*G$4 -> 0 | H62: =+$C62*H$4 -> 0 | I62: =+$C62*I$4 -> 0 | J62: =+$C62*J$4 -> 0 | K62: =+$C62*K$4 -> 0 | ... AE62: =+$C62*AE$4 -> 0
B63: textile manufacturing and clothes | C63: =+SAM!G8 -> 0 | D63: =+$C63*D$4 -> 0 | E63: =+$C63*E$4 -> 0 | F63: =+$C63*F$4 -> 0 | G63: =+$C63*G$4 -> 0 | H63: =+$C63*H$4 -> 0 | I63: =+$C63*I$4 -> 0 | J63: =+$C63*J$4 -> 0 | K63: =+$C63*K$4 -> 0 | ... AE63: =+$C63*AE$4 -> 0
B64: Wood product manufacturing | C64: =+SAM!G9 -> 0.0075 | D64: =+$C64*D$4 -> 0 | E64: =+$C64*E$4 -> 0 | F64: =+$C64*F$4 -> 0 | G64: =+$C64*G$4 -> 9.2944117e-05 | H64: =+$C64*H$4 -> 0.00017971061 | I64: =+$C64*I$4 -> 0.00026037661 | J64: =+$C64*J$4 -> 0.0003350769 | K64: =+$C64*K$4 -> 0.00048620468 | ... AE64: =+$C64*AE$4 -> 0.011410617
B65: coking and refining production | C65: =+SAM!G10 -> 0 | D65: =+$C65*D$4 -> 0 | E65: =+$C65*E$4 -> 0 | F65: =+$C65*F$4 -> 0 | G65: =+$C65*G$4 -> 0 | H65: =+$C65*H$4 -> 0 | I65: =+$C65*I$4 -> 0 | J65: =+$C65*J$4 -> 0 | K65: =+$C65*K$4 -> 0 | ... AE65: =+$C65*AE$4 -> 0
B66: chemical products | C66: =+SAM!G11 -> 0 | D66: =+$C66*D$4 -> 0 | E66: =+$C66*E$4 -> 0 | F66: =+$C66*F$4 -> 0 | G66: =+$C66*G$4 -> 0 | H66: =+$C66*H$4 -> 0 | I66: =+$C66*I$4 -> 0 | J66: =+$C66*J$4 -> 0 | K66: =+$C66*K$4 -> 0 | ... AE66: =+$C66*AE$4 -> 0
B67: pharmaceutical products | C67: =+SAM!G12 -> 0 | D67: =+$C67*D$4 -> 0 | E67: =+$C67*E$4 -> 0 | F67: =+$C67*F$4 -> 0 | G67: =+$C67*G$4 -> 0 | H67: =+$C67*H$4 -> 0 | I67: =+$C67*I$4 -> 0 | J67: =+$C67*J$4 -> 0 | K67: =+$C67*K$4 -> 0 | ... AE67: =+$C67*AE$4 -> 0
B68: rubber manufacturing | C68: =+SAM!G13 -> 0 | D68: =+$C68*D$4 -> 0 | E68: =+$C68*E$4 -> 0 | F68: =+$C68*F$4 -> 0 | G68: =+$C68*G$4 -> 0 | H68: =+$C68*H$4 -> 0 | I68: =+$C68*I$4 -> 0 | J68: =+$C68*J$4 -> 0 | K68: =+$C68*K$4 -> 0 | ... AE68: =+$C68*AE$4 -> 0
B69: metalwork manufacturing | C69: =+SAM!G14 -> 0 | D69: =+$C69*D$4 -> 0 | E69: =+$C69*E$4 -> 0 | F69: =+$C69*F$4 -> 0 | G69: =+$C69*G$4 -> 0 | H69: =+$C69*H$4 -> 0 | I69: =+$C69*I$4 -> 0 | J69: =+$C69*J$4 -> 0 | K69: =+$C69*K$4 -> 0 | ... AE69: =+$C69*AE$4 -> 0
... B96: imports | C96: =+SAM!G41 -> 0.1125 | D96: =+$C96*D$4 -> 0 | E96: =+$C96*E$4 -> 0 | F96: =+$C96*F$4 -> 0 | G96: =+$C96*G$4 -> 0.0013941618 | H96: =+$C96*H$4 -> 0.0026956592 | I96: =+$C96*I$4 -> 0.0039056492 | J96: =+$C96*J$4 -> 0.0050261535 | K96: =+$C96*K$4 -> 0.0072930702 | ... AE96: =+$C96*AE$4 -> 0.17115926
A97: EN - Transportation | B97: crops | C97: =+SAM!K2 -> 0 | D97: =+$C97*D$5 -> 0 | E97: =+$C97*E$5 -> 0 | F97: =+$C97*F$5 -> 0 | G97: =+$C97*G$5 -> 0 | H97: =+$C97*H$5 -> 0 | I97: =+$C97*I$5 -> 0 | J97: =+$C97*J$5 -> 0 | K97: =+$C97*K$5 -> 0 | ... AE97: =+$C97*AE$5 -> 0
B98: forestry | C98: =+SAM!K3 -> 0 | D98: =+$C98*D$5 -> 0 | E98: =+$C98*E$5 -> 0 | F98: =+$C98*F$5 -> 0 | G98: =+$C98*G$5 -> 0 | H98: =+$C98*H$5 -> 0 | I98: =+$C98*I$5 -> 0 | J98: =+$C98*J$5 -> 0 | K98: =+$C98*K$5 -> 0 | ... AE98: =+$C98*AE$5 -> 0
B99: livestock | C99: =+SAM!K4 -> 0 | D99: =+$C99*D$5 -> 0 | E99: =+$C99*E$5 -> 0 | F99: =+$C99*F$5 -> 0 | G99: =+$C99*G$5 -> 0 | H99: =+$C99*H$5 -> 0 | I99: =+$C99*I$5 -> 0 | J99: =+$C99*J$5 -> 0 | K99: =+$C99*K$5 -> 0 | ... AE99: =+$C99*AE$5 -> 0
B100: fishery and aquaculture | C100: =+SAM!K5 -> 0 | D100: =+$C100*D$5 -> 0 | E100: =+$C100*E$5 -> 0 | F100: =+$C100*F$5 -> 0 | G100: =+$C100*G$5 -> 0 | H100: =+$C100*H$5 -> 0 | I100: =+$C100*I$5 -> 0 | J100: =+$C100*J$5 -> 0 | K100: =+$C100*K$5 -> 0 | ... AE100: =+$C100*AE$5 -> 0
B101: Extractive activities | C101: =+SAM!K6 -> 0 | D101: =+$C101*D$5 -> 0 | E101: =+$C101*E$5 -> 0 | F101: =+$C101*F$5 -> 0 | G101: =+$C101*G$5 -> 0 | H101: =+$C101*H$5 -> 0 | I101: =+$C101*I$5 -> 0 | J101: =+$C101*J$5 -> 0 | K101: =+$C101*K$5 -> 0 | ... AE101: =+$C101*AE$5 -> 0
B102: food manufacturing and beverage | C102: =+SAM!K7 -> 0 | D102: =+$C102*D$5 -> 0 | E102: =+$C102*E$5 -> 0 | F102: =+$C102*F$5 -> 0 | G102: =+$C102*G$5 -> 0 | H102: =+$C102*H$5 -> 0 | I102: =+$C102*I$5 -> 0 | J102: =+$C102*J$5 -> 0 | K102: =+$C102*K$5 -> 0 | ... AE102: =+$C102*AE$5 -> 0
B103: textile manufacturing and clothes | C103: =+SAM!K8 -> 0 | D103: =+$C103*D$5 -> 0 | E103: =+$C103*E$5 -> 0 | F103: =+$C103*F$5 -> 0 | G103: =+$C103*G$5 -> 0 | H103: =+$C103*H$5 -> 0 | I103: =+$C103*I$5 -> 0 | J103: =+$C103*J$5 -> 0 | K103: =+$C103*K$5 -> 0 | ... AE103: =+$C103*AE$5 -> 0
B104: Wood product manufacturing | C104: =+SAM!K9 -> 0 | D104: =+$C104*D$5 -> 0 | E104: =+$C104*E$5 -> 0 | F104: =+$C104*F$5 -> 0 | G104: =+$C104*G$5 -> 0 | H104: =+$C104*H$5 -> 0 | I104: =+$C104*I$5 -> 0 | J104: =+$C104*J$5 -> 0 | K104: =+$C104*K$5 -> 0 | ... AE104: =+$C104*AE$5 -> 0
B105: coking and refining production | C105: =+SAM!K10 -> 0 | D105: =+$C105*D$5 -> 0 | E105: =+$C105*E$5 -> 0 | F105: =+$C105*F$5 -> 0 | G105: =+$C105*G$5 -> 0 | H105: =+$C105*H$5 -> 0 | I105: =+$C105*I$5 -> 0 | J105: =+$C105*J$5 -> 0 | K105: =+$C105*K$5 -> 0 | ... AE105: =+$C105*AE$5 -> 0
B106: chemical products | C106: =+SAM!K11 -> 0 | D106: =+$C106*D$5 -> 0 | E106: =+$C106*E$5 -> 0 | F106: =+$C106*F$5 -> 0 | G106: =+$C106*G$5 -> 0 | H106: =+$C106*H$5 -> 0 | I106: =+$C106*I$5 -> 0 | J106: =+$C106*J$5 -> 0 | K106: =+$C106*K$5 -> 0 | ... AE106: =+$C106*AE$5 -> 0
B107: pharmaceutical products | C107: =+SAM!K12 -> 0 | D107: =+$C107*D$5 -> 0 | E107: =+$C107*E$5 -> 0 | F107: =+$C107*F$5 -> 0 | G107: =+$C107*G$5 -> 0 | H107: =+$C107*H$5 -> 0 | I107: =+$C107*I$5 -> 0 | J107: =+$C107*J$5 -> 0 | K107: =+$C107*K$5 -> 0 | ... AE107: =+$C107*AE$5 -> 0
B108: rubber manufacturing | C108: =+SAM!K13 -> 0 | D108: =+$C108*D$5 -> 0 | E108: =+$C108*E$5 -> 0 | F108: =+$C108*F$5 -> 0 | G108: =+$C108*G$5 -> 0 | H108: =+$C108*H$5 -> 0 | I108: =+$C108*I$5 -> 0 | J108: =+$C108*J$5 -> 0 | K108: =+$C108*K$5 -> 0 | ... AE108: =+$C108*AE$5 -> 0
B109: metalwork manufacturing | C109: =+SAM!K14 -> 0 | D109: =+$C109*D$5 -> 0 | E109: =+$C109*E$5 -> 0 | F109: =+$C109*F$5 -> 0 | G109: =+$C109*G$5 -> 0 | H109: =+$C109*H$5 -> 0 | I109: =+$C109*I$5 -> 0 | J109: =+$C109*J$5 -> 0 | K109: =+$C109*K$5 -> 0 | ... AE109: =+$C109*AE$5 -> 0
... B136: imports | C136: =+SAM!K41 -> 0.0825 | D136: =+$C136*D$5 -> 0 | E136: =+$C136*E$5 -> 0 | F136: =+$C136*F$5 -> 5.8867694e-05 | G136: =+$C136*G$5 -> 0.00028742061 | H136: =+$C136*H$5 -> 0.00052931496 | I136: =+$C136*I$5 -> 0.00078500797 | J136: =+$C136*J$5 -> 0.0010555942 | K136: =+$C136*K$5 -> 0.0013408944 | ... AE136: =+$C136*AE$5 -> 0.060342603
A137: EN - Industrial combustion | B137: crops | C137: =+SAM!O2 -> 0 | D137: =+$C137*D$6 -> 0 | E137: =+$C137*E$6 -> 0 | F137: =+$C137*F$6 -> 0 | G137: =+$C137*G$6 -> 0 | H137: =+$C137*H$6 -> 0 | I137: =+$C137*I$6 -> 0 | J137: =+$C137*J$6 -> 0 | K137: =+$C137*K$6 -> 0 | ... AE137: =+$C137*AE$6 -> 0
B138: forestry | C138: =+SAM!O3 -> 0 | D138: =+$C138*D$6 -> 0 | E138: =+$C138*E$6 -> 0 | F138: =+$C138*F$6 -> 0 | G138: =+$C138*G$6 -> 0 | H138: =+$C138*H$6 -> 0 | I138: =+$C138*I$6 -> 0 | J138: =+$C138*J$6 -> 0 | K138: =+$C138*K$6 -> 0 | ... AE138: =+$C138*AE$6 -> 0
B139: livestock | C139: =+SAM!O4 -> 0 | D139: =+$C139*D$6 -> 0 | E139: =+$C139*E$6 -> 0 | F139: =+$C139*F$6 -> 0 | G139: =+$C139*G$6 -> 0 | H139: =+$C139*H$6 -> 0 | I139: =+$C139*I$6 -> 0 | J139: =+$C139*J$6 -> 0 | K139: =+$C139*K$6 -> 0 | ... AE139: =+$C139*AE$6 -> 0
B140: fishery and aquaculture | C140: =+SAM!O5 -> 0 | D140: =+$C140*D$6 -> 0 | E140: =+$C140*E$6 -> 0 | F140: =+$C140*F$6 -> 0 | G140: =+$C140*G$6 -> 0 | H140: =+$C140*H$6 -> 0 | I140: =+$C140*I$6 -> 0 | J140: =+$C140*J$6 -> 0 | K140: =+$C140*K$6 -> 0 | ... AE140: =+$C140*AE$6 -> 0
B141: Extractive activities | C141: =+SAM!O6 -> 0 | D141: =+$C141*D$6 -> 0 | E141: =+$C141*E$6 -> 0 | F141: =+$C141*F$6 -> 0 | G141: =+$C141*G$6 -> 0 | H141: =+$C141*H$6 -> 0 | I141: =+$C141*I$6 -> 0 | J141: =+$C141*J$6 -> 0 | K141: =+$C141*K$6 -> 0 | ... AE141: =+$C141*AE$6 -> 0
B142: food manufacturing and beverage | C142: =+SAM!O7 -> 0 | D142: =+$C142*D$6 -> 0 | E142: =+$C142*E$6 -> 0 | F142: =+$C142*F$6 -> 0 | G142: =+$C142*G$6 -> 0 | H142: =+$C142*H$6 -> 0 | I142: =+$C142*I$6 -> 0 | J142: =+$C142*J$6 -> 0 | K142: =+$C142*K$6 -> 0 | ... AE142: =+$C142*AE$6 -> 0
B143: textile manufacturing and clothes | C143: =+SAM!O8 -> 0 | D143: =+$C143*D$6 -> 0 | E143: =+$C143*E$6 -> 0 | F143: =+$C143*F$6 -> 0 | G143: =+$C143*G$6 -> 0 | H143: =+$C143*H$6 -> 0 | I143: =+$C143*I$6 -> 0 | J143: =+$C143*J$6 -> 0 | K143: =+$C143*K$6 -> 0 | ... AE143: =+$C143*AE$6 -> 0
B144: Wood product manufacturing | C144: =+SAM!O9 -> 0 | D144: =+$C144*D$6 -> 0 | E144: =+$C144*E$6 -> 0 | F144: =+$C144*F$6 -> 0 | G144: =+$C144*G$6 -> 0 | H144: =+$C144*H$6 -> 0 | I144: =+$C144*I$6 -> 0 | J144: =+$C144*J$6 -> 0 | K144: =+$C144*K$6 -> 0 | ... AE144: =+$C144*AE$6 -> 0
B145: coking and refining production | C145: =+SAM!O10 -> 0 | D145: =+$C145*D$6 -> 0 | E145: =+$C145*E$6 -> 0 | F145: =+$C145*F$6 -> 0 | G145: =+$C145*G$6 -> 0 | H145: =+$C145*H$6 -> 0 | I145: =+$C145*I$6 -> 0 | J145: =+$C145*J$6 -> 0 | K145: =+$C145*K$6 -> 0 | ... AE145: =+$C145*AE$6 -> 0
B146: chemical products | C146: =+SAM!O11 -> 0 | D146: =+$C146*D$6 -> 0 | E146: =+$C146*E$6 -> 0 | F146: =+$C146*F$6 -> 0 | G146: =+$C146*G$6 -> 0 | H146: =+$C146*H$6 -> 0 | I146: =+$C146*I$6 -> 0 | J146: =+$C146*J$6 -> 0 | K146: =+$C146*K$6 -> 0 | ... AE146: =+$C146*AE$6 -> 0
B147: pharmaceutical products | C147: =+SAM!O12 -> 0 | D147: =+$C147*D$6 -> 0 | E147: =+$C147*E$6 -> 0 | F147: =+$C147*F$6 -> 0 | G147: =+$C147*G$6 -> 0 | H147: =+$C147*H$6 -> 0 | I147: =+$C147*I$6 -> 0 | J147: =+$C147*J$6 -> 0 | K147: =+$C147*K$6 -> 0 | ... AE147: =+$C147*AE$6 -> 0
B148: rubber manufacturing | C148: =+SAM!O13 -> 0 | D148: =+$C148*D$6 -> 0 | E148: =+$C148*E$6 -> 0 | F148: =+$C148*F$6 -> 0 | G148: =+$C148*G$6 -> 0 | H148: =+$C148*H$6 -> 0 | I148: =+$C148*I$6 -> 0 | J148: =+$C148*J$6 -> 0 | K148: =+$C148*K$6 -> 0 | ... AE148: =+$C148*AE$6 -> 0
B149: metalwork manufacturing | C149: =+SAM!O14 -> 0.012 | D149: =+$C149*D$6 -> 0 | E149: =+$C149*E$6 -> 0 | F149: =+$C149*F$6 -> 0.0001797409 | G149: =+$C149*G$6 -> 0.00046318917 | H149: =+$C149*H$6 -> 0.00074221157 | I149: =+$C149*I$6 -> 0.0010527467 | J149: =+$C149*J$6 -> 0.0013593297 | K149: =+$C149*K$6 -> 0.0016628603 | ... AE149: =+$C149*AE$6 -> 0.0077729112
... B176: imports | C176: =+SAM!O41 -> 0.04 | D176: =+$C176*D$6 -> 0 | E176: =+$C176*E$6 -> 0 | F176: =+$C176*F$6 -> 0.00059913633 | G176: =+$C176*G$6 -> 0.0015439639 | H176: =+$C176*H$6 -> 0.0024740386 | I176: =+$C176*I$6 -> 0.0035091558 | J176: =+$C176*J$6 -> 0.0045310991 | K176: =+$C176*K$6 -> 0.0055428675 | ... AE176: =+$C176*AE$6 -> 0.025909704
A177: IN - Industrial processes | B177: crops | C177: =+SAM!S2 -> 0 | D177: =+$C177*D$7 -> 0 | E177: =+$C177*E$7 -> 0 | F177: =+$C177*F$7 -> 0 | G177: =+$C177*G$7 -> 0 | H177: =+$C177*H$7 -> 0 | I177: =+$C177*I$7 -> 0 | J177: =+$C177*J$7 -> 0 | K177: =+$C177*K$7 -> 0 | ... AE177: =+$C177*AE$7 -> 0
B178: forestry | C178: =+SAM!S3 -> 0 | D178: =+$C178*D$7 -> 0 | E178: =+$C178*E$7 -> 0 | F178: =+$C178*F$7 -> 0 | G178: =+$C178*G$7 -> 0 | H178: =+$C178*H$7 -> 0 | I178: =+$C178*I$7 -> 0 | J178: =+$C178*J$7 -> 0 | K178: =+$C178*K$7 -> 0 | ... AE178: =+$C178*AE$7 -> 0
B179: livestock | C179: =+SAM!S4 -> 0 | D179: =+$C179*D$7 -> 0 | E179: =+$C179*E$7 -> 0 | F179: =+$C179*F$7 -> 0 | G179: =+$C179*G$7 -> 0 | H179: =+$C179*H$7 -> 0 | I179: =+$C179*I$7 -> 0 | J179: =+$C179*J$7 -> 0 | K179: =+$C179*K$7 -> 0 | ... AE179: =+$C179*AE$7 -> 0
B180: fishery and aquaculture | C180: =+SAM!S5 -> 0 | D180: =+$C180*D$7 -> 0 | E180: =+$C180*E$7 -> 0 | F180: =+$C180*F$7 -> 0 | G180: =+$C180*G$7 -> 0 | H180: =+$C180*H$7 -> 0 | I180: =+$C180*I$7 -> 0 | J180: =+$C180*J$7 -> 0 | K180: =+$C180*K$7 -> 0 | ... AE180: =+$C180*AE$7 -> 0
B181: Extractive activities | C181: =+SAM!S6 -> 0 | D181: =+$C181*D$7 -> 0 | E181: =+$C181*E$7 -> 0 | F181: =+$C181*F$7 -> 0 | G181: =+$C181*G$7 -> 0 | H181: =+$C181*H$7 -> 0 | I181: =+$C181*I$7 -> 0 | J181: =+$C181*J$7 -> 0 | K181: =+$C181*K$7 -> 0 | ... AE181: =+$C181*AE$7 -> 0
B182: food manufacturing and beverage | C182: =+SAM!S7 -> 0 | D182: =+$C182*D$7 -> 0 | E182: =+$C182*E$7 -> 0 | F182: =+$C182*F$7 -> 0 | G182: =+$C182*G$7 -> 0 | H182: =+$C182*H$7 -> 0 | I182: =+$C182*I$7 -> 0 | J182: =+$C182*J$7 -> 0 | K182: =+$C182*K$7 -> 0 | ... AE182: =+$C182*AE$7 -> 0
B183: textile manufacturing and clothes | C183: =+SAM!S8 -> 0 | D183: =+$C183*D$7 -> 0 | E183: =+$C183*E$7 -> 0 | F183: =+$C183*F$7 -> 0 | G183: =+$C183*G$7 -> 0 | H183: =+$C183*H$7 -> 0 | I183: =+$C183*I$7 -> 0 | J183: =+$C183*J$7 -> 0 | K183: =+$C183*K$7 -> 0 | ... AE183: =+$C183*AE$7 -> 0
B184: Wood product manufacturing | C184: =+SAM!S9 -> 0 | D184: =+$C184*D$7 -> 0 | E184: =+$C184*E$7 -> 0 | F184: =+$C184*F$7 -> 0 | G184: =+$C184*G$7 -> 0 | H184: =+$C184*H$7 -> 0 | I184: =+$C184*I$7 -> 0 | J184: =+$C184*J$7 -> 0 | K184: =+$C184*K$7 -> 0 | ... AE184: =+$C184*AE$7 -> 0
B185: coking and refining production | C185: =+SAM!S10 -> 0 | D185: =+$C185*D$7 -> 0 | E185: =+$C185*E$7 -> 0 | F185: =+$C185*F$7 -> 0 | G185: =+$C185*G$7 -> 0 | H185: =+$C185*H$7 -> 0 | I185: =+$C185*I$7 -> 0 | J185: =+$C185*J$7 -> 0 | K185: =+$C185*K$7 -> 0 | ... AE185: =+$C185*AE$7 -> 0
B186: chemical products | C186: =+SAM!S11 -> 0.002 | D186: =+$C186*D$7 -> 0 | E186: =+$C186*E$7 -> 0 | F186: =+$C186*F$7 -> 0 | G186: =+$C186*G$7 -> 0.0016278458 | H186: =+$C186*H$7 -> 0.0018166084 | I186: =+$C186*I$7 -> 0.0020096783 | J186: =+$C186*J$7 -> 0.0022075184 | K186: =+$C186*K$7 -> 0.0024096063 | ... AE186: =+$C186*AE$7 -> 0.0073385418
B187: pharmaceutical products | C187: =+SAM!S12 -> 0 | D187: =+$C187*D$7 -> 0 | E187: =+$C187*E$7 -> 0 | F187: =+$C187*F$7 -> 0 | G187: =+$C187*G$7 -> 0 | H187: =+$C187*H$7 -> 0 | I187: =+$C187*I$7 -> 0 | J187: =+$C187*J$7 -> 0 | K187: =+$C187*K$7 -> 0 | ... AE187: =+$C187*AE$7 -> 0
B188: rubber manufacturing | C188: =+SAM!S13 -> 0 | D188: =+$C188*D$7 -> 0 | E188: =+$C188*E$7 -> 0 | F188: =+$C188*F$7 -> 0 | G188: =+$C188*G$7 -> 0 | H188: =+$C188*H$7 -> 0 | I188: =+$C188*I$7 -> 0 | J188: =+$C188*J$7 -> 0 | K188: =+$C188*K$7 -> 0 | ... AE188: =+$C188*AE$7 -> 0
B189: metalwork manufacturing | C189: =+SAM!S14 -> 0.003 | D189: =+$C189*D$7 -> 0 | E189: =+$C189*E$7 -> 0 | F189: =+$C189*F$7 -> 0 | G189: =+$C189*G$7 -> 0.0024417688 | H189: =+$C189*H$7 -> 0.0027249126 | I189: =+$C189*I$7 -> 0.0030145175 | J189: =+$C189*J$7 -> 0.0033112777 | K189: =+$C189*K$7 -> 0.0036144094 | ... AE189: =+$C189*AE$7 -> 0.011007813
... B216: imports | C216: =+SAM!S41 -> 0.003 | D216: =+$C216*D$7 -> 0 | E216: =+$C216*E$7 -> 0 | F216: =+$C216*F$7 -> 0 | G216: =+$C216*G$7 -> 0.0024417688 | H216: =+$C216*H$7 -> 0.0027249126 | I216: =+$C216*I$7 -> 0.0030145175 | J216: =+$C216*J$7 -> 0.0033112777 | K216: =+$C216*K$7 -> 0.0036144094 | ... AE216: =+$C216*AE$7 -> 0.011007813
A217: Waste - Solid waste | B217: crops | C217: =+SAM!W2 -> 0 | D217: =+$C217*D$8 -> 0 | E217: =+$C217*E$8 -> 0 | F217: =+$C217*F$8 -> 0 | G217: =+$C217*G$8 -> 0 | H217: =+$C217*H$8 -> 0 | I217: =+$C217*I$8 -> 0 | J217: =+$C217*J$8 -> 0 | K217: =+$C217*K$8 -> 0 | ... AE217: =+$C217*AE$8 -> 0
B218: forestry | C218: =+SAM!W3 -> 0 | D218: =+$C218*D$8 -> 0 | E218: =+$C218*E$8 -> 0 | F218: =+$C218*F$8 -> 0 | G218: =+$C218*G$8 -> 0 | H218: =+$C218*H$8 -> 0 | I218: =+$C218*I$8 -> 0 | J218: =+$C218*J$8 -> 0 | K218: =+$C218*K$8 -> 0 | ... AE218: =+$C218*AE$8 -> 0
B219: livestock | C219: =+SAM!W4 -> 0 | D219: =+$C219*D$8 -> 0 | E219: =+$C219*E$8 -> 0 | F219: =+$C219*F$8 -> 0 | G219: =+$C219*G$8 -> 0 | H219: =+$C219*H$8 -> 0 | I219: =+$C219*I$8 -> 0 | J219: =+$C219*J$8 -> 0 | K219: =+$C219*K$8 -> 0 | ... AE219: =+$C219*AE$8 -> 0
B220: fishery and aquaculture | C220: =+SAM!W5 -> 0 | D220: =+$C220*D$8 -> 0 | E220: =+$C220*E$8 -> 0 | F220: =+$C220*F$8 -> 0 | G220: =+$C220*G$8 -> 0 | H220: =+$C220*H$8 -> 0 | I220: =+$C220*I$8 -> 0 | J220: =+$C220*J$8 -> 0 | K220: =+$C220*K$8 -> 0 | ... AE220: =+$C220*AE$8 -> 0
B221: Extractive activities | C221: =+SAM!W6 -> 0 | D221: =+$C221*D$8 -> 0 | E221: =+$C221*E$8 -> 0 | F221: =+$C221*F$8 -> 0 | G221: =+$C221*G$8 -> 0 | H221: =+$C221*H$8 -> 0 | I221: =+$C221*I$8 -> 0 | J221: =+$C221*J$8 -> 0 | K221: =+$C221*K$8 -> 0 | ... AE221: =+$C221*AE$8 -> 0
B222: food manufacturing and beverage | C222: =+SAM!W7 -> 0 | D222: =+$C222*D$8 -> 0 | E222: =+$C222*E$8 -> 0 | F222: =+$C222*F$8 -> 0 | G222: =+$C222*G$8 -> 0 | H222: =+$C222*H$8 -> 0 | I222: =+$C222*I$8 -> 0 | J222: =+$C222*J$8 -> 0 | K222: =+$C222*K$8 -> 0 | ... AE222: =+$C222*AE$8 -> 0
B223: textile manufacturing and clothes | C223: =+SAM!W8 -> 0 | D223: =+$C223*D$8 -> 0 | E223: =+$C223*E$8 -> 0 | F223: =+$C223*F$8 -> 0 | G223: =+$C223*G$8 -> 0 | H223: =+$C223*H$8 -> 0 | I223: =+$C223*I$8 -> 0 | J223: =+$C223*J$8 -> 0 | K223: =+$C223*K$8 -> 0 | ... AE223: =+$C223*AE$8 -> 0
B224: Wood product manufacturing | C224: =+SAM!W9 -> 0 | D224: =+$C224*D$8 -> 0 | E224: =+$C224*E$8 -> 0 | F224: =+$C224*F$8 -> 0 | G224: =+$C224*G$8 -> 0 | H224: =+$C224*H$8 -> 0 | I224: =+$C224*I$8 -> 0 | J224: =+$C224*J$8 -> 0 | K224: =+$C224*K$8 -> 0 | ... AE224: =+$C224*AE$8 -> 0
B225: coking and refining production | C225: =+SAM!W10 -> 0 | D225: =+$C225*D$8 -> 0 | E225: =+$C225*E$8 -> 0 | F225: =+$C225*F$8 -> 0 | G225: =+$C225*G$8 -> 0 | H225: =+$C225*H$8 -> 0 | I225: =+$C225*I$8 -> 0 | J225: =+$C225*J$8 -> 0 | K225: =+$C225*K$8 -> 0 | ... AE225: =+$C225*AE$8 -> 0
B226: chemical products | C226: =+SAM!W11 -> 0 | D226: =+$C226*D$8 -> 0 | E226: =+$C226*E$8 -> 0 | F226: =+$C226*F$8 -> 0 | G226: =+$C226*G$8 -> 0 | H226: =+$C226*H$8 -> 0 | I226: =+$C226*I$8 -> 0 | J226: =+$C226*J$8 -> 0 | K226: =+$C226*K$8 -> 0 | ... AE226: =+$C226*AE$8 -> 0
B227: pharmaceutical products | C227: =+SAM!W12 -> 0 | D227: =+$C227*D$8 -> 0 | E227: =+$C227*E$8 -> 0 | F227: =+$C227*F$8 -> 0 | G227: =+$C227*G$8 -> 0 | H227: =+$C227*H$8 -> 0 | I227: =+$C227*I$8 -> 0 | J227: =+$C227*J$8 -> 0 | K227: =+$C227*K$8 -> 0 | ... AE227: =+$C227*AE$8 -> 0
B228: rubber manufacturing | C228: =+SAM!W13 -> 0 | D228: =+$C228*D$8 -> 0 | E228: =+$C228*E$8 -> 0 | F228: =+$C228*F$8 -> 0 | G228: =+$C228*G$8 -> 0 | H228: =+$C228*H$8 -> 0 | I228: =+$C228*I$8 -> 0 | J228: =+$C228*J$8 -> 0 | K228: =+$C228*K$8 -> 0 | ... AE228: =+$C228*AE$8 -> 0
B229: metalwork manufacturing | C229: =+SAM!W14 -> 0 | D229: =+$C229*D$8 -> 0 | E229: =+$C229*E$8 -> 0 | F229: =+$C229*F$8 -> 0 | G229: =+$C229*G$8 -> 0 | H229: =+$C229*H$8 -> 0 | I229: =+$C229*I$8 -> 0 | J229: =+$C229*J$8 -> 0 | K229: =+$C229*K$8 -> 0 | ... AE229: =+$C229*AE$8 -> 0
... B256: imports | C256: =+SAM!W41 -> 0.06 | D256: =+$C256*D$8 -> 0 | E256: =+$C256*E$8 -> 0 | F256: =+$C256*F$8 -> 0.0052231468 | G256: =+$C256*G$8 -> 0.0068148862 | H256: =+$C256*H$8 -> 0.008395614 | I256: =+$C256*I$8 -> 0.0098128639 | J256: =+$C256*J$8 -> 0.010977384 | K256: =+$C256*K$8 -> 0.01187707 | ... AE256: =+$C256*AE$8 -> 0.014989996
A257: Waste - Wastewater treatment (trww) | B257: crops | C257: =+SAM!AA2 -> 0 | D257: =+$C257*D$9 -> 0 | E257: =+$C257*E$9 -> 0 | F257: =+$C257*F$9 -> 0 | G257: =+$C257*G$9 -> 0 | H257: =+$C257*H$9 -> 0 | I257: =+$C257*I$9 -> 0 | J257: =+$C257*J$9 -> 0 | K257: =+$C257*K$9 -> 0 | ... AE257: =+$C257*AE$9 -> 0
B258: forestry | C258: =+SAM!AA3 -> 0 | D258: =+$C258*D$9 -> 0 | E258: =+$C258*E$9 -> 0 | F258: =+$C258*F$9 -> 0 | G258: =+$C258*G$9 -> 0 | H258: =+$C258*H$9 -> 0 | I258: =+$C258*I$9 -> 0 | J258: =+$C258*J$9 -> 0 | K258: =+$C258*K$9 -> 0 | ... AE258: =+$C258*AE$9 -> 0
...

Sheet Firms
C1: LTS
A2: Sector | D2: 2023 | E2: 2024 | F2: 2025 | G2: 2026 | H2: 2027 | I2: 2028 | J2: 2029 | K2: 2030 | L2: 2031 | M2: 2032 | N2: 2033 | O2: 2034 | P2: 2035 | Q2: 2036 | R2: 2037 | S2: 2038 | T2: 2039 | U2: 2040 | V2: 2041 | W2: 2042 | X2: 2043 | Y2: 2044 | Z2: 2045 | AA2: 2046 | AB2: 2047 | AC2: 2048 | AD2: 2049 | AE2: 2050
A3: EN - Power Industry | D3: =+Total!D3 -> 0 | E3: =+Total!E3 -> 0 | F3: =+Total!F3 -> 1.6405576 | G3: =+Total!G3 -> 0.34625024 | H3: =+Total!H3 -> 1.9174732 | I3: =+Total!I3 -> 2.5989561 | J3: =+Total!J3 -> 7.4215444 | K3: =+Total!K3 -> 12.361299 | ... AE3: =+Total!AE3 -> 7.1215774
A4: EN - Building | D4: =+Total!D4 -> 0 | E4: =+Total!E4 -> 0 | F4: =+Total!F4 -> 0 | G4: =+Total!G4 -> 0.012392549 | H4: =+Total!H4 -> 0.023961415 | I4: =+Total!I4 -> 0.034716882 | J4: =+Total!J4 -> 0.04467692 | K4: =+Total!K4 -> 0.064827291 | ... AE4: =+Total!AE4 -> 1.5214156
A5: EN - Transportation | D5: =+Total!D5 -> 0 | E5: =+Total!E5 -> 0 | F5: =+Total!F5 -> 0.00071354781 | G5: =+Total!G5 -> 0.0034838861 | H5: =+Total!H5 -> 0.0064159389 | I5: =+Total!I5 -> 0.0095152481 | J5: =+Total!J5 -> 0.012795081 | K5: =+Total!K5 -> 0.016253265 | ... AE5: =+Total!AE5 -> 0.73142549
A6: EN - Industrial combustion | D6: =+Total!D6 -> 0 | E6: =+Total!E6 -> 0 | F6: =+Total!F6 -> 0.014978408 | G6: =+Total!G6 -> 0.038599098 | H6: =+Total!H6 -> 0.061850965 | I6: =+Total!I6 -> 0.087728895 | J6: =+Total!J6 -> 0.11327748 | K6: =+Total!K6 -> 0.13857169 | ... AE6: =+Total!AE6 -> 0.6477426
A7: IN - Industrial processes | D7: =+Total!D7 -> 0 | E7: =+Total!E7 -> 0 | F7: =+Total!F7 -> 0 | G7: =+Total!G7 -> 0.81392292 | H7: =+Total!H7 -> 0.9083042 | I7: =+Total!I7 -> 1.0048392 | J7: =+Total!J7 -> 1.1037592 | K7: =+Total!K7 -> 1.2048031 | ... AE7: =+Total!AE7 -> 3.6692709
A8: Waste - Solid waste | D8: =+Total!D8 -> 0 | E8: =+Total!E8 -> 0 | F8: =+Total!F8 -> 0.087052446 | G8: =+Total!G8 -> 0.11358144 | H8: =+Total!H8 -> 0.1399269 | I8: =+Total!I8 -> 0.16354773 | J8: =+Total!J8 -> 0.1829564 | K8: =+Total!K8 -> 0.19795117 | ... AE8: =+Total!AE8 -> 0.24983327
A9: Waste - Wastewater treatment (trww) | D9: =+Total!D9 -> 0 | E9: =+Total!E9 -> 0 | F9: =+Total!F9 -> 0 | G9: =+Total!G9 -> 0.11709818 | H9: =+Total!H9 -> 0.24928301 | I9: =+Total!I9 -> 0.39763456 | J9: =+Total!J9 -> 0.56345437 | K9: =+Total!K9 -> 0.74777457 | ... AE9: =+Total!AE9 -> 2.9393447
A10: Waste - Wastewater (liquid waste) | D10: =+Total!D10 -> 0 | E10: =+Total!E10 -> 0 | F10: =+Total!F10 -> 0 | G10: =+Total!G10 -> 0 | H10: =+Total!H10 -> 0 | I10: =+Total!I10 -> 0 | J10: =+Total!J10 -> 0 | K10: =+Total!K10 -> 0 | ... AE10: =+Total!AE10 -> 0
A11: AG - Livestock (manure) | D11: =+Total!D11 -> 0 | E11: =+Total!E11 -> 0 | F11: =+Total!F11 -> 0 | G11: =+Total!G11 -> 0 | H11: =+Total!H11 -> 0 | I11: =+Total!I11 -> 0 | J11: =+Total!J11 -> 0 | K11: =+Total!K11 -> 0 | ... AE11: =+Total!AE11 -> 0
A12: LULUCF - Forest land | D12: =+Total!D12 -> 0 | E12: =+Total!E12 -> 0 | F12: =+Total!F12 -> 0.98551391 | G12: =+Total!G12 -> 1.217631 | H12: =+Total!H12 -> 1.4249767 | I12: =+Total!I12 -> 1.6039905 | J12: =+Total!J12 -> 1.7589536 | K12: =+Total!K12 -> 1.8900428 | ... AE12: =+Total!AE12 -> 3.2774395
A14: units: billion 2019 USD
A16: Sector | B16: SAM destination | C16: Firms rate | D16: 2023 | E16: 2024 | F16: 2025 | G16: 2026 | H16: 2027 | I16: 2028 | J16: 2029 | K16: 2030 | L16: 2031 | M16: 2032 | N16: 2033 | O16: 2034 | P16: 2035 | Q16: 2036 | R16: 2037 | S16: 2038 | T16: 2039 | U16: 2040 | V16: 2041 | W16: 2042 | X16: 2043 | Y16: 2044 | Z16: 2045 | AA16: 2046 | AB16: 2047 | AC16: 2048 | AD16: 2049 | AE16: 2050
A17: EN - Power Industry | B17: crops | C17: =+SAM!D2 -> 0 | D17: =+$C17*D$3 -> 0 | E17: =+$C17*E$3 -> 0 | F17: =+$C17*F$3 -> 0 | G17: =+$C17*G$3 -> 0 | H17: =+$C17*H$3 -> 0 | I17: =+$C17*I$3 -> 0 | J17: =+$C17*J$3 -> 0 | K17: =+$C17*K$3 -> 0 | ... AE17: =+$C17*AE$3 -> 0
B18: forestry | C18: =+SAM!D3 -> 0 | D18: =+$C18*D$3 -> 0 | E18: =+$C18*E$3 -> 0 | F18: =+$C18*F$3 -> 0 | G18: =+$C18*G$3 -> 0 | H18: =+$C18*H$3 -> 0 | I18: =+$C18*I$3 -> 0 | J18: =+$C18*J$3 -> 0 | K18: =+$C18*K$3 -> 0 | ... AE18: =+$C18*AE$3 -> 0
B19: livestock | C19: =+SAM!D4 -> 0 | D19: =+$C19*D$3 -> 0 | E19: =+$C19*E$3 -> 0 | F19: =+$C19*F$3 -> 0 | G19: =+$C19*G$3 -> 0 | H19: =+$C19*H$3 -> 0 | I19: =+$C19*I$3 -> 0 | J19: =+$C19*J$3 -> 0 | K19: =+$C19*K$3 -> 0 | ... AE19: =+$C19*AE$3 -> 0
B20: fishery and aquaculture | C20: =+SAM!D5 -> 0 | D20: =+$C20*D$3 -> 0 | E20: =+$C20*E$3 -> 0 | F20: =+$C20*F$3 -> 0 | G20: =+$C20*G$3 -> 0 | H20: =+$C20*H$3 -> 0 | I20: =+$C20*I$3 -> 0 | J20: =+$C20*J$3 -> 0 | K20: =+$C20*K$3 -> 0 | ... AE20: =+$C20*AE$3 -> 0
B21: Extractive activities | C21: =+SAM!D6 -> 0 | D21: =+$C21*D$3 -> 0 | E21: =+$C21*E$3 -> 0 | F21: =+$C21*F$3 -> 0 | G21: =+$C21*G$3 -> 0 | H21: =+$C21*H$3 -> 0 | I21: =+$C21*I$3 -> 0 | J21: =+$C21*J$3 -> 0 | K21: =+$C21*K$3 -> 0 | ... AE21: =+$C21*AE$3 -> 0
B22: food manufacturing and beverage | C22: =+SAM!D7 -> 0 | D22: =+$C22*D$3 -> 0 | E22: =+$C22*E$3 -> 0 | F22: =+$C22*F$3 -> 0 | G22: =+$C22*G$3 -> 0 | H22: =+$C22*H$3 -> 0 | I22: =+$C22*I$3 -> 0 | J22: =+$C22*J$3 -> 0 | K22: =+$C22*K$3 -> 0 | ... AE22: =+$C22*AE$3 -> 0
B23: textile manufacturing and clothes | C23: =+SAM!D8 -> 0 | D23: =+$C23*D$3 -> 0 | E23: =+$C23*E$3 -> 0 | F23: =+$C23*F$3 -> 0 | G23: =+$C23*G$3 -> 0 | H23: =+$C23*H$3 -> 0 | I23: =+$C23*I$3 -> 0 | J23: =+$C23*J$3 -> 0 | K23: =+$C23*K$3 -> 0 | ... AE23: =+$C23*AE$3 -> 0
B24: Wood product manufacturing | C24: =+SAM!D9 -> 0 | D24: =+$C24*D$3 -> 0 | E24: =+$C24*E$3 -> 0 | F24: =+$C24*F$3 -> 0 | G24: =+$C24*G$3 -> 0 | H24: =+$C24*H$3 -> 0 | I24: =+$C24*I$3 -> 0 | J24: =+$C24*J$3 -> 0 | K24: =+$C24*K$3 -> 0 | ... AE24: =+$C24*AE$3 -> 0
B25: coking and refining production | C25: =+SAM!D10 -> 0 | D25: =+$C25*D$3 -> 0 | E25: =+$C25*E$3 -> 0 | F25: =+$C25*F$3 -> 0 | G25: =+$C25*G$3 -> 0 | H25: =+$C25*H$3 -> 0 | I25: =+$C25*I$3 -> 0 | J25: =+$C25*J$3 -> 0 | K25: =+$C25*K$3 -> 0 | ... AE25: =+$C25*AE$3 -> 0
B26: chemical products | C26: =+SAM!D11 -> 0 | D26: =+$C26*D$3 -> 0 | E26: =+$C26*E$3 -> 0 | F26: =+$C26*F$3 -> 0 | G26: =+$C26*G$3 -> 0 | H26: =+$C26*H$3 -> 0 | I26: =+$C26*I$3 -> 0 | J26: =+$C26*J$3 -> 0 | K26: =+$C26*K$3 -> 0 | ... AE26: =+$C26*AE$3 -> 0
B27: pharmaceutical products | C27: =+SAM!D12 -> 0 | D27: =+$C27*D$3 -> 0 | E27: =+$C27*E$3 -> 0 | F27: =+$C27*F$3 -> 0 | G27: =+$C27*G$3 -> 0 | H27: =+$C27*H$3 -> 0 | I27: =+$C27*I$3 -> 0 | J27: =+$C27*J$3 -> 0 | K27: =+$C27*K$3 -> 0 | ... AE27: =+$C27*AE$3 -> 0
B28: rubber manufacturing | C28: =+SAM!D13 -> 0 | D28: =+$C28*D$3 -> 0 | E28: =+$C28*E$3 -> 0 | F28: =+$C28*F$3 -> 0 | G28: =+$C28*G$3 -> 0 | H28: =+$C28*H$3 -> 0 | I28: =+$C28*I$3 -> 0 | J28: =+$C28*J$3 -> 0 | K28: =+$C28*K$3 -> 0 | ... AE28: =+$C28*AE$3 -> 0
B29: metalwork manufacturing | C29: =+SAM!D14 -> 0.0531 | D29: =+$C29*D$3 -> 0 | E29: =+$C29*E$3 -> 0 | F29: =+$C29*F$3 -> 0.087113608 | G29: =+$C29*G$3 -> 0.018385888 | H29: =+$C29*H$3 -> 0.10181783 | I29: =+$C29*I$3 -> 0.13800457 | J29: =+$C29*J$3 -> 0.39408401 | K29: =+$C29*K$3 -> 0.656385 | ... AE29: =+$C29*AE$3 -> 0.37815576
... B56: imports | C56: =+SAM!D41 -> 0.41301 | D56: =+$C56*D$3 -> 0 | E56: =+$C56*E$3 -> 0 | F56: =+$C56*F$3 -> 0.67756669 | G56: =+$C56*G$3 -> 0.14300481 | H56: =+$C56*H$3 -> 0.7919356 | I56: =+$C56*I$3 -> 1.0733949 | J56: =+$C56*J$3 -> 3.065172 | K56: =+$C56*K$3 -> 5.1053403 | ... AE56: =+$C56*AE$3 -> 2.9412827
A57: EN - Building | B57: crops | C57: =+SAM!H2 -> 0 | D57: =+$C57*D$4 -> 0 | E57: =+$C57*E$4 -> 0 | F57: =+$C57*F$4 -> 0 | G57: =+$C57*G$4 -> 0 | H57: =+$C57*H$4 -> 0 | I57: =+$C57*I$4 -> 0 | J57: =+$C57*J$4 -> 0 | K57: =+$C57*K$4 -> 0 | ... AE57: =+$C57*AE$4 -> 0
B58: forestry | C58: =+SAM!H3 -> 0 | D58: =+$C58*D$4 -> 0 | E58: =+$C58*E$4 -> 0 | F58: =+$C58*F$4 -> 0 | G58: =+$C58*G$4 -> 0 | H58: =+$C58*H$4 -> 0 | I58: =+$C58*I$4 -> 0 | J58: =+$C58*J$4 -> 0 | K58: =+$C58*K$4 -> 0 | ... AE58: =+$C58*AE$4 -> 0
B59: livestock | C59: =+SAM!H4 -> 0 | D59: =+$C59*D$4 -> 0 | E59: =+$C59*E$4 -> 0 | F59: =+$C59*F$4 -> 0 | G59: =+$C59*G$4 -> 0 | H59: =+$C59*H$4 -> 0 | I59: =+$C59*I$4 -> 0 | J59: =+$C59*J$4 -> 0 | K59: =+$C59*K$4 -> 0 | ... AE59: =+$C59*AE$4 -> 0
B60: fishery and aquaculture | C60: =+SAM!H5 -> 0 | D60: =+$C60*D$4 -> 0 | E60: =+$C60*E$4 -> 0 | F60: =+$C60*F$4 -> 0 | G60: =+$C60*G$4 -> 0 | H60: =+$C60*H$4 -> 0 | I60: =+$C60*I$4 -> 0 | J60: =+$C60*J$4 -> 0 | K60: =+$C60*K$4 -> 0 | ... AE60: =+$C60*AE$4 -> 0
B61: Extractive activities | C61: =+SAM!H6 -> 0 | D61: =+$C61*D$4 -> 0 | E61: =+$C61*E$4 -> 0 | F61: =+$C61*F$4 -> 0 | G61: =+$C61*G$4 -> 0 | H61: =+$C61*H$4 -> 0 | I61: =+$C61*I$4 -> 0 | J61: =+$C61*J$4 -> 0 | K61: =+$C61*K$4 -> 0 | ... AE61: =+$C61*AE$4 -> 0
B62: food manufacturing and beverage | C62: =+SAM!H7 -> 0 | D62: =+$C62*D$4 -> 0 | E62: =+$C62*E$4 -> 0 | F62: =+$C62*F$4 -> 0 | G62: =+$C62*G$4 -> 0 | H62: =+$C62*H$4 -> 0 | I62: =+$C62*I$4 -> 0 | J62: =+$C62*J$4 -> 0 | K62: =+$C62*K$4 -> 0 | ... AE62: =+$C62*AE$4 -> 0
B63: textile manufacturing and clothes | C63: =+SAM!H8 -> 0 | D63: =+$C63*D$4 -> 0 | E63: =+$C63*E$4 -> 0 | F63: =+$C63*F$4 -> 0 | G63: =+$C63*G$4 -> 0 | H63: =+$C63*H$4 -> 0 | I63: =+$C63*I$4 -> 0 | J63: =+$C63*J$4 -> 0 | K63: =+$C63*K$4 -> 0 | ... AE63: =+$C63*AE$4 -> 0
B64: Wood product manufacturing | C64: =+SAM!H9 -> 0.0075 | D64: =+$C64*D$4 -> 0 | E64: =+$C64*E$4 -> 0 | F64: =+$C64*F$4 -> 0 | G64: =+$C64*G$4 -> 9.2944117e-05 | H64: =+$C64*H$4 -> 0.00017971061 | I64: =+$C64*I$4 -> 0.00026037661 | J64: =+$C64*J$4 -> 0.0003350769 | K64: =+$C64*K$4 -> 0.00048620468 | ... AE64: =+$C64*AE$4 -> 0.011410617
B65: coking and refining production | C65: =+SAM!H10 -> 0 | D65: =+$C65*D$4 -> 0 | E65: =+$C65*E$4 -> 0 | F65: =+$C65*F$4 -> 0 | G65: =+$C65*G$4 -> 0 | H65: =+$C65*H$4 -> 0 | I65: =+$C65*I$4 -> 0 | J65: =+$C65*J$4 -> 0 | K65: =+$C65*K$4 -> 0 | ... AE65: =+$C65*AE$4 -> 0
B66: chemical products | C66: =+SAM!H11 -> 0 | D66: =+$C66*D$4 -> 0 | E66: =+$C66*E$4 -> 0 | F66: =+$C66*F$4 -> 0 | G66: =+$C66*G$4 -> 0 | H66: =+$C66*H$4 -> 0 | I66: =+$C66*I$4 -> 0 | J66: =+$C66*J$4 -> 0 | K66: =+$C66*K$4 -> 0 | ... AE66: =+$C66*AE$4 -> 0
B67: pharmaceutical products | C67: =+SAM!H12 -> 0 | D67: =+$C67*D$4 -> 0 | E67: =+$C67*E$4 -> 0 | F67: =+$C67*F$4 -> 0 | G67: =+$C67*G$4 -> 0 | H67: =+$C67*H$4 -> 0 | I67: =+$C67*I$4 -> 0 | J67: =+$C67*J$4 -> 0 | K67: =+$C67*K$4 -> 0 | ... AE67: =+$C67*AE$4 -> 0
B68: rubber manufacturing | C68: =+SAM!H13 -> 0 | D68: =+$C68*D$4 -> 0 | E68: =+$C68*E$4 -> 0 | F68: =+$C68*F$4 -> 0 | G68: =+$C68*G$4 -> 0 | H68: =+$C68*H$4 -> 0 | I68: =+$C68*I$4 -> 0 | J68: =+$C68*J$4 -> 0 | K68: =+$C68*K$4 -> 0 | ... AE68: =+$C68*AE$4 -> 0
B69: metalwork manufacturing | C69: =+SAM!H14 -> 0 | D69: =+$C69*D$4 -> 0 | E69: =+$C69*E$4 -> 0 | F69: =+$C69*F$4 -> 0 | G69: =+$C69*G$4 -> 0 | H69: =+$C69*H$4 -> 0 | I69: =+$C69*I$4 -> 0 | J69: =+$C69*J$4 -> 0 | K69: =+$C69*K$4 -> 0 | ... AE69: =+$C69*AE$4 -> 0
... B96: imports | C96: =+SAM!H41 -> 0.1125 | D96: =+$C96*D$4 -> 0 | E96: =+$C96*E$4 -> 0 | F96: =+$C96*F$4 -> 0 | G96: =+$C96*G$4 -> 0.0013941618 | H96: =+$C96*H$4 -> 0.0026956592 | I96: =+$C96*I$4 -> 0.0039056492 | J96: =+$C96*J$4 -> 0.0050261535 | K96: =+$C96*K$4 -> 0.0072930702 | ... AE96: =+$C96*AE$4 -> 0.17115926
A97: EN - Transportation | B97: crops | C97: =+SAM!L2 -> 0 | D97: =+$C97*D$5 -> 0 | E97: =+$C97*E$5 -> 0 | F97: =+$C97*F$5 -> 0 | G97: =+$C97*G$5 -> 0 | H97: =+$C97*H$5 -> 0 | I97: =+$C97*I$5 -> 0 | J97: =+$C97*J$5 -> 0 | K97: =+$C97*K$5 -> 0 | ... AE97: =+$C97*AE$5 -> 0
B98: forestry | C98: =+SAM!L3 -> 0 | D98: =+$C98*D$5 -> 0 | E98: =+$C98*E$5 -> 0 | F98: =+$C98*F$5 -> 0 | G98: =+$C98*G$5 -> 0 | H98: =+$C98*H$5 -> 0 | I98: =+$C98*I$5 -> 0 | J98: =+$C98*J$5 -> 0 | K98: =+$C98*K$5 -> 0 | ... AE98: =+$C98*AE$5 -> 0
B99: livestock | C99: =+SAM!L4 -> 0 | D99: =+$C99*D$5 -> 0 | E99: =+$C99*E$5 -> 0 | F99: =+$C99*F$5 -> 0 | G99: =+$C99*G$5 -> 0 | H99: =+$C99*H$5 -> 0 | I99: =+$C99*I$5 -> 0 | J99: =+$C99*J$5 -> 0 | K99: =+$C99*K$5 -> 0 | ... AE99: =+$C99*AE$5 -> 0
B100: fishery and aquaculture | C100: =+SAM!L5 -> 0 | D100: =+$C100*D$5 -> 0 | E100: =+$C100*E$5 -> 0 | F100: =+$C100*F$5 -> 0 | G100: =+$C100*G$5 -> 0 | H100: =+$C100*H$5 -> 0 | I100: =+$C100*I$5 -> 0 | J100: =+$C100*J$5 -> 0 | K100: =+$C100*K$5 -> 0 | ... AE100: =+$C100*AE$5 -> 0
B101: Extractive activities | C101: =+SAM!L6 -> 0 | D101: =+$C101*D$5 -> 0 | E101: =+$C101*E$5 -> 0 | F101: =+$C101*F$5 -> 0 | G101: =+$C101*G$5 -> 0 | H101: =+$C101*H$5 -> 0 | I101: =+$C101*I$5 -> 0 | J101: =+$C101*J$5 -> 0 | K101: =+$C101*K$5 -> 0 | ... AE101: =+$C101*AE$5 -> 0
B102: food manufacturing and beverage | C102: =+SAM!L7 -> 0 | D102: =+$C102*D$5 -> 0 | E102: =+$C102*E$5 -> 0 | F102: =+$C102*F$5 -> 0 | G102: =+$C102*G$5 -> 0 | H102: =+$C102*H$5 -> 0 | I102: =+$C102*I$5 -> 0 | J102: =+$C102*J$5 -> 0 | K102: =+$C102*K$5 -> 0 | ... AE102: =+$C102*AE$5 -> 0
B103: textile manufacturing and clothes | C103: =+SAM!L8 -> 0 | D103: =+$C103*D$5 -> 0 | E103: =+$C103*E$5 -> 0 | F103: =+$C103*F$5 -> 0 | G103: =+$C103*G$5 -> 0 | H103: =+$C103*H$5 -> 0 | I103: =+$C103*I$5 -> 0 | J103: =+$C103*J$5 -> 0 | K103: =+$C103*K$5 -> 0 | ... AE103: =+$C103*AE$5 -> 0
B104: Wood product manufacturing | C104: =+SAM!L9 -> 0 | D104: =+$C104*D$5 -> 0 | E104: =+$C104*E$5 -> 0 | F104: =+$C104*F$5 -> 0 | G104: =+$C104*G$5 -> 0 | H104: =+$C104*H$5 -> 0 | I104: =+$C104*I$5 -> 0 | J104: =+$C104*J$5 -> 0 | K104: =+$C104*K$5 -> 0 | ... AE104: =+$C104*AE$5 -> 0
B105: coking and refining production | C105: =+SAM!L10 -> 0 | D105: =+$C105*D$5 -> 0 | E105: =+$C105*E$5 -> 0 | F105: =+$C105*F$5 -> 0 | G105: =+$C105*G$5 -> 0 | H105: =+$C105*H$5 -> 0 | I105: =+$C105*I$5 -> 0 | J105: =+$C105*J$5 -> 0 | K105: =+$C105*K$5 -> 0 | ... AE105: =+$C105*AE$5 -> 0
B106: chemical products | C106: =+SAM!L11 -> 0 | D106: =+$C106*D$5 -> 0 | E106: =+$C106*E$5 -> 0 | F106: =+$C106*F$5 -> 0 | G106: =+$C106*G$5 -> 0 | H106: =+$C106*H$5 -> 0 | I106: =+$C106*I$5 -> 0 | J106: =+$C106*J$5 -> 0 | K106: =+$C106*K$5 -> 0 | ... AE106: =+$C106*AE$5 -> 0
B107: pharmaceutical products | C107: =+SAM!L12 -> 0 | D107: =+$C107*D$5 -> 0 | E107: =+$C107*E$5 -> 0 | F107: =+$C107*F$5 -> 0 | G107: =+$C107*G$5 -> 0 | H107: =+$C107*H$5 -> 0 | I107: =+$C107*I$5 -> 0 | J107: =+$C107*J$5 -> 0 | K107: =+$C107*K$5 -> 0 | ... AE107: =+$C107*AE$5 -> 0
B108: rubber manufacturing | C108: =+SAM!L13 -> 0 | D108: =+$C108*D$5 -> 0 | E108: =+$C108*E$5 -> 0 | F108: =+$C108*F$5 -> 0 | G108: =+$C108*G$5 -> 0 | H108: =+$C108*H$5 -> 0 | I108: =+$C108*I$5 -> 0 | J108: =+$C108*J$5 -> 0 | K108: =+$C108*K$5 -> 0 | ... AE108: =+$C108*AE$5 -> 0
B109: metalwork manufacturing | C109: =+SAM!L14 -> 0 | D109: =+$C109*D$5 -> 0 | E109: =+$C109*E$5 -> 0 | F109: =+$C109*F$5 -> 0 | G109: =+$C109*G$5 -> 0 | H109: =+$C109*H$5 -> 0 | I109: =+$C109*I$5 -> 0 | J109: =+$C109*J$5 -> 0 | K109: =+$C109*K$5 -> 0 | ... AE109: =+$C109*AE$5 -> 0
... B136: imports | C136: =+SAM!L41 -> 0.1925 | D136: =+$C136*D$5 -> 0 | E136: =+$C136*E$5 -> 0 | F136: =+$C136*F$5 -> 0.00013735795 | G136: =+$C136*G$5 -> 0.00067064808 | H136: =+$C136*H$5 -> 0.0012350682 | I136: =+$C136*I$5 -> 0.0018316853 | J136: =+$C136*J$5 -> 0.002463053 | K136: =+$C136*K$5 -> 0.0031287536 | ... AE136: =+$C136*AE$5 -> 0.14079941
A137: EN - Industrial combustion | B137: crops | C137: =+SAM!P2 -> 0 | D137: =+$C137*D$6 -> 0 | E137: =+$C137*E$6 -> 0 | F137: =+$C137*F$6 -> 0 | G137: =+$C137*G$6 -> 0 | H137: =+$C137*H$6 -> 0 | I137: =+$C137*I$6 -> 0 | J137: =+$C137*J$6 -> 0 | K137: =+$C137*K$6 -> 0 | ... AE137: =+$C137*AE$6 -> 0
B138: forestry | C138: =+SAM!P3 -> 0 | D138: =+$C138*D$6 -> 0 | E138: =+$C138*E$6 -> 0 | F138: =+$C138*F$6 -> 0 | G138: =+$C138*G$6 -> 0 | H138: =+$C138*H$6 -> 0 | I138: =+$C138*I$6 -> 0 | J138: =+$C138*J$6 -> 0 | K138: =+$C138*K$6 -> 0 | ... AE138: =+$C138*AE$6 -> 0
B139: livestock | C139: =+SAM!P4 -> 0 | D139: =+$C139*D$6 -> 0 | E139: =+$C139*E$6 -> 0 | F139: =+$C139*F$6 -> 0 | G139: =+$C139*G$6 -> 0 | H139: =+$C139*H$6 -> 0 | I139: =+$C139*I$6 -> 0 | J139: =+$C139*J$6 -> 0 | K139: =+$C139*K$6 -> 0 | ... AE139: =+$C139*AE$6 -> 0
B140: fishery and aquaculture | C140: =+SAM!P5 -> 0 | D140: =+$C140*D$6 -> 0 | E140: =+$C140*E$6 -> 0 | F140: =+$C140*F$6 -> 0 | G140: =+$C140*G$6 -> 0 | H140: =+$C140*H$6 -> 0 | I140: =+$C140*I$6 -> 0 | J140: =+$C140*J$6 -> 0 | K140: =+$C140*K$6 -> 0 | ... AE140: =+$C140*AE$6 -> 0
B141: Extractive activities | C141: =+SAM!P6 -> 0 | D141: =+$C141*D$6 -> 0 | E141: =+$C141*E$6 -> 0 | F141: =+$C141*F$6 -> 0 | G141: =+$C141*G$6 -> 0 | H141: =+$C141*H$6 -> 0 | I141: =+$C141*I$6 -> 0 | J141: =+$C141*J$6 -> 0 | K141: =+$C141*K$6 -> 0 | ... AE141: =+$C141*AE$6 -> 0
B142: food manufacturing and beverage | C142: =+SAM!P7 -> 0 | D142: =+$C142*D$6 -> 0 | E142: =+$C142*E$6 -> 0 | F142: =+$C142*F$6 -> 0 | G142: =+$C142*G$6 -> 0 | H142: =+$C142*H$6 -> 0 | I142: =+$C142*I$6 -> 0 | J142: =+$C142*J$6 -> 0 | K142: =+$C142*K$6 -> 0 | ... AE142: =+$C142*AE$6 -> 0
B143: textile manufacturing and clothes | C143: =+SAM!P8 -> 0 | D143: =+$C143*D$6 -> 0 | E143: =+$C143*E$6 -> 0 | F143: =+$C143*F$6 -> 0 | G143: =+$C143*G$6 -> 0 | H143: =+$C143*H$6 -> 0 | I143: =+$C143*I$6 -> 0 | J143: =+$C143*J$6 -> 0 | K143: =+$C143*K$6 -> 0 | ... AE143: =+$C143*AE$6 -> 0
B144: Wood product manufacturing | C144: =+SAM!P9 -> 0 | D144: =+$C144*D$6 -> 0 | E144: =+$C144*E$6 -> 0 | F144: =+$C144*F$6 -> 0 | G144: =+$C144*G$6 -> 0 | H144: =+$C144*H$6 -> 0 | I144: =+$C144*I$6 -> 0 | J144: =+$C144*J$6 -> 0 | K144: =+$C144*K$6 -> 0 | ... AE144: =+$C144*AE$6 -> 0
B145: coking and refining production | C145: =+SAM!P10 -> 0 | D145: =+$C145*D$6 -> 0 | E145: =+$C145*E$6 -> 0 | F145: =+$C145*F$6 -> 0 | G145: =+$C145*G$6 -> 0 | H145: =+$C145*H$6 -> 0 | I145: =+$C145*I$6 -> 0 | J145: =+$C145*J$6 -> 0 | K145: =+$C145*K$6 -> 0 | ... AE145: =+$C145*AE$6 -> 0
B146: chemical products | C146: =+SAM!P11 -> 0 | D146: =+$C146*D$6 -> 0 | E146: =+$C146*E$6 -> 0 | F146: =+$C146*F$6 -> 0 | G146: =+$C146*G$6 -> 0 | H146: =+$C146*H$6 -> 0 | I146: =+$C146*I$6 -> 0 | J146: =+$C146*J$6 -> 0 | K146: =+$C146*K$6 -> 0 | ... AE146: =+$C146*AE$6 -> 0
B147: pharmaceutical products | C147: =+SAM!P12 -> 0 | D147: =+$C147*D$6 -> 0 | E147: =+$C147*E$6 -> 0 | F147: =+$C147*F$6 -> 0 | G147: =+$C147*G$6 -> 0 | H147: =+$C147*H$6 -> 0 | I147: =+$C147*I$6 -> 0 | J147: =+$C147*J$6 -> 0 | K147: =+$C147*K$6 -> 0 | ... AE147: =+$C147*AE$6 -> 0
B148: rubber manufacturing | C148: =+SAM!P13 -> 0 | D148: =+$C148*D$6 -> 0 | E148: =+$C148*E$6 -> 0 | F148: =+$C148*F$6 -> 0 | G148: =+$C148*G$6 -> 0 | H148: =+$C148*H$6 -> 0 | I148: =+$C148*I$6 -> 0 | J148: =+$C148*J$6 -> 0 | K148: =+$C148*K$6 -> 0 | ... AE148: =+$C148*AE$6 -> 0
B149: metalwork manufacturing | C149: =+SAM!P14 -> 0.108 | D149: =+$C149*D$6 -> 0 | E149: =+$C149*E$6 -> 0 | F149: =+$C149*F$6 -> 0.0016176681 | G149: =+$C149*G$6 -> 0.0041687025 | H149: =+$C149*H$6 -> 0.0066799042 | I149: =+$C149*I$6 -> 0.0094747206 | J149: =+$C149*J$6 -> 0.012233968 | K149: =+$C149*K$6 -> 0.014965742 | ... AE149: =+$C149*AE$6 -> 0.069956201
... B176: imports | C176: =+SAM!P41 -> 0.36 | D176: =+$C176*D$6 -> 0 | E176: =+$C176*E$6 -> 0 | F176: =+$C176*F$6 -> 0.0053922269 | G176: =+$C176*G$6 -> 0.013895675 | H176: =+$C176*H$6 -> 0.022266347 | I176: =+$C176*I$6 -> 0.031582402 | J176: =+$C176*J$6 -> 0.040779892 | K176: =+$C176*K$6 -> 0.049885808 | ... AE176: =+$C176*AE$6 -> 0.23318734
A177: IN - Industrial processes | B177: crops | C177: =+SAM!T2 -> 0 | D177: =+$C177*D$7 -> 0 | E177: =+$C177*E$7 -> 0 | F177: =+$C177*F$7 -> 0 | G177: =+$C177*G$7 -> 0 | H177: =+$C177*H$7 -> 0 | I177: =+$C177*I$7 -> 0 | J177: =+$C177*J$7 -> 0 | K177: =+$C177*K$7 -> 0 | ... AE177: =+$C177*AE$7 -> 0
B178: forestry | C178: =+SAM!T3 -> 0 | D178: =+$C178*D$7 -> 0 | E178: =+$C178*E$7 -> 0 | F178: =+$C178*F$7 -> 0 | G178: =+$C178*G$7 -> 0 | H178: =+$C178*H$7 -> 0 | I178: =+$C178*I$7 -> 0 | J178: =+$C178*J$7 -> 0 | K178: =+$C178*K$7 -> 0 | ... AE178: =+$C178*AE$7 -> 0
B179: livestock | C179: =+SAM!T4 -> 0 | D179: =+$C179*D$7 -> 0 | E179: =+$C179*E$7 -> 0 | F179: =+$C179*F$7 -> 0 | G179: =+$C179*G$7 -> 0 | H179: =+$C179*H$7 -> 0 | I179: =+$C179*I$7 -> 0 | J179: =+$C179*J$7 -> 0 | K179: =+$C179*K$7 -> 0 | ... AE179: =+$C179*AE$7 -> 0
B180: fishery and aquaculture | C180: =+SAM!T5 -> 0 | D180: =+$C180*D$7 -> 0 | E180: =+$C180*E$7 -> 0 | F180: =+$C180*F$7 -> 0 | G180: =+$C180*G$7 -> 0 | H180: =+$C180*H$7 -> 0 | I180: =+$C180*I$7 -> 0 | J180: =+$C180*J$7 -> 0 | K180: =+$C180*K$7 -> 0 | ... AE180: =+$C180*AE$7 -> 0
B181: Extractive activities | C181: =+SAM!T6 -> 0 | D181: =+$C181*D$7 -> 0 | E181: =+$C181*E$7 -> 0 | F181: =+$C181*F$7 -> 0 | G181: =+$C181*G$7 -> 0 | H181: =+$C181*H$7 -> 0 | I181: =+$C181*I$7 -> 0 | J181: =+$C181*J$7 -> 0 | K181: =+$C181*K$7 -> 0 | ... AE181: =+$C181*AE$7 -> 0
B182: food manufacturing and beverage | C182: =+SAM!T7 -> 0 | D182: =+$C182*D$7 -> 0 | E182: =+$C182*E$7 -> 0 | F182: =+$C182*F$7 -> 0 | G182: =+$C182*G$7 -> 0 | H182: =+$C182*H$7 -> 0 | I182: =+$C182*I$7 -> 0 | J182: =+$C182*J$7 -> 0 | K182: =+$C182*K$7 -> 0 | ... AE182: =+$C182*AE$7 -> 0
B183: textile manufacturing and clothes | C183: =+SAM!T8 -> 0 | D183: =+$C183*D$7 -> 0 | E183: =+$C183*E$7 -> 0 | F183: =+$C183*F$7 -> 0 | G183: =+$C183*G$7 -> 0 | H183: =+$C183*H$7 -> 0 | I183: =+$C183*I$7 -> 0 | J183: =+$C183*J$7 -> 0 | K183: =+$C183*K$7 -> 0 | ... AE183: =+$C183*AE$7 -> 0
B184: Wood product manufacturing | C184: =+SAM!T9 -> 0 | D184: =+$C184*D$7 -> 0 | E184: =+$C184*E$7 -> 0 | F184: =+$C184*F$7 -> 0 | G184: =+$C184*G$7 -> 0 | H184: =+$C184*H$7 -> 0 | I184: =+$C184*I$7 -> 0 | J184: =+$C184*J$7 -> 0 | K184: =+$C184*K$7 -> 0 | ... AE184: =+$C184*AE$7 -> 0
B185: coking and refining production | C185: =+SAM!T10 -> 0 | D185: =+$C185*D$7 -> 0 | E185: =+$C185*E$7 -> 0 | F185: =+$C185*F$7 -> 0 | G185: =+$C185*G$7 -> 0 | H185: =+$C185*H$7 -> 0 | I185: =+$C185*I$7 -> 0 | J185: =+$C185*J$7 -> 0 | K185: =+$C185*K$7 -> 0 | ... AE185: =+$C185*AE$7 -> 0
B186: chemical products | C186: =+SAM!T11 -> 0.098 | D186: =+$C186*D$7 -> 0 | E186: =+$C186*E$7 -> 0 | F186: =+$C186*F$7 -> 0 | G186: =+$C186*G$7 -> 0.079764446 | H186: =+$C186*H$7 -> 0.089013811 | I186: =+$C186*I$7 -> 0.098474237 | J186: =+$C186*J$7 -> 0.1081684 | K186: =+$C186*K$7 -> 0.11807071 | ... AE186: =+$C186*AE$7 -> 0.35958855
B187: pharmaceutical products | C187: =+SAM!T12 -> 0 | D187: =+$C187*D$7 -> 0 | E187: =+$C187*E$7 -> 0 | F187: =+$C187*F$7 -> 0 | G187: =+$C187*G$7 -> 0 | H187: =+$C187*H$7 -> 0 | I187: =+$C187*I$7 -> 0 | J187: =+$C187*J$7 -> 0 | K187: =+$C187*K$7 -> 0 | ... AE187: =+$C187*AE$7 -> 0
B188: rubber manufacturing | C188: =+SAM!T13 -> 0 | D188: =+$C188*D$7 -> 0 | E188: =+$C188*E$7 -> 0 | F188: =+$C188*F$7 -> 0 | G188: =+$C188*G$7 -> 0 | H188: =+$C188*H$7 -> 0 | I188: =+$C188*I$7 -> 0 | J188: =+$C188*J$7 -> 0 | K188: =+$C188*K$7 -> 0 | ... AE188: =+$C188*AE$7 -> 0
B189: metalwork manufacturing | C189: =+SAM!T14 -> 0.147 | D189: =+$C189*D$7 -> 0 | E189: =+$C189*E$7 -> 0 | F189: =+$C189*F$7 -> 0 | G189: =+$C189*G$7 -> 0.11964667 | H189: =+$C189*H$7 -> 0.13352072 | I189: =+$C189*I$7 -> 0.14771136 | J189: =+$C189*J$7 -> 0.16225261 | K189: =+$C189*K$7 -> 0.17710606 | ... AE189: =+$C189*AE$7 -> 0.53938282
... B216: imports | C216: =+SAM!T41 -> 0.147 | D216: =+$C216*D$7 -> 0 | E216: =+$C216*E$7 -> 0 | F216: =+$C216*F$7 -> 0 | G216: =+$C216*G$7 -> 0.11964667 | H216: =+$C216*H$7 -> 0.13352072 | I216: =+$C216*I$7 -> 0.14771136 | J216: =+$C216*J$7 -> 0.16225261 | K216: =+$C216*K$7 -> 0.17710606 | ... AE216: =+$C216*AE$7 -> 0.53938282
A217: Waste - Solid waste | B217: crops | C217: =+SAM!X2 -> 0 | D217: =+$C217*D$8 -> 0 | E217: =+$C217*E$8 -> 0 | F217: =+$C217*F$8 -> 0 | G217: =+$C217*G$8 -> 0 | H217: =+$C217*H$8 -> 0 | I217: =+$C217*I$8 -> 0 | J217: =+$C217*J$8 -> 0 | K217: =+$C217*K$8 -> 0 | ... AE217: =+$C217*AE$8 -> 0
B218: forestry | C218: =+SAM!X3 -> 0 | D218: =+$C218*D$8 -> 0 | E218: =+$C218*E$8 -> 0 | F218: =+$C218*F$8 -> 0 | G218: =+$C218*G$8 -> 0 | H218: =+$C218*H$8 -> 0 | I218: =+$C218*I$8 -> 0 | J218: =+$C218*J$8 -> 0 | K218: =+$C218*K$8 -> 0 | ... AE218: =+$C218*AE$8 -> 0
B219: livestock | C219: =+SAM!X4 -> 0 | D219: =+$C219*D$8 -> 0 | E219: =+$C219*E$8 -> 0 | F219: =+$C219*F$8 -> 0 | G219: =+$C219*G$8 -> 0 | H219: =+$C219*H$8 -> 0 | I219: =+$C219*I$8 -> 0 | J219: =+$C219*J$8 -> 0 | K219: =+$C219*K$8 -> 0 | ... AE219: =+$C219*AE$8 -> 0
B220: fishery and aquaculture | C220: =+SAM!X5 -> 0 | D220: =+$C220*D$8 -> 0 | E220: =+$C220*E$8 -> 0 | F220: =+$C220*F$8 -> 0 | G220: =+$C220*G$8 -> 0 | H220: =+$C220*H$8 -> 0 | I220: =+$C220*I$8 -> 0 | J220: =+$C220*J$8 -> 0 | K220: =+$C220*K$8 -> 0 | ... AE220: =+$C220*AE$8 -> 0
B221: Extractive activities | C221: =+SAM!X6 -> 0 | D221: =+$C221*D$8 -> 0 | E221: =+$C221*E$8 -> 0 | F221: =+$C221*F$8 -> 0 | G221: =+$C221*G$8 -> 0 | H221: =+$C221*H$8 -> 0 | I221: =+$C221*I$8 -> 0 | J221: =+$C221*J$8 -> 0 | K221: =+$C221*K$8 -> 0 | ... AE221: =+$C221*AE$8 -> 0
B222: food manufacturing and beverage | C222: =+SAM!X7 -> 0 | D222: =+$C222*D$8 -> 0 | E222: =+$C222*E$8 -> 0 | F222: =+$C222*F$8 -> 0 | G222: =+$C222*G$8 -> 0 | H222: =+$C222*H$8 -> 0 | I222: =+$C222*I$8 -> 0 | J222: =+$C222*J$8 -> 0 | K222: =+$C222*K$8 -> 0 | ... AE222: =+$C222*AE$8 -> 0
B223: textile manufacturing and clothes | C223: =+SAM!X8 -> 0 | D223: =+$C223*D$8 -> 0 | E223: =+$C223*E$8 -> 0 | F223: =+$C223*F$8 -> 0 | G223: =+$C223*G$8 -> 0 | H223: =+$C223*H$8 -> 0 | I223: =+$C223*I$8 -> 0 | J223: =+$C223*J$8 -> 0 | K223: =+$C223*K$8 -> 0 | ... AE223: =+$C223*AE$8 -> 0
B224: Wood product manufacturing | C224: =+SAM!X9 -> 0 | D224: =+$C224*D$8 -> 0 | E224: =+$C224*E$8 -> 0 | F224: =+$C224*F$8 -> 0 | G224: =+$C224*G$8 -> 0 | H224: =+$C224*H$8 -> 0 | I224: =+$C224*I$8 -> 0 | J224: =+$C224*J$8 -> 0 | K224: =+$C224*K$8 -> 0 | ... AE224: =+$C224*AE$8 -> 0
B225: coking and refining production | C225: =+SAM!X10 -> 0 | D225: =+$C225*D$8 -> 0 | E225: =+$C225*E$8 -> 0 | F225: =+$C225*F$8 -> 0 | G225: =+$C225*G$8 -> 0 | H225: =+$C225*H$8 -> 0 | I225: =+$C225*I$8 -> 0 | J225: =+$C225*J$8 -> 0 | K225: =+$C225*K$8 -> 0 | ... AE225: =+$C225*AE$8 -> 0
B226: chemical products | C226: =+SAM!X11 -> 0 | D226: =+$C226*D$8 -> 0 | E226: =+$C226*E$8 -> 0 | F226: =+$C226*F$8 -> 0 | G226: =+$C226*G$8 -> 0 | H226: =+$C226*H$8 -> 0 | I226: =+$C226*I$8 -> 0 | J226: =+$C226*J$8 -> 0 | K226: =+$C226*K$8 -> 0 | ... AE226: =+$C226*AE$8 -> 0
B227: pharmaceutical products | C227: =+SAM!X12 -> 0 | D227: =+$C227*D$8 -> 0 | E227: =+$C227*E$8 -> 0 | F227: =+$C227*F$8 -> 0 | G227: =+$C227*G$8 -> 0 | H227: =+$C227*H$8 -> 0 | I227: =+$C227*I$8 -> 0 | J227: =+$C227*J$8 -> 0 | K227: =+$C227*K$8 -> 0 | ... AE227: =+$C227*AE$8 -> 0
B228: rubber manufacturing | C228: =+SAM!X13 -> 0 | D228: =+$C228*D$8 -> 0 | E228: =+$C228*E$8 -> 0 | F228: =+$C228*F$8 -> 0 | G228: =+$C228*G$8 -> 0 | H228: =+$C228*H$8 -> 0 | I228: =+$C228*I$8 -> 0 | J228: =+$C228*J$8 -> 0 | K228: =+$C228*K$8 -> 0 | ... AE228: =+$C228*AE$8 -> 0
B229: metalwork manufacturing | C229: =+SAM!X14 -> 0 | D229: =+$C229*D$8 -> 0 | E229: =+$C229*E$8 -> 0 | F229: =+$C229*F$8 -> 0 | G229: =+$C229*G$8 -> 0 | H229: =+$C229*H$8 -> 0 | I229: =+$C229*I$8 -> 0 | J229: =+$C229*J$8 -> 0 | K229: =+$C229*K$8 -> 0 | ... AE229: =+$C229*AE$8 -> 0
... B256: imports | C256: =+SAM!X41 -> 0.06 | D256: =+$C256*D$8 -> 0 | E256: =+$C256*E$8 -> 0 | F256: =+$C256*F$8 -> 0.0052231468 | G256: =+$C256*G$8 -> 0.0068148862 | H256: =+$C256*H$8 -> 0.008395614 | I256: =+$C256*I$8 -> 0.0098128639 | J256: =+$C256*J$8 -> 0.010977384 | K256: =+$C256*K$8 -> 0.01187707 | ... AE256: =+$C256*AE$8 -> 0.014989996
A257: Waste - Wastewater treatment (trww) | B257: crops | C257: =+SAM!AB2 -> 0 | D257: =+$C257*D$9 -> 0 | E257: =+$C257*E$9 -> 0 | F257: =+$C257*F$9 -> 0 | G257: =+$C257*G$9 -> 0 | H257: =+$C257*H$9 -> 0 | I257: =+$C257*I$9 -> 0 | J257: =+$C257*J$9 -> 0 | K257: =+$C257*K$9 -> 0 | ... AE257: =+$C257*AE$9 -> 0
B258: forestry | C258: =+SAM!AB3 -> 0 | D258: =+$C258*D$9 -> 0 | E258: =+$C258*E$9 -> 0 | F258: =+$C258*F$9 -> 0 | G258: =+$C258*G$9 -> 0 | H258: =+$C258*H$9 -> 0 | I258: =+$C258*I$9 -> 0 | J258: =+$C258*J$9 -> 0 | K258: =+$C258*K$9 -> 0 | ... AE258: =+$C258*AE$9 -> 0
...

Sheet Households
C1: LTS
A2: Sector | D2: 2023 | E2: 2024 | F2: 2025 | G2: 2026 | H2: 2027 | I2: 2028 | J2: 2029 | K2: 2030 | L2: 2031 | M2: 2032 | N2: 2033 | O2: 2034 | P2: 2035 | Q2: 2036 | R2: 2037 | S2: 2038 | T2: 2039 | U2: 2040 | V2: 2041 | W2: 2042 | X2: 2043 | Y2: 2044 | Z2: 2045 | AA2: 2046 | AB2: 2047 | AC2: 2048 | AD2: 2049 | AE2: 2050
A3: EN - Power Industry | D3: =+Total!D3 -> 0 | E3: =+Total!E3 -> 0 | F3: =+Total!F3 -> 1.6405576 | G3: =+Total!G3 -> 0.34625024 | H3: =+Total!H3 -> 1.9174732 | I3: =+Total!I3 -> 2.5989561 | J3: =+Total!J3 -> 7.4215444 | K3: =+Total!K3 -> 12.361299 | ... AE3: =+Total!AE3 -> 7.1215774
A4: EN - Building | D4: =+Total!D4 -> 0 | E4: =+Total!E4 -> 0 | F4: =+Total!F4 -> 0 | G4: =+Total!G4 -> 0.012392549 | H4: =+Total!H4 -> 0.023961415 | I4: =+Total!I4 -> 0.034716882 | J4: =+Total!J4 -> 0.04467692 | K4: =+Total!K4 -> 0.064827291 | ... AE4: =+Total!AE4 -> 1.5214156
A5: EN - Transportation | D5: =+Total!D5 -> 0 | E5: =+Total!E5 -> 0 | F5: =+Total!F5 -> 0.00071354781 | G5: =+Total!G5 -> 0.0034838861 | H5: =+Total!H5 -> 0.0064159389 | I5: =+Total!I5 -> 0.0095152481 | J5: =+Total!J5 -> 0.012795081 | K5: =+Total!K5 -> 0.016253265 | ... AE5: =+Total!AE5 -> 0.73142549
A6: EN - Industrial combustion | D6: =+Total!D6 -> 0 | E6: =+Total!E6 -> 0 | F6: =+Total!F6 -> 0.014978408 | G6: =+Total!G6 -> 0.038599098 | H6: =+Total!H6 -> 0.061850965 | I6: =+Total!I6 -> 0.087728895 | J6: =+Total!J6 -> 0.11327748 | K6: =+Total!K6 -> 0.13857169 | ... AE6: =+Total!AE6 -> 0.6477426
A7: IN - Industrial processes | D7: =+Total!D7 -> 0 | E7: =+Total!E7 -> 0 | F7: =+Total!F7 -> 0 | G7: =+Total!G7 -> 0.81392292 | H7: =+Total!H7 -> 0.9083042 | I7: =+Total!I7 -> 1.0048392 | J7: =+Total!J7 -> 1.1037592 | K7: =+Total!K7 -> 1.2048031 | ... AE7: =+Total!AE7 -> 3.6692709
A8: Waste - Solid waste | D8: =+Total!D8 -> 0 | E8: =+Total!E8 -> 0 | F8: =+Total!F8 -> 0.087052446 | G8: =+Total!G8 -> 0.11358144 | H8: =+Total!H8 -> 0.1399269 | I8: =+Total!I8 -> 0.16354773 | J8: =+Total!J8 -> 0.1829564 | K8: =+Total!K8 -> 0.19795117 | ... AE8: =+Total!AE8 -> 0.24983327
A9: Waste - Wastewater treatment (trww) | D9: =+Total!D9 -> 0 | E9: =+Total!E9 -> 0 | F9: =+Total!F9 -> 0 | G9: =+Total!G9 -> 0.11709818 | H9: =+Total!H9 -> 0.24928301 | I9: =+Total!I9 -> 0.39763456 | J9: =+Total!J9 -> 0.56345437 | K9: =+Total!K9 -> 0.74777457 | ... AE9: =+Total!AE9 -> 2.9393447
A10: Waste - Wastewater (liquid waste) | D10: =+Total!D10 -> 0 | E10: =+Total!E10 -> 0 | F10: =+Total!F10 -> 0 | G10: =+Total!G10 -> 0 | H10: =+Total!H10 -> 0 | I10: =+Total!I10 -> 0 | J10: =+Total!J10 -> 0 | K10: =+Total!K10 -> 0 | ... AE10: =+Total!AE10 -> 0
A11: AG - Livestock (manure) | D11: =+Total!D11 -> 0 | E11: =+Total!E11 -> 0 | F11: =+Total!F11 -> 0 | G11: =+Total!G11 -> 0 | H11: =+Total!H11 -> 0 | I11: =+Total!I11 -> 0 | J11: =+Total!J11 -> 0 | K11: =+Total!K11 -> 0 | ... AE11: =+Total!AE11 -> 0
A12: LULUCF - Forest land | D12: =+Total!D12 -> 0 | E12: =+Total!E12 -> 0 | F12: =+Total!F12 -> 0.98551391 | G12: =+Total!G12 -> 1.217631 | H12: =+Total!H12 -> 1.4249767 | I12: =+Total!I12 -> 1.6039905 | J12: =+Total!J12 -> 1.7589536 | K12: =+Total!K12 -> 1.8900428 | ... AE12: =+Total!AE12 -> 3.2774395
A14: units: billion 2019 USD
A16: Sector | B16: SAM destination | C16: Households rate | D16: 2023 | E16: 2024 | F16: 2025 | G16: 2026 | H16: 2027 | I16: 2028 | J16: 2029 | K16: 2030 | L16: 2031 | M16: 2032 | N16: 2033 | O16: 2034 | P16: 2035 | Q16: 2036 | R16: 2037 | S16: 2038 | T16: 2039 | U16: 2040 | V16: 2041 | W16: 2042 | X16: 2043 | Y16: 2044 | Z16: 2045 | AA16: 2046 | AB16: 2047 | AC16: 2048 | AD16: 2049 | AE16: 2050
A17: EN - Power Industry | B17: crops | C17: =+SAM!E2 -> 0 | D17: =+$C17*D$3 -> 0 | E17: =+$C17*E$3 -> 0 | F17: =+$C17*F$3 -> 0 | G17: =+$C17*G$3 -> 0 | H17: =+$C17*H$3 -> 0 | I17: =+$C17*I$3 -> 0 | J17: =+$C17*J$3 -> 0 | K17: =+$C17*K$3 -> 0 | ... AE17: =+$C17*AE$3 -> 0
B18: forestry | C18: =+SAM!E3 -> 0 | D18: =+$C18*D$3 -> 0 | E18: =+$C18*E$3 -> 0 | F18: =+$C18*F$3 -> 0 | G18: =+$C18*G$3 -> 0 | H18: =+$C18*H$3 -> 0 | I18: =+$C18*I$3 -> 0 | J18: =+$C18*J$3 -> 0 | K18: =+$C18*K$3 -> 0 | ... AE18: =+$C18*AE$3 -> 0
B19: livestock | C19: =+SAM!E4 -> 0 | D19: =+$C19*D$3 -> 0 | E19: =+$C19*E$3 -> 0 | F19: =+$C19*F$3 -> 0 | G19: =+$C19*G$3 -> 0 | H19: =+$C19*H$3 -> 0 | I19: =+$C19*I$3 -> 0 | J19: =+$C19*J$3 -> 0 | K19: =+$C19*K$3 -> 0 | ... AE19: =+$C19*AE$3 -> 0
B20: fishery and aquaculture | C20: =+SAM!E5 -> 0 | D20: =+$C20*D$3 -> 0 | E20: =+$C20*E$3 -> 0 | F20: =+$C20*F$3 -> 0 | G20: =+$C20*G$3 -> 0 | H20: =+$C20*H$3 -> 0 | I20: =+$C20*I$3 -> 0 | J20: =+$C20*J$3 -> 0 | K20: =+$C20*K$3 -> 0 | ... AE20: =+$C20*AE$3 -> 0
B21: Extractive activities | C21: =+SAM!E6 -> 0 | D21: =+$C21*D$3 -> 0 | E21: =+$C21*E$3 -> 0 | F21: =+$C21*F$3 -> 0 | G21: =+$C21*G$3 -> 0 | H21: =+$C21*H$3 -> 0 | I21: =+$C21*I$3 -> 0 | J21: =+$C21*J$3 -> 0 | K21: =+$C21*K$3 -> 0 | ... AE21: =+$C21*AE$3 -> 0
B22: food manufacturing and beverage | C22: =+SAM!E7 -> 0 | D22: =+$C22*D$3 -> 0 | E22: =+$C22*E$3 -> 0 | F22: =+$C22*F$3 -> 0 | G22: =+$C22*G$3 -> 0 | H22: =+$C22*H$3 -> 0 | I22: =+$C22*I$3 -> 0 | J22: =+$C22*J$3 -> 0 | K22: =+$C22*K$3 -> 0 | ... AE22: =+$C22*AE$3 -> 0
B23: textile manufacturing and clothes | C23: =+SAM!E8 -> 0 | D23: =+$C23*D$3 -> 0 | E23: =+$C23*E$3 -> 0 | F23: =+$C23*F$3 -> 0 | G23: =+$C23*G$3 -> 0 | H23: =+$C23*H$3 -> 0 | I23: =+$C23*I$3 -> 0 | J23: =+$C23*J$3 -> 0 | K23: =+$C23*K$3 -> 0 | ... AE23: =+$C23*AE$3 -> 0
B24: Wood product manufacturing | C24: =+SAM!E9 -> 0 | D24: =+$C24*D$3 -> 0 | E24: =+$C24*E$3 -> 0 | F24: =+$C24*F$3 -> 0 | G24: =+$C24*G$3 -> 0 | H24: =+$C24*H$3 -> 0 | I24: =+$C24*I$3 -> 0 | J24: =+$C24*J$3 -> 0 | K24: =+$C24*K$3 -> 0 | ... AE24: =+$C24*AE$3 -> 0
B25: coking and refining production | C25: =+SAM!E10 -> 0 | D25: =+$C25*D$3 -> 0 | E25: =+$C25*E$3 -> 0 | F25: =+$C25*F$3 -> 0 | G25: =+$C25*G$3 -> 0 | H25: =+$C25*H$3 -> 0 | I25: =+$C25*I$3 -> 0 | J25: =+$C25*J$3 -> 0 | K25: =+$C25*K$3 -> 0 | ... AE25: =+$C25*AE$3 -> 0
B26: chemical products | C26: =+SAM!E11 -> 0 | D26: =+$C26*D$3 -> 0 | E26: =+$C26*E$3 -> 0 | F26: =+$C26*F$3 -> 0 | G26: =+$C26*G$3 -> 0 | H26: =+$C26*H$3 -> 0 | I26: =+$C26*I$3 -> 0 | J26: =+$C26*J$3 -> 0 | K26: =+$C26*K$3 -> 0 | ... AE26: =+$C26*AE$3 -> 0
B27: pharmaceutical products | C27: =+SAM!E12 -> 0 | D27: =+$C27*D$3 -> 0 | E27: =+$C27*E$3 -> 0 | F27: =+$C27*F$3 -> 0 | G27: =+$C27*G$3 -> 0 | H27: =+$C27*H$3 -> 0 | I27: =+$C27*I$3 -> 0 | J27: =+$C27*J$3 -> 0 | K27: =+$C27*K$3 -> 0 | ... AE27: =+$C27*AE$3 -> 0
B28: rubber manufacturing | C28: =+SAM!E13 -> 0 | D28: =+$C28*D$3 -> 0 | E28: =+$C28*E$3 -> 0 | F28: =+$C28*F$3 -> 0 | G28: =+$C28*G$3 -> 0 | H28: =+$C28*H$3 -> 0 | I28: =+$C28*I$3 -> 0 | J28: =+$C28*J$3 -> 0 | K28: =+$C28*K$3 -> 0 | ... AE28: =+$C28*AE$3 -> 0
B29: metalwork manufacturing | C29: =+SAM!E14 -> 0.00295 | D29: =+$C29*D$3 -> 0 | E29: =+$C29*E$3 -> 0 | F29: =+$C29*F$3 -> 0.0048396449 | G29: =+$C29*G$3 -> 0.0010214382 | H29: =+$C29*H$3 -> 0.0056565459 | I29: =+$C29*I$3 -> 0.0076669205 | J29: =+$C29*J$3 -> 0.021893556 | K29: =+$C29*K$3 -> 0.036465833 | ... AE29: =+$C29*AE$3 -> 0.021008653
... B56: imports | C56: =+SAM!E41 -> 0.022945 | D56: =+$C56*D$3 -> 0 | E56: =+$C56*E$3 -> 0 | F56: =+$C56*F$3 -> 0.037642594 | G56: =+$C56*G$3 -> 0.0079447118 | H56: =+$C56*H$3 -> 0.043996422 | I56: =+$C56*I$3 -> 0.059633048 | J56: =+$C56*J$3 -> 0.17028734 | K56: =+$C56*K$3 -> 0.28363001 | ... AE56: =+$C56*AE$3 -> 0.16340459
A57: EN - Building | B57: crops | C57: =+SAM!I2 -> 0 | D57: =+$C57*D$4 -> 0 | E57: =+$C57*E$4 -> 0 | F57: =+$C57*F$4 -> 0 | G57: =+$C57*G$4 -> 0 | H57: =+$C57*H$4 -> 0 | I57: =+$C57*I$4 -> 0 | J57: =+$C57*J$4 -> 0 | K57: =+$C57*K$4 -> 0 | ... AE57: =+$C57*AE$4 -> 0
B58: forestry | C58: =+SAM!I3 -> 0 | D58: =+$C58*D$4 -> 0 | E58: =+$C58*E$4 -> 0 | F58: =+$C58*F$4 -> 0 | G58: =+$C58*G$4 -> 0 | H58: =+$C58*H$4 -> 0 | I58: =+$C58*I$4 -> 0 | J58: =+$C58*J$4 -> 0 | K58: =+$C58*K$4 -> 0 | ... AE58: =+$C58*AE$4 -> 0
B59: livestock | C59: =+SAM!I4 -> 0 | D59: =+$C59*D$4 -> 0 | E59: =+$C59*E$4 -> 0 | F59: =+$C59*F$4 -> 0 | G59: =+$C59*G$4 -> 0 | H59: =+$C59*H$4 -> 0 | I59: =+$C59*I$4 -> 0 | J59: =+$C59*J$4 -> 0 | K59: =+$C59*K$4 -> 0 | ... AE59: =+$C59*AE$4 -> 0
B60: fishery and aquaculture | C60: =+SAM!I5 -> 0 | D60: =+$C60*D$4 -> 0 | E60: =+$C60*E$4 -> 0 | F60: =+$C60*F$4 -> 0 | G60: =+$C60*G$4 -> 0 | H60: =+$C60*H$4 -> 0 | I60: =+$C60*I$4 -> 0 | J60: =+$C60*J$4 -> 0 | K60: =+$C60*K$4 -> 0 | ... AE60: =+$C60*AE$4 -> 0
B61: Extractive activities | C61: =+SAM!I6 -> 0 | D61: =+$C61*D$4 -> 0 | E61: =+$C61*E$4 -> 0 | F61: =+$C61*F$4 -> 0 | G61: =+$C61*G$4 -> 0 | H61: =+$C61*H$4 -> 0 | I61: =+$C61*I$4 -> 0 | J61: =+$C61*J$4 -> 0 | K61: =+$C61*K$4 -> 0 | ... AE61: =+$C61*AE$4 -> 0
B62: food manufacturing and beverage | C62: =+SAM!I7 -> 0 | D62: =+$C62*D$4 -> 0 | E62: =+$C62*E$4 -> 0 | F62: =+$C62*F$4 -> 0 | G62: =+$C62*G$4 -> 0 | H62: =+$C62*H$4 -> 0 | I62: =+$C62*I$4 -> 0 | J62: =+$C62*J$4 -> 0 | K62: =+$C62*K$4 -> 0 | ... AE62: =+$C62*AE$4 -> 0
B63: textile manufacturing and clothes | C63: =+SAM!I8 -> 0 | D63: =+$C63*D$4 -> 0 | E63: =+$C63*E$4 -> 0 | F63: =+$C63*F$4 -> 0 | G63: =+$C63*G$4 -> 0 | H63: =+$C63*H$4 -> 0 | I63: =+$C63*I$4 -> 0 | J63: =+$C63*J$4 -> 0 | K63: =+$C63*K$4 -> 0 | ... AE63: =+$C63*AE$4 -> 0
B64: Wood product manufacturing | C64: =+SAM!I9 -> 0.015 | D64: =+$C64*D$4 -> 0 | E64: =+$C64*E$4 -> 0 | F64: =+$C64*F$4 -> 0 | G64: =+$C64*G$4 -> 0.00018588823 | H64: =+$C64*H$4 -> 0.00035942123 | I64: =+$C64*I$4 -> 0.00052075323 | J64: =+$C64*J$4 -> 0.0006701538 | K64: =+$C64*K$4 -> 0.00097240936 | ... AE64: =+$C64*AE$4 -> 0.022821234
B65: coking and refining production | C65: =+SAM!I10 -> 0 | D65: =+$C65*D$4 -> 0 | E65: =+$C65*E$4 -> 0 | F65: =+$C65*F$4 -> 0 | G65: =+$C65*G$4 -> 0 | H65: =+$C65*H$4 -> 0 | I65: =+$C65*I$4 -> 0 | J65: =+$C65*J$4 -> 0 | K65: =+$C65*K$4 -> 0 | ... AE65: =+$C65*AE$4 -> 0
B66: chemical products | C66: =+SAM!I11 -> 0 | D66: =+$C66*D$4 -> 0 | E66: =+$C66*E$4 -> 0 | F66: =+$C66*F$4 -> 0 | G66: =+$C66*G$4 -> 0 | H66: =+$C66*H$4 -> 0 | I66: =+$C66*I$4 -> 0 | J66: =+$C66*J$4 -> 0 | K66: =+$C66*K$4 -> 0 | ... AE66: =+$C66*AE$4 -> 0
B67: pharmaceutical products | C67: =+SAM!I12 -> 0 | D67: =+$C67*D$4 -> 0 | E67: =+$C67*E$4 -> 0 | F67: =+$C67*F$4 -> 0 | G67: =+$C67*G$4 -> 0 | H67: =+$C67*H$4 -> 0 | I67: =+$C67*I$4 -> 0 | J67: =+$C67*J$4 -> 0 | K67: =+$C67*K$4 -> 0 | ... AE67: =+$C67*AE$4 -> 0
B68: rubber manufacturing | C68: =+SAM!I13 -> 0 | D68: =+$C68*D$4 -> 0 | E68: =+$C68*E$4 -> 0 | F68: =+$C68*F$4 -> 0 | G68: =+$C68*G$4 -> 0 | H68: =+$C68*H$4 -> 0 | I68: =+$C68*I$4 -> 0 | J68: =+$C68*J$4 -> 0 | K68: =+$C68*K$4 -> 0 | ... AE68: =+$C68*AE$4 -> 0
B69: metalwork manufacturing | C69: =+SAM!I14 -> 0 | D69: =+$C69*D$4 -> 0 | E69: =+$C69*E$4 -> 0 | F69: =+$C69*F$4 -> 0 | G69: =+$C69*G$4 -> 0 | H69: =+$C69*H$4 -> 0 | I69: =+$C69*I$4 -> 0 | J69: =+$C69*J$4 -> 0 | K69: =+$C69*K$4 -> 0 | ... AE69: =+$C69*AE$4 -> 0
... B96: imports | C96: =+SAM!I41 -> 0.225 | D96: =+$C96*D$4 -> 0 | E96: =+$C96*E$4 -> 0 | F96: =+$C96*F$4 -> 0 | G96: =+$C96*G$4 -> 0.0027883235 | H96: =+$C96*H$4 -> 0.0053913184 | I96: =+$C96*I$4 -> 0.0078112984 | J96: =+$C96*J$4 -> 0.010052307 | K96: =+$C96*K$4 -> 0.01458614 | ... AE96: =+$C96*AE$4 -> 0.34231852
A97: EN - Transportation | B97: crops | C97: =+SAM!M2 -> 0 | D97: =+$C97*D$5 -> 0 | E97: =+$C97*E$5 -> 0 | F97: =+$C97*F$5 -> 0 | G97: =+$C97*G$5 -> 0 | H97: =+$C97*H$5 -> 0 | I97: =+$C97*I$5 -> 0 | J97: =+$C97*J$5 -> 0 | K97: =+$C97*K$5 -> 0 | ... AE97: =+$C97*AE$5 -> 0
B98: forestry | C98: =+SAM!M3 -> 0 | D98: =+$C98*D$5 -> 0 | E98: =+$C98*E$5 -> 0 | F98: =+$C98*F$5 -> 0 | G98: =+$C98*G$5 -> 0 | H98: =+$C98*H$5 -> 0 | I98: =+$C98*I$5 -> 0 | J98: =+$C98*J$5 -> 0 | K98: =+$C98*K$5 -> 0 | ... AE98: =+$C98*AE$5 -> 0
B99: livestock | C99: =+SAM!M4 -> 0 | D99: =+$C99*D$5 -> 0 | E99: =+$C99*E$5 -> 0 | F99: =+$C99*F$5 -> 0 | G99: =+$C99*G$5 -> 0 | H99: =+$C99*H$5 -> 0 | I99: =+$C99*I$5 -> 0 | J99: =+$C99*J$5 -> 0 | K99: =+$C99*K$5 -> 0 | ... AE99: =+$C99*AE$5 -> 0
B100: fishery and aquaculture | C100: =+SAM!M5 -> 0 | D100: =+$C100*D$5 -> 0 | E100: =+$C100*E$5 -> 0 | F100: =+$C100*F$5 -> 0 | G100: =+$C100*G$5 -> 0 | H100: =+$C100*H$5 -> 0 | I100: =+$C100*I$5 -> 0 | J100: =+$C100*J$5 -> 0 | K100: =+$C100*K$5 -> 0 | ... AE100: =+$C100*AE$5 -> 0
B101: Extractive activities | C101: =+SAM!M6 -> 0 | D101: =+$C101*D$5 -> 0 | E101: =+$C101*E$5 -> 0 | F101: =+$C101*F$5 -> 0 | G101: =+$C101*G$5 -> 0 | H101: =+$C101*H$5 -> 0 | I101: =+$C101*I$5 -> 0 | J101: =+$C101*J$5 -> 0 | K101: =+$C101*K$5 -> 0 | ... AE101: =+$C101*AE$5 -> 0
B102: food manufacturing and beverage | C102: =+SAM!M7 -> 0 | D102: =+$C102*D$5 -> 0 | E102: =+$C102*E$5 -> 0 | F102: =+$C102*F$5 -> 0 | G102: =+$C102*G$5 -> 0 | H102: =+$C102*H$5 -> 0 | I102: =+$C102*I$5 -> 0 | J102: =+$C102*J$5 -> 0 | K102: =+$C102*K$5 -> 0 | ... AE102: =+$C102*AE$5 -> 0
B103: textile manufacturing and clothes | C103: =+SAM!M8 -> 0 | D103: =+$C103*D$5 -> 0 | E103: =+$C103*E$5 -> 0 | F103: =+$C103*F$5 -> 0 | G103: =+$C103*G$5 -> 0 | H103: =+$C103*H$5 -> 0 | I103: =+$C103*I$5 -> 0 | J103: =+$C103*J$5 -> 0 | K103: =+$C103*K$5 -> 0 | ... AE103: =+$C103*AE$5 -> 0
B104: Wood product manufacturing | C104: =+SAM!M9 -> 0 | D104: =+$C104*D$5 -> 0 | E104: =+$C104*E$5 -> 0 | F104: =+$C104*F$5 -> 0 | G104: =+$C104*G$5 -> 0 | H104: =+$C104*H$5 -> 0 | I104: =+$C104*I$5 -> 0 | J104: =+$C104*J$5 -> 0 | K104: =+$C104*K$5 -> 0 | ... AE104: =+$C104*AE$5 -> 0
B105: coking and refining production | C105: =+SAM!M10 -> 0 | D105: =+$C105*D$5 -> 0 | E105: =+$C105*E$5 -> 0 | F105: =+$C105*F$5 -> 0 | G105: =+$C105*G$5 -> 0 | H105: =+$C105*H$5 -> 0 | I105: =+$C105*I$5 -> 0 | J105: =+$C105*J$5 -> 0 | K105: =+$C105*K$5 -> 0 | ... AE105: =+$C105*AE$5 -> 0
B106: chemical products | C106: =+SAM!M11 -> 0 | D106: =+$C106*D$5 -> 0 | E106: =+$C106*E$5 -> 0 | F106: =+$C106*F$5 -> 0 | G106: =+$C106*G$5 -> 0 | H106: =+$C106*H$5 -> 0 | I106: =+$C106*I$5 -> 0 | J106: =+$C106*J$5 -> 0 | K106: =+$C106*K$5 -> 0 | ... AE106: =+$C106*AE$5 -> 0
B107: pharmaceutical products | C107: =+SAM!M12 -> 0 | D107: =+$C107*D$5 -> 0 | E107: =+$C107*E$5 -> 0 | F107: =+$C107*F$5 -> 0 | G107: =+$C107*G$5 -> 0 | H107: =+$C107*H$5 -> 0 | I107: =+$C107*I$5 -> 0 | J107: =+$C107*J$5 -> 0 | K107: =+$C107*K$5 -> 0 | ... AE107: =+$C107*AE$5 -> 0
B108: rubber manufacturing | C108: =+SAM!M13 -> 0 | D108: =+$C108*D$5 -> 0 | E108: =+$C108*E$5 -> 0 | F108: =+$C108*F$5 -> 0 | G108: =+$C108*G$5 -> 0 | H108: =+$C108*H$5 -> 0 | I108: =+$C108*I$5 -> 0 | J108: =+$C108*J$5 -> 0 | K108: =+$C108*K$5 -> 0 | ... AE108: =+$C108*AE$5 -> 0
B109: metalwork manufacturing | C109: =+SAM!M14 -> 0 | D109: =+$C109*D$5 -> 0 | E109: =+$C109*E$5 -> 0 | F109: =+$C109*F$5 -> 0 | G109: =+$C109*G$5 -> 0 | H109: =+$C109*H$5 -> 0 | I109: =+$C109*I$5 -> 0 | J109: =+$C109*J$5 -> 0 | K109: =+$C109*K$5 -> 0 | ... AE109: =+$C109*AE$5 -> 0
... B136: imports | C136: =+SAM!M41 -> 0.275 | D136: =+$C136*D$5 -> 0 | E136: =+$C136*E$5 -> 0 | F136: =+$C136*F$5 -> 0.00019622565 | G136: =+$C136*G$5 -> 0.00095806869 | H136: =+$C136*H$5 -> 0.0017643832 | I136: =+$C136*I$5 -> 0.0026166932 | J136: =+$C136*J$5 -> 0.0035186472 | K136: =+$C136*K$5 -> 0.004469648 | ... AE136: =+$C136*AE$5 -> 0.20114201
A137: EN - Industrial combustion | B137: crops | C137: =+SAM!Q2 -> 0 | D137: =+$C137*D$6 -> 0 | E137: =+$C137*E$6 -> 0 | F137: =+$C137*F$6 -> 0 | G137: =+$C137*G$6 -> 0 | H137: =+$C137*H$6 -> 0 | I137: =+$C137*I$6 -> 0 | J137: =+$C137*J$6 -> 0 | K137: =+$C137*K$6 -> 0 | ... AE137: =+$C137*AE$6 -> 0
B138: forestry | C138: =+SAM!Q3 -> 0 | D138: =+$C138*D$6 -> 0 | E138: =+$C138*E$6 -> 0 | F138: =+$C138*F$6 -> 0 | G138: =+$C138*G$6 -> 0 | H138: =+$C138*H$6 -> 0 | I138: =+$C138*I$6 -> 0 | J138: =+$C138*J$6 -> 0 | K138: =+$C138*K$6 -> 0 | ... AE138: =+$C138*AE$6 -> 0
B139: livestock | C139: =+SAM!Q4 -> 0 | D139: =+$C139*D$6 -> 0 | E139: =+$C139*E$6 -> 0 | F139: =+$C139*F$6 -> 0 | G139: =+$C139*G$6 -> 0 | H139: =+$C139*H$6 -> 0 | I139: =+$C139*I$6 -> 0 | J139: =+$C139*J$6 -> 0 | K139: =+$C139*K$6 -> 0 | ... AE139: =+$C139*AE$6 -> 0
B140: fishery and aquaculture | C140: =+SAM!Q5 -> 0 | D140: =+$C140*D$6 -> 0 | E140: =+$C140*E$6 -> 0 | F140: =+$C140*F$6 -> 0 | G140: =+$C140*G$6 -> 0 | H140: =+$C140*H$6 -> 0 | I140: =+$C140*I$6 -> 0 | J140: =+$C140*J$6 -> 0 | K140: =+$C140*K$6 -> 0 | ... AE140: =+$C140*AE$6 -> 0
B141: Extractive activities | C141: =+SAM!Q6 -> 0 | D141: =+$C141*D$6 -> 0 | E141: =+$C141*E$6 -> 0 | F141: =+$C141*F$6 -> 0 | G141: =+$C141*G$6 -> 0 | H141: =+$C141*H$6 -> 0 | I141: =+$C141*I$6 -> 0 | J141: =+$C141*J$6 -> 0 | K141: =+$C141*K$6 -> 0 | ... AE141: =+$C141*AE$6 -> 0
B142: food manufacturing and beverage | C142: =+SAM!Q7 -> 0 | D142: =+$C142*D$6 -> 0 | E142: =+$C142*E$6 -> 0 | F142: =+$C142*F$6 -> 0 | G142: =+$C142*G$6 -> 0 | H142: =+$C142*H$6 -> 0 | I142: =+$C142*I$6 -> 0 | J142: =+$C142*J$6 -> 0 | K142: =+$C142*K$6 -> 0 | ... AE142: =+$C142*AE$6 -> 0
B143: textile manufacturing and clothes | C143: =+SAM!Q8 -> 0 | D143: =+$C143*D$6 -> 0 | E143: =+$C143*E$6 -> 0 | F143: =+$C143*F$6 -> 0 | G143: =+$C143*G$6 -> 0 | H143: =+$C143*H$6 -> 0 | I143: =+$C143*I$6 -> 0 | J143: =+$C143*J$6 -> 0 | K143: =+$C143*K$6 -> 0 | ... AE143: =+$C143*AE$6 -> 0
B144: Wood product manufacturing | C144: =+SAM!Q9 -> 0 | D144: =+$C144*D$6 -> 0 | E144: =+$C144*E$6 -> 0 | F144: =+$C144*F$6 -> 0 | G144: =+$C144*G$6 -> 0 | H144: =+$C144*H$6 -> 0 | I144: =+$C144*I$6 -> 0 | J144: =+$C144*J$6 -> 0 | K144: =+$C144*K$6 -> 0 | ... AE144: =+$C144*AE$6 -> 0
B145: coking and refining production | C145: =+SAM!Q10 -> 0 | D145: =+$C145*D$6 -> 0 | E145: =+$C145*E$6 -> 0 | F145: =+$C145*F$6 -> 0 | G145: =+$C145*G$6 -> 0 | H145: =+$C145*H$6 -> 0 | I145: =+$C145*I$6 -> 0 | J145: =+$C145*J$6 -> 0 | K145: =+$C145*K$6 -> 0 | ... AE145: =+$C145*AE$6 -> 0
B146: chemical products | C146: =+SAM!Q11 -> 0 | D146: =+$C146*D$6 -> 0 | E146: =+$C146*E$6 -> 0 | F146: =+$C146*F$6 -> 0 | G146: =+$C146*G$6 -> 0 | H146: =+$C146*H$6 -> 0 | I146: =+$C146*I$6 -> 0 | J146: =+$C146*J$6 -> 0 | K146: =+$C146*K$6 -> 0 | ... AE146: =+$C146*AE$6 -> 0
B147: pharmaceutical products | C147: =+SAM!Q12 -> 0 | D147: =+$C147*D$6 -> 0 | E147: =+$C147*E$6 -> 0 | F147: =+$C147*F$6 -> 0 | G147: =+$C147*G$6 -> 0 | H147: =+$C147*H$6 -> 0 | I147: =+$C147*I$6 -> 0 | J147: =+$C147*J$6 -> 0 | K147: =+$C147*K$6 -> 0 | ... AE147: =+$C147*AE$6 -> 0
B148: rubber manufacturing | C148: =+SAM!Q13 -> 0 | D148: =+$C148*D$6 -> 0 | E148: =+$C148*E$6 -> 0 | F148: =+$C148*F$6 -> 0 | G148: =+$C148*G$6 -> 0 | H148: =+$C148*H$6 -> 0 | I148: =+$C148*I$6 -> 0 | J148: =+$C148*J$6 -> 0 | K148: =+$C148*K$6 -> 0 | ... AE148: =+$C148*AE$6 -> 0
B149: metalwork manufacturing | C149: =+SAM!Q14 -> 0 | D149: =+$C149*D$6 -> 0 | E149: =+$C149*E$6 -> 0 | F149: =+$C149*F$6 -> 0 | G149: =+$C149*G$6 -> 0 | H149: =+$C149*H$6 -> 0 | I149: =+$C149*I$6 -> 0 | J149: =+$C149*J$6 -> 0 | K149: =+$C149*K$6 -> 0 | ... AE149: =+$C149*AE$6 -> 0
... B176: imports | C176: =+SAM!Q41 -> 0 | D176: =+$C176*D$6 -> 0 | E176: =+$C176*E$6 -> 0 | F176: =+$C176*F$6 -> 0 | G176: =+$C176*G$6 -> 0 | H176: =+$C176*H$6 -> 0 | I176: =+$C176*I$6 -> 0 | J176: =+$C176*J$6 -> 0 | K176: =+$C176*K$6 -> 0 | ... AE176: =+$C176*AE$6 -> 0
A177: IN - Industrial processes | B177: crops | C177: =+SAM!U2 -> 0 | D177: =+$C177*D$7 -> 0 | E177: =+$C177*E$7 -> 0 | F177: =+$C177*F$7 -> 0 | G177: =+$C177*G$7 -> 0 | H177: =+$C177*H$7 -> 0 | I177: =+$C177*I$7 -> 0 | J177: =+$C177*J$7 -> 0 | K177: =+$C177*K$7 -> 0 | ... AE177: =+$C177*AE$7 -> 0
B178: forestry | C178: =+SAM!U3 -> 0 | D178: =+$C178*D$7 -> 0 | E178: =+$C178*E$7 -> 0 | F178: =+$C178*F$7 -> 0 | G178: =+$C178*G$7 -> 0 | H178: =+$C178*H$7 -> 0 | I178: =+$C178*I$7 -> 0 | J178: =+$C178*J$7 -> 0 | K178: =+$C178*K$7 -> 0 | ... AE178: =+$C178*AE$7 -> 0
B179: livestock | C179: =+SAM!U4 -> 0 | D179: =+$C179*D$7 -> 0 | E179: =+$C179*E$7 -> 0 | F179: =+$C179*F$7 -> 0 | G179: =+$C179*G$7 -> 0 | H179: =+$C179*H$7 -> 0 | I179: =+$C179*I$7 -> 0 | J179: =+$C179*J$7 -> 0 | K179: =+$C179*K$7 -> 0 | ... AE179: =+$C179*AE$7 -> 0
B180: fishery and aquaculture | C180: =+SAM!U5 -> 0 | D180: =+$C180*D$7 -> 0 | E180: =+$C180*E$7 -> 0 | F180: =+$C180*F$7 -> 0 | G180: =+$C180*G$7 -> 0 | H180: =+$C180*H$7 -> 0 | I180: =+$C180*I$7 -> 0 | J180: =+$C180*J$7 -> 0 | K180: =+$C180*K$7 -> 0 | ... AE180: =+$C180*AE$7 -> 0
B181: Extractive activities | C181: =+SAM!U6 -> 0 | D181: =+$C181*D$7 -> 0 | E181: =+$C181*E$7 -> 0 | F181: =+$C181*F$7 -> 0 | G181: =+$C181*G$7 -> 0 | H181: =+$C181*H$7 -> 0 | I181: =+$C181*I$7 -> 0 | J181: =+$C181*J$7 -> 0 | K181: =+$C181*K$7 -> 0 | ... AE181: =+$C181*AE$7 -> 0
B182: food manufacturing and beverage | C182: =+SAM!U7 -> 0 | D182: =+$C182*D$7 -> 0 | E182: =+$C182*E$7 -> 0 | F182: =+$C182*F$7 -> 0 | G182: =+$C182*G$7 -> 0 | H182: =+$C182*H$7 -> 0 | I182: =+$C182*I$7 -> 0 | J182: =+$C182*J$7 -> 0 | K182: =+$C182*K$7 -> 0 | ... AE182: =+$C182*AE$7 -> 0
B183: textile manufacturing and clothes | C183: =+SAM!U8 -> 0 | D183: =+$C183*D$7 -> 0 | E183: =+$C183*E$7 -> 0 | F183: =+$C183*F$7 -> 0 | G183: =+$C183*G$7 -> 0 | H183: =+$C183*H$7 -> 0 | I183: =+$C183*I$7 -> 0 | J183: =+$C183*J$7 -> 0 | K183: =+$C183*K$7 -> 0 | ... AE183: =+$C183*AE$7 -> 0
B184: Wood product manufacturing | C184: =+SAM!U9 -> 0 | D184: =+$C184*D$7 -> 0 | E184: =+$C184*E$7 -> 0 | F184: =+$C184*F$7 -> 0 | G184: =+$C184*G$7 -> 0 | H184: =+$C184*H$7 -> 0 | I184: =+$C184*I$7 -> 0 | J184: =+$C184*J$7 -> 0 | K184: =+$C184*K$7 -> 0 | ... AE184: =+$C184*AE$7 -> 0
B185: coking and refining production | C185: =+SAM!U10 -> 0 | D185: =+$C185*D$7 -> 0 | E185: =+$C185*E$7 -> 0 | F185: =+$C185*F$7 -> 0 | G185: =+$C185*G$7 -> 0 | H185: =+$C185*H$7 -> 0 | I185: =+$C185*I$7 -> 0 | J185: =+$C185*J$7 -> 0 | K185: =+$C185*K$7 -> 0 | ... AE185: =+$C185*AE$7 -> 0
B186: chemical products | C186: =+SAM!U11 -> 0 | D186: =+$C186*D$7 -> 0 | E186: =+$C186*E$7 -> 0 | F186: =+$C186*F$7 -> 0 | G186: =+$C186*G$7 -> 0 | H186: =+$C186*H$7 -> 0 | I186: =+$C186*I$7 -> 0 | J186: =+$C186*J$7 -> 0 | K186: =+$C186*K$7 -> 0 | ... AE186: =+$C186*AE$7 -> 0
B187: pharmaceutical products | C187: =+SAM!U12 -> 0 | D187: =+$C187*D$7 -> 0 | E187: =+$C187*E$7 -> 0 | F187: =+$C187*F$7 -> 0 | G187: =+$C187*G$7 -> 0 | H187: =+$C187*H$7 -> 0 | I187: =+$C187*I$7 -> 0 | J187: =+$C187*J$7 -> 0 | K187: =+$C187*K$7 -> 0 | ... AE187: =+$C187*AE$7 -> 0
B188: rubber manufacturing | C188: =+SAM!U13 -> 0 | D188: =+$C188*D$7 -> 0 | E188: =+$C188*E$7 -> 0 | F188: =+$C188*F$7 -> 0 | G188: =+$C188*G$7 -> 0 | H188: =+$C188*H$7 -> 0 | I188: =+$C188*I$7 -> 0 | J188: =+$C188*J$7 -> 0 | K188: =+$C188*K$7 -> 0 | ... AE188: =+$C188*AE$7 -> 0
B189: metalwork manufacturing | C189: =+SAM!U14 -> 0 | D189: =+$C189*D$7 -> 0 | E189: =+$C189*E$7 -> 0 | F189: =+$C189*F$7 -> 0 | G189: =+$C189*G$7 -> 0 | H189: =+$C189*H$7 -> 0 | I189: =+$C189*I$7 -> 0 | J189: =+$C189*J$7 -> 0 | K189: =+$C189*K$7 -> 0 | ... AE189: =+$C189*AE$7 -> 0
... B216: imports | C216: =+SAM!U41 -> 0 | D216: =+$C216*D$7 -> 0 | E216: =+$C216*E$7 -> 0 | F216: =+$C216*F$7 -> 0 | G216: =+$C216*G$7 -> 0 | H216: =+$C216*H$7 -> 0 | I216: =+$C216*I$7 -> 0 | J216: =+$C216*J$7 -> 0 | K216: =+$C216*K$7 -> 0 | ... AE216: =+$C216*AE$7 -> 0
A217: Waste - Solid waste | B217: crops | C217: =+SAM!Y2 -> 0 | D217: =+$C217*D$8 -> 0 | E217: =+$C217*E$8 -> 0 | F217: =+$C217*F$8 -> 0 | G217: =+$C217*G$8 -> 0 | H217: =+$C217*H$8 -> 0 | I217: =+$C217*I$8 -> 0 | J217: =+$C217*J$8 -> 0 | K217: =+$C217*K$8 -> 0 | ... AE217: =+$C217*AE$8 -> 0
B218: forestry | C218: =+SAM!Y3 -> 0 | D218: =+$C218*D$8 -> 0 | E218: =+$C218*E$8 -> 0 | F218: =+$C218*F$8 -> 0 | G218: =+$C218*G$8 -> 0 | H218: =+$C218*H$8 -> 0 | I218: =+$C218*I$8 -> 0 | J218: =+$C218*J$8 -> 0 | K218: =+$C218*K$8 -> 0 | ... AE218: =+$C218*AE$8 -> 0
B219: livestock | C219: =+SAM!Y4 -> 0 | D219: =+$C219*D$8 -> 0 | E219: =+$C219*E$8 -> 0 | F219: =+$C219*F$8 -> 0 | G219: =+$C219*G$8 -> 0 | H219: =+$C219*H$8 -> 0 | I219: =+$C219*I$8 -> 0 | J219: =+$C219*J$8 -> 0 | K219: =+$C219*K$8 -> 0 | ... AE219: =+$C219*AE$8 -> 0
B220: fishery and aquaculture | C220: =+SAM!Y5 -> 0 | D220: =+$C220*D$8 -> 0 | E220: =+$C220*E$8 -> 0 | F220: =+$C220*F$8 -> 0 | G220: =+$C220*G$8 -> 0 | H220: =+$C220*H$8 -> 0 | I220: =+$C220*I$8 -> 0 | J220: =+$C220*J$8 -> 0 | K220: =+$C220*K$8 -> 0 | ... AE220: =+$C220*AE$8 -> 0
B221: Extractive activities | C221: =+SAM!Y6 -> 0 | D221: =+$C221*D$8 -> 0 | E221: =+$C221*E$8 -> 0 | F221: =+$C221*F$8 -> 0 | G221: =+$C221*G$8 -> 0 | H221: =+$C221*H$8 -> 0 | I221: =+$C221*I$8 -> 0 | J221: =+$C221*J$8 -> 0 | K221: =+$C221*K$8 -> 0 | ... AE221: =+$C221*AE$8 -> 0
B222: food manufacturing and beverage | C222: =+SAM!Y7 -> 0 | D222: =+$C222*D$8 -> 0 | E222: =+$C222*E$8 -> 0 | F222: =+$C222*F$8 -> 0 | G222: =+$C222*G$8 -> 0 | H222: =+$C222*H$8 -> 0 | I222: =+$C222*I$8 -> 0 | J222: =+$C222*J$8 -> 0 | K222: =+$C222*K$8 -> 0 | ... AE222: =+$C222*AE$8 -> 0
B223: textile manufacturing and clothes | C223: =+SAM!Y8 -> 0 | D223: =+$C223*D$8 -> 0 | E223: =+$C223*E$8 -> 0 | F223: =+$C223*F$8 -> 0 | G223: =+$C223*G$8 -> 0 | H223: =+$C223*H$8 -> 0 | I223: =+$C223*I$8 -> 0 | J223: =+$C223*J$8 -> 0 | K223: =+$C223*K$8 -> 0 | ... AE223: =+$C223*AE$8 -> 0
B224: Wood product manufacturing | C224: =+SAM!Y9 -> 0 | D224: =+$C224*D$8 -> 0 | E224: =+$C224*E$8 -> 0 | F224: =+$C224*F$8 -> 0 | G224: =+$C224*G$8 -> 0 | H224: =+$C224*H$8 -> 0 | I224: =+$C224*I$8 -> 0 | J224: =+$C224*J$8 -> 0 | K224: =+$C224*K$8 -> 0 | ... AE224: =+$C224*AE$8 -> 0
B225: coking and refining production | C225: =+SAM!Y10 -> 0 | D225: =+$C225*D$8 -> 0 | E225: =+$C225*E$8 -> 0 | F225: =+$C225*F$8 -> 0 | G225: =+$C225*G$8 -> 0 | H225: =+$C225*H$8 -> 0 | I225: =+$C225*I$8 -> 0 | J225: =+$C225*J$8 -> 0 | K225: =+$C225*K$8 -> 0 | ... AE225: =+$C225*AE$8 -> 0
B226: chemical products | C226: =+SAM!Y11 -> 0 | D226: =+$C226*D$8 -> 0 | E226: =+$C226*E$8 -> 0 | F226: =+$C226*F$8 -> 0 | G226: =+$C226*G$8 -> 0 | H226: =+$C226*H$8 -> 0 | I226: =+$C226*I$8 -> 0 | J226: =+$C226*J$8 -> 0 | K226: =+$C226*K$8 -> 0 | ... AE226: =+$C226*AE$8 -> 0
B227: pharmaceutical products | C227: =+SAM!Y12 -> 0 | D227: =+$C227*D$8 -> 0 | E227: =+$C227*E$8 -> 0 | F227: =+$C227*F$8 -> 0 | G227: =+$C227*G$8 -> 0 | H227: =+$C227*H$8 -> 0 | I227: =+$C227*I$8 -> 0 | J227: =+$C227*J$8 -> 0 | K227: =+$C227*K$8 -> 0 | ... AE227: =+$C227*AE$8 -> 0
B228: rubber manufacturing | C228: =+SAM!Y13 -> 0 | D228: =+$C228*D$8 -> 0 | E228: =+$C228*E$8 -> 0 | F228: =+$C228*F$8 -> 0 | G228: =+$C228*G$8 -> 0 | H228: =+$C228*H$8 -> 0 | I228: =+$C228*I$8 -> 0 | J228: =+$C228*J$8 -> 0 | K228: =+$C228*K$8 -> 0 | ... AE228: =+$C228*AE$8 -> 0
B229: metalwork manufacturing | C229: =+SAM!Y14 -> 0 | D229: =+$C229*D$8 -> 0 | E229: =+$C229*E$8 -> 0 | F229: =+$C229*F$8 -> 0 | G229: =+$C229*G$8 -> 0 | H229: =+$C229*H$8 -> 0 | I229: =+$C229*I$8 -> 0 | J229: =+$C229*J$8 -> 0 | K229: =+$C229*K$8 -> 0 | ... AE229: =+$C229*AE$8 -> 0
... B256: imports | C256: =+SAM!Y41 -> 0 | D256: =+$C256*D$8 -> 0 | E256: =+$C256*E$8 -> 0 | F256: =+$C256*F$8 -> 0 | G256: =+$C256*G$8 -> 0 | H256: =+$C256*H$8 -> 0 | I256: =+$C256*I$8 -> 0 | J256: =+$C256*J$8 -> 0 | K256: =+$C256*K$8 -> 0 | ... AE256: =+$C256*AE$8 -> 0
A257: Waste - Wastewater treatment (trww) | B257: crops | C257: =+SAM!AC2 -> 0 | D257: =+$C257*D$9 -> 0 | E257: =+$C257*E$9 -> 0 | F257: =+$C257*F$9 -> 0 | G257: =+$C257*G$9 -> 0 | H257: =+$C257*H$9 -> 0 | I257: =+$C257*I$9 -> 0 | J257: =+$C257*J$9 -> 0 | K257: =+$C257*K$9 -> 0 | ... AE257: =+$C257*AE$9 -> 0
B258: forestry | C258: =+SAM!AC3 -> 0 | D258: =+$C258*D$9 -> 0 | E258: =+$C258*E$9 -> 0 | F258: =+$C258*F$9 -> 0 | G258: =+$C258*G$9 -> 0 | H258: =+$C258*H$9 -> 0 | I258: =+$C258*I$9 -> 0 | J258: =+$C258*J$9 -> 0 | K258: =+$C258*K$9 -> 0 | ... AE258: =+$C258*AE$9 -> 0
...
